Workbook

Sheet Anleitung
A1: Buchhaltung Einzelfirma – Garage (Dornach SO)
A2: Arbeitsmappe für das Geschäftsjahr. Schweizer KMU-Kontenrahmen, MWST, AHV, Steuern.
A4: SO FUNKTIONIERT'S
A5: 1. Einstellungen | B5: Firma, Jahr, MWST-Methode (Saldo/Effektiv) und gelbe Annahmen prüfen (AK-Sätze, Steuersätze).
A6: 2. Kontenplan | B6: Eröffnungssalden per 1.1. aus der Schlussbilanz des Vorjahres in Spalte G eintragen. Kontrolle rechts muss 'ausgeglichen' zeigen.
A7: 3. Journal | B7: JEDEN Beleg erfassen: Datum, Beleg-Nr., Text, Soll-Konto, Haben-Konto, Betrag inkl. MWST, MWST-Code. Rest rechnet automatisch.
A8: 4. Nebenlisten | B8: Debitoren, Kreditoren, Fahrzeuge, Löhne, Lager, Anlagen führen – sie zeigen offene Posten, Margen und Abgleich zur Buchhaltung.
A9: 5. Auswerten | B9: Übersicht, Erfolgsrechnung, Bilanz, Margen, MWST, Steuern und Stundensatz aktualisieren sich automatisch.
A11: FARBEN
A12: Blaue Schrift | B12: Eingabefelder
A13: Gelb hinterlegt | B13: Wichtige Annahmen – prüfen und anpassen
A14: Grau hinterlegt | B14: Formeln – nicht überschreiben
A16: BUCHUNGSSATZ-SPICKZETTEL (Soll an Haben)
A17: Werkstattrechnung an Kunde | B17: 1100 an 3000 (Arbeit) / 3200 (Teile) · Code U81
A18: Barzahlung Kunde | B18: 1000 an 3000/3200/3210 · U81
A19: Kunde zahlt Rechnung | B19: 1020 an 1100 · –
A20: Einkauf Ersatzteile auf Rechnung | B20: 4000 an 2000 · V81
A21: Lieferantenrechnung bezahlen | B21: 2000 an 1020 · –
A22: Occasion ankaufen (von Privat) | B22: 4200 an 1020 · – (von Händler mit MWST: V81)
A23: Occasion verkaufen | B23: 1020 an 3400 · U81
A24: Fremdarbeit (Carrosserie/Lack) | B24: 4400 an 2000 · V81
A25: Miete Werkstatt | B25: 6000 an 1020 · – (ausser Vermieter optiert: V81)
A26: Strom, Telefon, Software, Werbung | B26: 6400 / 6500 / 6600 an 1020 · V81
A27: Versicherungsprämie | B27: 6300 an 1020 · – (keine MWST)
A28: Investition (Maschine, Werkzeug) | B28: 1500 / 1510 an 1020 · VI81 + Blatt Anlagen ergänzen
... A35: Debitorenverlust | B35: 3805 an 1100 · – (betrag inkl. MWST)
A37: AUTOMATISCH (nicht selbst buchen)
A38: Abschreibungen | B38: Aus Blatt Anlagen → Konto 6800 und Anlagekonten
A39: MWST Saldomethode | B39: Aus Blatt MWST → Konto 3809 (Ertragsminderung) und 2200
A40: MWST effektiv | B40: Aus MWST-Code: Netto auf Ertrag/Aufwand, MWST auf 2200 bzw. 1170/1171
A42: JAHRESABSCHLUSS – CHECKLISTE
A43: ☐ Kasse | B43: Bargeld zählen = Saldo Konto 1000 (Blatt Kontoauszug)
A44: ☐ Bank | B44: Saldo 1020 = Bankauszug 31.12.
A45: ☐ Debitoren / Kreditoren | B45: Listen vollständig, Abgleich 'stimmt'
A46: ☐ Inventur | B46: Blatt Lager ausfüllen, Bestandesänderung buchen; unverkaufte Fahrzeuge auf 1210
A47: ☐ Abgrenzungen | B47: Im Voraus bezahlte / noch nicht erhaltene Rechnungen (1300 / 2300)
A48: ☐ Anlagen | B48: Zugänge eingetragen, Abschreibungssätze ok
A49: ☐ MWST | B49: Umsatzabstimmung, letzte Abrechnung
A50: ☐ Privatanteile | B50: Auto, Telefon etc. im Blatt Steuern
A51: ☐ Bilanz ausgeglichen | B51: Blatt Bilanz Kontrolle = 0
A53: WICHTIG
A54: Haftung | B54: Dies ist ein Hilfsmittel, keine Steuer- oder Rechtsberatung. Annahmen (gelb) prüfen; im Zweifel Treuhänder beiziehen.
A55: Beispieldaten | B55: Alle Zeilen mit 'BEISPIEL' sowie Beispiel-Einträge in den Nebenlisten löschen, bevor du startest. Eröffnungssalden ersetzen.
A56: Buchführungspflicht | B56: Einzelfirma mit Umsatz unter CHF 500'000: vereinfachte Buchführung ('Milchbüchlein') erlaubt; diese doppelte Buchhaltung erfüllt mehr.

Sheet Übersicht
A1: =Einstellungen!$B$5&" – Übersicht Geschäftsjahr "&Einstellungen!$B$7 -> Garage Muster, Dornach – Übersicht Geschäftsjahr 2026
A2: Alle Werte automatisch. Grün = gut, Rot = Handlungsbedarf.
A3: =Bilanz!F29 -> Bilanz ausgeglichen ✓
A5: Kennzahl | B5: Wert | C5: Erklärung | E5: Monat | F5: Ertrag netto | G5: Aufwand | H5: Gewinn | I5: Gewinn kumuliert
A6: Nettoerlös (Umsatz) | B6: =Erfolgsrechnung!C17 -> 18332.71 | C6: Alle Erträge nach Rabatten und MWST | E6: Jan | F6: =SUMIFS(Journal!$N$5:$N$1504,Journal!$U$5:$U$1504,"Ertrag",Journal!$O$5:$O$1504,1)-SUMIFS(Journal!$M$5:$M$1504,Journal!$T$5:$T$1504,"Ertrag",Journal!$O$5:$O$1504,1)-IF(MWST!$C$5,Einstellungen!$B$12*(SUMIFS(Journal!$F$5:$F$1504,Journal!$R$5:$R$1504,1,Journal!$O$5:$O$1504,1)-SUMIFS(Journal!$F$5:$F$1504,Journal!$S$5:$S$1504,1,Journal!$O$5:$O$1504,1))+Einstellungen!$B$13*(SUMIFS(Journal!$F$5:$F$1504,Journal!$R$5:$R$1504,2,Journal!$O$5:$O$1504,1)-SUMIFS(Journal!$F$5:$F$1504,Journal!$S$5:$S$1504,2,Journal!$O$5:$O$1504,1)),0) -> 2528.111 | G6: =SUMIFS(Journal!$M$5:$M$1504,Journal!$T$5:$T$1504,"Aufwand",Journal!$O$5:$O$1504,1)-SUMIFS(Journal!$N$5:$N$1504,Journal!$U$5:$U$1504,"Aufwand",Journal!$O$5:$O$1504,1)+Anlagen!$J$3/12 -> 13560.533 | H6: =F6-G6 -> -11032.422 | I6: =H6 -> -11032.422
A7: Bruttogewinn | B7: =Erfolgsrechnung!C29 -> 5035.51 | C7: Umsatz minus Material/Waren/Fremdarbeiten | E7: Feb | F7: =SUMIFS(Journal!$N$5:$N$1504,Journal!$U$5:$U$1504,"Ertrag",Journal!$O$5:$O$1504,2)-SUMIFS(Journal!$M$5:$M$1504,Journal!$T$5:$T$1504,"Ertrag",Journal!$O$5:$O$1504,2)-IF(MWST!$C$5,Einstellungen!$B$12*(SUMIFS(Journal!$F$5:$F$1504,Journal!$R$5:$R$1504,1,Journal!$O$5:$O$1504,2)-SUMIFS(Journal!$F$5:$F$1504,Journal!$S$5:$S$1504,1,Journal!$O$5:$O$1504,2))+Einstellungen!$B$13*(SUMIFS(Journal!$F$5:$F$1504,Journal!$R$5:$R$1504,2,Journal!$O$5:$O$1504,2)-SUMIFS(Journal!$F$5:$F$1504,Journal!$S$5:$S$1504,2,Journal!$O$5:$O$1504,2)),0) -> 0 | G7: =SUMIFS(Journal!$M$5:$M$1504,Journal!$T$5:$T$1504,"Aufwand",Journal!$O$5:$O$1504,2)-SUMIFS(Journal!$N$5:$N$1504,Journal!$U$5:$U$1504,"Aufwand",Journal!$O$5:$O$1504,2)+Anlagen!$J$3/12 -> 17669.933 | H7: =F7-G7 -> -17669.933 | I7: =I6+H7 -> -28702.356
A8: Bruttomarge | B8: =IF(B6=0,"",B7/B6) -> 0.27467352 | C8: Bruttogewinn in % vom Umsatz | E8: Mär | F8: =SUMIFS(Journal!$N$5:$N$1504,Journal!$U$5:$U$1504,"Ertrag",Journal!$O$5:$O$1504,3)-SUMIFS(Journal!$M$5:$M$1504,Journal!$T$5:$T$1504,"Ertrag",Journal!$O$5:$O$1504,3)-IF(MWST!$C$5,Einstellungen!$B$12*(SUMIFS(Journal!$F$5:$F$1504,Journal!$R$5:$R$1504,1,Journal!$O$5:$O$1504,3)-SUMIFS(Journal!$F$5:$F$1504,Journal!$S$5:$S$1504,1,Journal!$O$5:$O$1504,3))+Einstellungen!$B$13*(SUMIFS(Journal!$F$5:$F$1504,Journal!$R$5:$R$1504,2,Journal!$O$5:$O$1504,3)-SUMIFS(Journal!$F$5:$F$1504,Journal!$S$5:$S$1504,2,Journal!$O$5:$O$1504,3)),0) -> 15804.6 | G8: =SUMIFS(Journal!$M$5:$M$1504,Journal!$T$5:$T$1504,"Aufwand",Journal!$O$5:$O$1504,3)-SUMIFS(Journal!$N$5:$N$1504,Journal!$U$5:$U$1504,"Aufwand",Journal!$O$5:$O$1504,3)+Anlagen!$J$3/12 -> 3408.3333 | H8: =F8-G8 -> 12396.267 | I8: =I7+H8 -> -16306.089
A9: Personalaufwand | B9: =-Erfolgsrechnung!C36 -> 5980 | C9: Löhne + Sozialleistungen Mitarbeitende | E9: Apr | F9: =SUMIFS(Journal!$N$5:$N$1504,Journal!$U$5:$U$1504,"Ertrag",Journal!$O$5:$O$1504,4)-SUMIFS(Journal!$M$5:$M$1504,Journal!$T$5:$T$1504,"Ertrag",Journal!$O$5:$O$1504,4)-IF(MWST!$C$5,Einstellungen!$B$12*(SUMIFS(Journal!$F$5:$F$1504,Journal!$R$5:$R$1504,1,Journal!$O$5:$O$1504,4)-SUMIFS(Journal!$F$5:$F$1504,Journal!$S$5:$S$1504,1,Journal!$O$5:$O$1504,4))+Einstellungen!$B$13*(SUMIFS(Journal!$F$5:$F$1504,Journal!$R$5:$R$1504,2,Journal!$O$5:$O$1504,4)-SUMIFS(Journal!$F$5:$F$1504,Journal!$S$5:$S$1504,2,Journal!$O$5:$O$1504,4)),0) -> 0 | G9: =SUMIFS(Journal!$M$5:$M$1504,Journal!$T$5:$T$1504,"Aufwand",Journal!$O$5:$O$1504,4)-SUMIFS(Journal!$N$5:$N$1504,Journal!$U$5:$U$1504,"Aufwand",Journal!$O$5:$O$1504,4)+Anlagen!$J$3/12 -> 2783.3333 | H9: =F9-G9 -> -2783.3333 | I9: =I8+H9 -> -19089.422
A10: EBITDA | B10: =Erfolgsrechnung!C50 -> -7871.09 | C10: Ergebnis vor Abschreibungen | E10: Mai | F10: =SUMIFS(Journal!$N$5:$N$1504,Journal!$U$5:$U$1504,"Ertrag",Journal!$O$5:$O$1504,5)-SUMIFS(Journal!$M$5:$M$1504,Journal!$T$5:$T$1504,"Ertrag",Journal!$O$5:$O$1504,5)-IF(MWST!$C$5,Einstellungen!$B$12*(SUMIFS(Journal!$F$5:$F$1504,Journal!$R$5:$R$1504,1,Journal!$O$5:$O$1504,5)-SUMIFS(Journal!$F$5:$F$1504,Journal!$S$5:$S$1504,1,Journal!$O$5:$O$1504,5))+Einstellungen!$B$13*(SUMIFS(Journal!$F$5:$F$1504,Journal!$R$5:$R$1504,2,Journal!$O$5:$O$1504,5)-SUMIFS(Journal!$F$5:$F$1504,Journal!$S$5:$S$1504,2,Journal!$O$5:$O$1504,5)),0) -> 0 | G10: =SUMIFS(Journal!$M$5:$M$1504,Journal!$T$5:$T$1504,"Aufwand",Journal!$O$5:$O$1504,5)-SUMIFS(Journal!$N$5:$N$1504,Journal!$U$5:$U$1504,"Aufwand",Journal!$O$5:$O$1504,5)+Anlagen!$J$3/12 -> 2783.3333 | H10: =F10-G10 -> -2783.3333 | I10: =I9+H10 -> -21872.756
A11: Jahresgewinn (= dein Einkommen) | B11: =Erfolgsrechnung!$C$72 -> -41356.09 | C11: Vor AHV und Steuern des Inhabers | E11: Jun | F11: =SUMIFS(Journal!$N$5:$N$1504,Journal!$U$5:$U$1504,"Ertrag",Journal!$O$5:$O$1504,6)-SUMIFS(Journal!$M$5:$M$1504,Journal!$T$5:$T$1504,"Ertrag",Journal!$O$5:$O$1504,6)-IF(MWST!$C$5,Einstellungen!$B$12*(SUMIFS(Journal!$F$5:$F$1504,Journal!$R$5:$R$1504,1,Journal!$O$5:$O$1504,6)-SUMIFS(Journal!$F$5:$F$1504,Journal!$S$5:$S$1504,1,Journal!$O$5:$O$1504,6))+Einstellungen!$B$13*(SUMIFS(Journal!$F$5:$F$1504,Journal!$R$5:$R$1504,2,Journal!$O$5:$O$1504,6)-SUMIFS(Journal!$F$5:$F$1504,Journal!$S$5:$S$1504,2,Journal!$O$5:$O$1504,6)),0) -> 0 | G11: =SUMIFS(Journal!$M$5:$M$1504,Journal!$T$5:$T$1504,"Aufwand",Journal!$O$5:$O$1504,6)-SUMIFS(Journal!$N$5:$N$1504,Journal!$U$5:$U$1504,"Aufwand",Journal!$O$5:$O$1504,6)+Anlagen!$J$3/12 -> 2783.3333 | H11: =F11-G11 -> -2783.3333 | I11: =I10+H11 -> -24656.089
A12: Umsatzrendite | B12: =IF(B6=0,"",B11/B6) -> -2.2558634 | C12: Gewinn in % vom Umsatz | E12: Jul | F12: =SUMIFS(Journal!$N$5:$N$1504,Journal!$U$5:$U$1504,"Ertrag",Journal!$O$5:$O$1504,7)-SUMIFS(Journal!$M$5:$M$1504,Journal!$T$5:$T$1504,"Ertrag",Journal!$O$5:$O$1504,7)-IF(MWST!$C$5,Einstellungen!$B$12*(SUMIFS(Journal!$F$5:$F$1504,Journal!$R$5:$R$1504,1,Journal!$O$5:$O$1504,7)-SUMIFS(Journal!$F$5:$F$1504,Journal!$S$5:$S$1504,1,Journal!$O$5:$O$1504,7))+Einstellungen!$B$13*(SUMIFS(Journal!$F$5:$F$1504,Journal!$R$5:$R$1504,2,Journal!$O$5:$O$1504,7)-SUMIFS(Journal!$F$5:$F$1504,Journal!$S$5:$S$1504,2,Journal!$O$5:$O$1504,7)),0) -> 0 | G12: =SUMIFS(Journal!$M$5:$M$1504,Journal!$T$5:$T$1504,"Aufwand",Journal!$O$5:$O$1504,7)-SUMIFS(Journal!$N$5:$N$1504,Journal!$U$5:$U$1504,"Aufwand",Journal!$O$5:$O$1504,7)+Anlagen!$J$3/12 -> 2783.3333 | H12: =F12-G12 -> -2783.3333 | I12: =I11+H12 -> -27439.422
A13: Liquide Mittel (Kasse + Bank) | B13: =SUMIF(Kontenplan!$A$5:$A$90,1000,Kontenplan!$K$5:$K$90)+SUMIF(Kontenplan!$A$5:$A$90,1020,Kontenplan!$K$5:$K$90) -> 37844.7 | E13: Aug | F13: =SUMIFS(Journal!$N$5:$N$1504,Journal!$U$5:$U$1504,"Ertrag",Journal!$O$5:$O$1504,8)-SUMIFS(Journal!$M$5:$M$1504,Journal!$T$5:$T$1504,"Ertrag",Journal!$O$5:$O$1504,8)-IF(MWST!$C$5,Einstellungen!$B$12*(SUMIFS(Journal!$F$5:$F$1504,Journal!$R$5:$R$1504,1,Journal!$O$5:$O$1504,8)-SUMIFS(Journal!$F$5:$F$1504,Journal!$S$5:$S$1504,1,Journal!$O$5:$O$1504,8))+Einstellungen!$B$13*(SUMIFS(Journal!$F$5:$F$1504,Journal!$R$5:$R$1504,2,Journal!$O$5:$O$1504,8)-SUMIFS(Journal!$F$5:$F$1504,Journal!$S$5:$S$1504,2,Journal!$O$5:$O$1504,8)),0) -> 0 | G13: =SUMIFS(Journal!$M$5:$M$1504,Journal!$T$5:$T$1504,"Aufwand",Journal!$O$5:$O$1504,8)-SUMIFS(Journal!$N$5:$N$1504,Journal!$U$5:$U$1504,"Aufwand",Journal!$O$5:$O$1504,8)+Anlagen!$J$3/12 -> 2783.3333 | H13: =F13-G13 -> -2783.3333 | I13: =I12+H13 -> -30222.756
A14: Offene Debitoren | B14: =SUMIF(Kontenplan!$A$5:$A$90,1100,Kontenplan!$K$5:$K$90) -> 0 | C14: Überfällige siehe Blatt Debitoren | E14: Sep | F14: =SUMIFS(Journal!$N$5:$N$1504,Journal!$U$5:$U$1504,"Ertrag",Journal!$O$5:$O$1504,9)-SUMIFS(Journal!$M$5:$M$1504,Journal!$T$5:$T$1504,"Ertrag",Journal!$O$5:$O$1504,9)-IF(MWST!$C$5,Einstellungen!$B$12*(SUMIFS(Journal!$F$5:$F$1504,Journal!$R$5:$R$1504,1,Journal!$O$5:$O$1504,9)-SUMIFS(Journal!$F$5:$F$1504,Journal!$S$5:$S$1504,1,Journal!$O$5:$O$1504,9))+Einstellungen!$B$13*(SUMIFS(Journal!$F$5:$F$1504,Journal!$R$5:$R$1504,2,Journal!$O$5:$O$1504,9)-SUMIFS(Journal!$F$5:$F$1504,Journal!$S$5:$S$1504,2,Journal!$O$5:$O$1504,9)),0) -> 0 | G14: =SUMIFS(Journal!$M$5:$M$1504,Journal!$T$5:$T$1504,"Aufwand",Journal!$O$5:$O$1504,9)-SUMIFS(Journal!$N$5:$N$1504,Journal!$U$5:$U$1504,"Aufwand",Journal!$O$5:$O$1504,9)+Anlagen!$J$3/12 -> 2783.3333 | H14: =F14-G14 -> -2783.3333 | I14: =I13+H14 -> -33006.089
A15: Offene Kreditoren | B15: =SUMIF(Kontenplan!$A$5:$A$90,2000,Kontenplan!$K$5:$K$90) -> 1297.2 | E15: Okt | F15: =SUMIFS(Journal!$N$5:$N$1504,Journal!$U$5:$U$1504,"Ertrag",Journal!$O$5:$O$1504,10)-SUMIFS(Journal!$M$5:$M$1504,Journal!$T$5:$T$1504,"Ertrag",Journal!$O$5:$O$1504,10)-IF(MWST!$C$5,Einstellungen!$B$12*(SUMIFS(Journal!$F$5:$F$1504,Journal!$R$5:$R$1504,1,Journal!$O$5:$O$1504,10)-SUMIFS(Journal!$F$5:$F$1504,Journal!$S$5:$S$1504,1,Journal!$O$5:$O$1504,10))+Einstellungen!$B$13*(SUMIFS(Journal!$F$5:$F$1504,Journal!$R$5:$R$1504,2,Journal!$O$5:$O$1504,10)-SUMIFS(Journal!$F$5:$F$1504,Journal!$S$5:$S$1504,2,Journal!$O$5:$O$1504,10)),0) -> 0 | G15: =SUMIFS(Journal!$M$5:$M$1504,Journal!$T$5:$T$1504,"Aufwand",Journal!$O$5:$O$1504,10)-SUMIFS(Journal!$N$5:$N$1504,Journal!$U$5:$U$1504,"Aufwand",Journal!$O$5:$O$1504,10)+Anlagen!$J$3/12 -> 2783.3333 | H15: =F15-G15 -> -2783.3333 | I15: =I14+H15 -> -35789.422
A16: Liquiditätsgrad 2 | B16: =IF(Bilanz!G11=0,"",(B13+B14)/Bilanz!G11) -> 13.512152 | C16: Ziel > 100 % | E16: Nov | F16: =SUMIFS(Journal!$N$5:$N$1504,Journal!$U$5:$U$1504,"Ertrag",Journal!$O$5:$O$1504,11)-SUMIFS(Journal!$M$5:$M$1504,Journal!$T$5:$T$1504,"Ertrag",Journal!$O$5:$O$1504,11)-IF(MWST!$C$5,Einstellungen!$B$12*(SUMIFS(Journal!$F$5:$F$1504,Journal!$R$5:$R$1504,1,Journal!$O$5:$O$1504,11)-SUMIFS(Journal!$F$5:$F$1504,Journal!$S$5:$S$1504,1,Journal!$O$5:$O$1504,11))+Einstellungen!$B$13*(SUMIFS(Journal!$F$5:$F$1504,Journal!$R$5:$R$1504,2,Journal!$O$5:$O$1504,11)-SUMIFS(Journal!$F$5:$F$1504,Journal!$S$5:$S$1504,2,Journal!$O$5:$O$1504,11)),0) -> 0 | G16: =SUMIFS(Journal!$M$5:$M$1504,Journal!$T$5:$T$1504,"Aufwand",Journal!$O$5:$O$1504,11)-SUMIFS(Journal!$N$5:$N$1504,Journal!$U$5:$U$1504,"Aufwand",Journal!$O$5:$O$1504,11)+Anlagen!$J$3/12 -> 2783.3333 | H16: =F16-G16 -> -2783.3333 | I16: =I15+H16 -> -38572.756
A17: Eigenkapitalquote | B17: =IF(Bilanz!C27=0,"",Bilanz!G25/Bilanz!C27) -> 0.64166857 | C17: Eigenkapital / Bilanzsumme | E17: Dez | F17: =SUMIFS(Journal!$N$5:$N$1504,Journal!$U$5:$U$1504,"Ertrag",Journal!$O$5:$O$1504,12)-SUMIFS(Journal!$M$5:$M$1504,Journal!$T$5:$T$1504,"Ertrag",Journal!$O$5:$O$1504,12)-IF(MWST!$C$5,Einstellungen!$B$12*(SUMIFS(Journal!$F$5:$F$1504,Journal!$R$5:$R$1504,1,Journal!$O$5:$O$1504,12)-SUMIFS(Journal!$F$5:$F$1504,Journal!$S$5:$S$1504,1,Journal!$O$5:$O$1504,12))+Einstellungen!$B$13*(SUMIFS(Journal!$F$5:$F$1504,Journal!$R$5:$R$1504,2,Journal!$O$5:$O$1504,12)-SUMIFS(Journal!$F$5:$F$1504,Journal!$S$5:$S$1504,2,Journal!$O$5:$O$1504,12)),0) -> 0 | G17: =SUMIFS(Journal!$M$5:$M$1504,Journal!$T$5:$T$1504,"Aufwand",Journal!$O$5:$O$1504,12)-SUMIFS(Journal!$N$5:$N$1504,Journal!$U$5:$U$1504,"Aufwand",Journal!$O$5:$O$1504,12)+Anlagen!$J$3/12 -> 2783.3333 | H17: =F17-G17 -> -2783.3333 | I17: =I16+H17 -> -41356.089
A18: MWST noch offen | B18: =MWST!$B$29 -> 173.59 | C18: Zurücklegen – gehört der ESTV | E18: Total | F18: =SUM(F6:F17) -> 18332.711 | G18: =SUM(G6:G17) -> 59688.8 | H18: =SUM(H6:H17) -> -41356.089
A19: AHV + Steuern Inhaber (geschätzt) | B19: =Steuern!$C$21+Steuern!$C$42 -> 546 | C19: Siehe Blatt Steuern | E19: Abstimmung mit ER | H19: =IF(ABS(H18-Erfolgsrechnung!$C$72)<1,"✓","Differenz (Buchungen ausserhalb Jahr?)") -> ✓
A20: Rückstellung pro Monat empfohlen | B20: =Steuern!$C$53 -> 45.5 | C20: Monatlich auf separates Konto
A21: Frei verfügbar pro Monat (Schätzung) | B21: =Steuern!$C$51 -> -3491.8408 | C21: Nach AHV, Steuern und 3a
A22: Bisherige Privatbezüge | B22: =Steuern!$C$52 -> 4000
A23: Fahrzeuge an Lager | B23: =Fahrzeuge!$D$3 -> 0 | C23: Länger als 90 Tage: Preis prüfen
A24: Kostendeckender Stundensatz | B24: =Stundensatz!$C$29 -> 98.811664 | C24: exkl. MWST
A25: Journal-Zeilen mit Fehlern | B25: =COUNTIF(Journal!$V$5:$V$1504,"Konto prüfen!")+COUNTIF(Journal!$V$5:$V$1504,"Datum fehlt")+COUNTIF(Journal!$V$5:$V$1504,"anderes Jahr!")+COUNTIF(Journal!$V$5:$V$1504,"MWST-Code fehlt") -> 0 | C25: Muss 0 sein

Sheet Einstellungen
A1: Einstellungen & Sätze 2026
A2: Gelbe Felder anpassen. Blaue Schrift = Eingabe. Quellen in Spalte C.
A4: Parameter | B4: Wert | C4: Quelle / Hinweis | E4: MWST-Code | F4: Beschreibung | G4: Satz | H4: Art
A5: Firma | B5: Garage Muster, Dornach | C5: Eigene Angabe | E5: U81 | F5: Umsatz Normalsatz 8,1 % | G5: =Einstellungen!$B$10 -> 0.081 | H5: U
A6: Inhaber/in | B6: Vorname Name | C6: Eigene Angabe | E6: U26 | F6: Umsatz reduziert 2,6 % | G6: =Einstellungen!$B$11 -> 0.026 | H6: U
A7: Geschäftsjahr | B7: 2026 | E7: U0 | F7: Umsatz steuerfrei / Export 0 % | G7: 0 | H7: U
A8: MWST-pflichtig? (Ja/Nein) | B8: Ja | C8: Pflicht ab CHF 100'000 Umsatz/Jahr | E8: V81 | F8: Vorsteuer Material/DL 8,1 % | G8: =Einstellungen!$B$10 -> 0.081 | H8: V
A9: MWST-Methode (Saldo/Effektiv) | B9: Saldo | C9: Saldo: halbjährlich, pauschal. Effektiv: quartalsweise mit Vorsteuerabzug | E9: V26 | F9: Vorsteuer Material 2,6 % | G9: =Einstellungen!$B$11 -> 0.026 | H9: V
A10: MWST Normalsatz | B10: 0.081 | C10: ESTV, gültig seit 1.1.2024, 2026 unverändert | E10: VI81 | F10: Vorsteuer Investitionen 8,1 % | G10: =Einstellungen!$B$10 -> 0.081 | H10: V
A11: MWST reduzierter Satz | B11: 0.026 | C11: ESTV | E11: - | F11: ohne MWST (Lohn, Miete, Privat, Bank) | G11: 0 | H11: -
A12: Saldosteuersatz 1: Auto-Reparaturwerkstätte | B12: 0.03 | C12: ESTV-Verordnung Saldosteuersätze: Auto-Reparaturwerkstätte 3,0 % – bewilligten Satz aus ESTV-Verfügung eintragen
A13: Saldosteuersatz 2: Occasionen-/Neuwagenhandel | B13: 0.006 | C13: ESTV: Auto-Occasionen bis 3,5 t / Neuwagen Handel 0,6 %
E14: Anlagekategorie | F14: Satz degressiv | G14: Quelle
A15: AHV/IV/EO Satz Selbständige (max.) | B15: 0.1 | C15: BSV 2026: 8,1 % AHV + 1,4 % IV + 0,5 % EO = 10 % | E15: Maschinen & Apparate | F15: 0.3 | G15: ESTV Merkblatt A 1995 (Geschäftsbetriebe)
A16: Sinkende Skala: obere Grenze | B16: 60500 | C16: BSV 2026 | E16: Werkzeuge | F16: 0.45 | G16: ESTV Merkblatt A 1995 (Geschäftsbetriebe)
A17: Sinkende Skala: untere Grenze | B17: 10100 | C17: BSV 2026 | E17: Fahrzeuge | F17: 0.4 | G17: ESTV Merkblatt A 1995 (Geschäftsbetriebe)
A18: Sinkende Skala: tiefster Satz | B18: 0.05371 | C18: BSV 2026 | E18: Mobiliar & Einrichtungen | F18: 0.25 | G18: ESTV Merkblatt A 1995 (Geschäftsbetriebe)
A19: AHV-Mindestbeitrag | B19: 530 | C19: BSV 2026 | E19: EDV / Software | F19: 0.4 | G19: ESTV Merkblatt A 1995 (Geschäftsbetriebe)
A20: Verwaltungskosten Ausgleichskasse (% der Beiträge) | B20: 0.03 | C20: ANNAHME – Satz auf Rechnung der AK Solothurn prüfen | E20: Geschäftsliegenschaft | F20: 0.04 | G20: ESTV Merkblatt A 1995 (Geschäftsbetriebe)
A21: FAK-Beitrag Selbständige (% vom Einkommen) | B21: 0.012 | C21: ANNAHME – Satz bei der AK Solothurn prüfen
A22: Eigenkapitalzins-Abzug AHV | B22: 0.015 | C22: ANNAHME – Zinssatz gemäss AK (jährlich festgelegt)
A24: Steuerfuss Kanton Solothurn (nat. Personen) | B24: 1.04 | C24: Kantonsratsbeschluss Voranschlag 2026: 104 %
A25: Steuerfuss Gemeinde Dornach | B25: 0.92 | C25: Regierungsratsbeschluss 30.6.2026: 92 %
A26: Kirchensteuerfuss (0 wenn keine) | B26: 0 | C26: Dornach 2025: röm.-kath. 17 %, ref. 15 % – eintragen falls Mitglied
A27: Einfache Staatssteuer: Ø-Satz auf steuerb. Eink. | B27: 0.07 | C27: ANNAHME – mit Steuerrechner SO/ESTV ersetzen (abhängig von Einkommen, Zivilstand)
A28: Direkte Bundessteuer: Ø-Satz | B28: 0.02 | C28: ANNAHME – mit ESTV-Steuerrechner ersetzen
A29: Säule 3a Maximum ohne Pensionskasse | B29: 36288 | C29: 2026: 20 % des Erwerbseinkommens, max. CHF 36'288
A30: Privatanteil Geschäftsauto pro Monat | B30: 0.009 | C30: ESTV-Pauschale 0,9 % des Kaufpreises (exkl. MWST) pro Monat
A32: Löhne: AHV/IV/EO Arbeitnehmer | B32: 0.053 | C32: BSV 2026: 5,3 % AN + 5,3 % AG
A33: Löhne: AHV/IV/EO Arbeitgeber | B33: 0.053 | C33: BSV 2026
A34: Löhne: ALV je AN/AG | B34: 0.011 | C34: BSV 2026: 1,1 % bis CHF 148'200
... A40: Standard-Zahlungsfrist Kunden (Tage) | B40: 30 | C40: Eigene Angabe

Sheet Kontenplan
A1: Kontenplan (nach KMU-Kontenrahmen, angepasst für Garagen)
A2: Eröffnungssalden per 1.1. in Spalte G eintragen (blau). Neue Konten unten anfügen (bis Zeile 90) – Typ, Gruppe und Bereich ausfüllen.
A4: Konto | B4: Bezeichnung | C4: Typ | D4: Gruppe | E4: Bereich | F4: Saldo-satz-Gruppe | G4: Eröffnung 1.1. | H4: Soll | I4: Haben | J4: Automatisch (Abschluss) | K4: Saldo | M4: Kontrolle Eröffnung
A5: 1000 | B5: Kasse | C5: Aktiv | D5: UV | G5: 2000 | H5: =IF($A5="",0,SUMIFS(Journal!$M$5:$M$1504,Journal!$D$5:$D$1504,$A5)+IF($A5=1170,SUMIFS(Journal!$K$5:$K$1504,Journal!$J$5:$J$1504,"V",Journal!$G$5:$G$1504,"<>VI81"),0)+IF($A5=1171,SUMIFS(Journal!$K$5:$K$1504,Journal!$J$5:$J$1504,"V",Journal!$G$5:$G$1504,"VI81"),0)) -> 120 | I5: =IF($A5="",0,SUMIFS(Journal!$N$5:$N$1504,Journal!$E$5:$E$1504,$A5)+IF($A5=2200,SUMIFS(Journal!$K$5:$K$1504,Journal!$J$5:$J$1504,"U"),0)) -> 0 | J5: =IF($A5="",0,IF($A5=3809,-MWST!$H$13,IF($A5=2200,MWST!$H$13,IF($A5=6800,Anlagen!$J$3,-SUMIF(Anlagen!$B$6:$B$105,$A5,Anlagen!$J$6:$J$105))))) -> 0 | K5: =IF($A5="","",IF(OR($C5="Aktiv",$C5="Aufwand"),$G5+$H5-$I5+$J5,$G5+$I5-$H5+$J5)) -> 2120 | M5: Aktiven | N5: =SUMIFS(Kontenplan!$G$5:$G$90,Kontenplan!$C$5:$C$90,"Aktiv") -> 162000
A6: 1020 | B6: Bank | C6: Aktiv | D6: UV | G6: 45000 | H6: =IF($A6="",0,SUMIFS(Journal!$M$5:$M$1504,Journal!$D$5:$D$1504,$A6)+IF($A6=1170,SUMIFS(Journal!$K$5:$K$1504,Journal!$J$5:$J$1504,"V",Journal!$G$5:$G$1504,"<>VI81"),0)+IF($A6=1171,SUMIFS(Journal!$K$5:$K$1504,Journal!$J$5:$J$1504,"V",Journal!$G$5:$G$1504,"VI81"),0)) -> 18386.3 | I6: =IF($A6="",0,SUMIFS(Journal!$N$5:$N$1504,Journal!$E$5:$E$1504,$A6)+IF($A6=2200,SUMIFS(Journal!$K$5:$K$1504,Journal!$J$5:$J$1504,"U"),0)) -> 27661.6 | J6: =IF($A6="",0,IF($A6=3809,-MWST!$H$13,IF($A6=2200,MWST!$H$13,IF($A6=6800,Anlagen!$J$3,-SUMIF(Anlagen!$B$6:$B$105,$A6,Anlagen!$J$6:$J$105))))) -> 0 | K6: =IF($A6="","",IF(OR($C6="Aktiv",$C6="Aufwand"),$G6+$H6-$I6+$J6,$G6+$I6-$H6+$J6)) -> 35724.7 | M6: Passiven | N6: =SUMIFS(Kontenplan!$G$5:$G$90,Kontenplan!$C$5:$C$90,"Passiv") -> 162000
A7: 1100 | B7: Forderungen Kunden (Debitoren) | C7: Aktiv | D7: UV | G7: 0 | H7: =IF($A7="",0,SUMIFS(Journal!$M$5:$M$1504,Journal!$D$5:$D$1504,$A7)+IF($A7=1170,SUMIFS(Journal!$K$5:$K$1504,Journal!$J$5:$J$1504,"V",Journal!$G$5:$G$1504,"<>VI81"),0)+IF($A7=1171,SUMIFS(Journal!$K$5:$K$1504,Journal!$J$5:$J$1504,"V",Journal!$G$5:$G$1504,"VI81"),0)) -> 2486.3 | I7: =IF($A7="",0,SUMIFS(Journal!$N$5:$N$1504,Journal!$E$5:$E$1504,$A7)+IF($A7=2200,SUMIFS(Journal!$K$5:$K$1504,Journal!$J$5:$J$1504,"U"),0)) -> 2486.3 | J7: =IF($A7="",0,IF($A7=3809,-MWST!$H$13,IF($A7=2200,MWST!$H$13,IF($A7=6800,Anlagen!$J$3,-SUMIF(Anlagen!$B$6:$B$105,$A7,Anlagen!$J$6:$J$105))))) -> 0 | K7: =IF($A7="","",IF(OR($C7="Aktiv",$C7="Aufwand"),$G7+$H7-$I7+$J7,$G7+$I7-$H7+$J7)) -> 0 | M7: Differenz | N7: =N5-N6 -> 0
A8: 1170 | B8: Vorsteuer MWST Material/DL | C8: Aktiv | D8: UV | G8: 0 | H8: =IF($A8="",0,SUMIFS(Journal!$M$5:$M$1504,Journal!$D$5:$D$1504,$A8)+IF($A8=1170,SUMIFS(Journal!$K$5:$K$1504,Journal!$J$5:$J$1504,"V",Journal!$G$5:$G$1504,"<>VI81"),0)+IF($A8=1171,SUMIFS(Journal!$K$5:$K$1504,Journal!$J$5:$J$1504,"V",Journal!$G$5:$G$1504,"VI81"),0)) -> 0 | I8: =IF($A8="",0,SUMIFS(Journal!$N$5:$N$1504,Journal!$E$5:$E$1504,$A8)+IF($A8=2200,SUMIFS(Journal!$K$5:$K$1504,Journal!$J$5:$J$1504,"U"),0)) -> 0 | J8: =IF($A8="",0,IF($A8=3809,-MWST!$H$13,IF($A8=2200,MWST!$H$13,IF($A8=6800,Anlagen!$J$3,-SUMIF(Anlagen!$B$6:$B$105,$A8,Anlagen!$J$6:$J$105))))) -> 0 | K8: =IF($A8="","",IF(OR($C8="Aktiv",$C8="Aufwand"),$G8+$H8-$I8+$J8,$G8+$I8-$H8+$J8)) -> 0 | M8: Status | N8: =IF(ABS(N7)<0.01,"Eröffnungsbilanz ausgeglichen ✓","ACHTUNG: Eröffnung nicht ausgeglichen") -> Eröffnungsbilanz ausgeglichen ✓
A9: 1171 | B9: Vorsteuer MWST Investitionen | C9: Aktiv | D9: UV | G9: 0 | H9: =IF($A9="",0,SUMIFS(Journal!$M$5:$M$1504,Journal!$D$5:$D$1504,$A9)+IF($A9=1170,SUMIFS(Journal!$K$5:$K$1504,Journal!$J$5:$J$1504,"V",Journal!$G$5:$G$1504,"<>VI81"),0)+IF($A9=1171,SUMIFS(Journal!$K$5:$K$1504,Journal!$J$5:$J$1504,"V",Journal!$G$5:$G$1504,"VI81"),0)) -> 0 | I9: =IF($A9="",0,SUMIFS(Journal!$N$5:$N$1504,Journal!$E$5:$E$1504,$A9)+IF($A9=2200,SUMIFS(Journal!$K$5:$K$1504,Journal!$J$5:$J$1504,"U"),0)) -> 0 | J9: =IF($A9="",0,IF($A9=3809,-MWST!$H$13,IF($A9=2200,MWST!$H$13,IF($A9=6800,Anlagen!$J$3,-SUMIF(Anlagen!$B$6:$B$105,$A9,Anlagen!$J$6:$J$105))))) -> 0 | K9: =IF($A9="","",IF(OR($C9="Aktiv",$C9="Aufwand"),$G9+$H9-$I9+$J9,$G9+$I9-$H9+$J9)) -> 0
A10: 1200 | B10: Lager Ersatzteile, Pneus, Öl | C10: Aktiv | D10: UV | G10: 18000 | H10: =IF($A10="",0,SUMIFS(Journal!$M$5:$M$1504,Journal!$D$5:$D$1504,$A10)+IF($A10=1170,SUMIFS(Journal!$K$5:$K$1504,Journal!$J$5:$J$1504,"V",Journal!$G$5:$G$1504,"<>VI81"),0)+IF($A10=1171,SUMIFS(Journal!$K$5:$K$1504,Journal!$J$5:$J$1504,"V",Journal!$G$5:$G$1504,"VI81"),0)) -> 0 | I10: =IF($A10="",0,SUMIFS(Journal!$N$5:$N$1504,Journal!$E$5:$E$1504,$A10)+IF($A10=2200,SUMIFS(Journal!$K$5:$K$1504,Journal!$J$5:$J$1504,"U"),0)) -> 0 | J10: =IF($A10="",0,IF($A10=3809,-MWST!$H$13,IF($A10=2200,MWST!$H$13,IF($A10=6800,Anlagen!$J$3,-SUMIF(Anlagen!$B$6:$B$105,$A10,Anlagen!$J$6:$J$105))))) -> 0 | K10: =IF($A10="","",IF(OR($C10="Aktiv",$C10="Aufwand"),$G10+$H10-$I10+$J10,$G10+$I10-$H10+$J10)) -> 18000 | M10: Gruppen: UV Umlaufvermögen · AV Anlagevermögen · FKK kurzfr. FK · FKL langfr. FK · EK Eigenkapital
A11: 1210 | B11: Lager Fahrzeuge (Occasionen) | C11: Aktiv | D11: UV | G11: 0 | H11: =IF($A11="",0,SUMIFS(Journal!$M$5:$M$1504,Journal!$D$5:$D$1504,$A11)+IF($A11=1170,SUMIFS(Journal!$K$5:$K$1504,Journal!$J$5:$J$1504,"V",Journal!$G$5:$G$1504,"<>VI81"),0)+IF($A11=1171,SUMIFS(Journal!$K$5:$K$1504,Journal!$J$5:$J$1504,"V",Journal!$G$5:$G$1504,"VI81"),0)) -> 0 | I11: =IF($A11="",0,SUMIFS(Journal!$N$5:$N$1504,Journal!$E$5:$E$1504,$A11)+IF($A11=2200,SUMIFS(Journal!$K$5:$K$1504,Journal!$J$5:$J$1504,"U"),0)) -> 0 | J11: =IF($A11="",0,IF($A11=3809,-MWST!$H$13,IF($A11=2200,MWST!$H$13,IF($A11=6800,Anlagen!$J$3,-SUMIF(Anlagen!$B$6:$B$105,$A11,Anlagen!$J$6:$J$105))))) -> 0 | K11: =IF($A11="","",IF(OR($C11="Aktiv",$C11="Aufwand"),$G11+$H11-$I11+$J11,$G11+$I11-$H11+$J11)) -> 0 | M11: ERT Betriebsertrag · MAT Material/Waren · PERS Personal · BA Betriebsaufwand · ABS Abschreibungen
A12: 1300 | B12: Aktive Rechnungsabgrenzung | C12: Aktiv | D12: UV | G12: 0 | H12: =IF($A12="",0,SUMIFS(Journal!$M$5:$M$1504,Journal!$D$5:$D$1504,$A12)+IF($A12=1170,SUMIFS(Journal!$K$5:$K$1504,Journal!$J$5:$J$1504,"V",Journal!$G$5:$G$1504,"<>VI81"),0)+IF($A12=1171,SUMIFS(Journal!$K$5:$K$1504,Journal!$J$5:$J$1504,"V",Journal!$G$5:$G$1504,"VI81"),0)) -> 0 | I12: =IF($A12="",0,SUMIFS(Journal!$N$5:$N$1504,Journal!$E$5:$E$1504,$A12)+IF($A12=2200,SUMIFS(Journal!$K$5:$K$1504,Journal!$J$5:$J$1504,"U"),0)) -> 0 | J12: =IF($A12="",0,IF($A12=3809,-MWST!$H$13,IF($A12=2200,MWST!$H$13,IF($A12=6800,Anlagen!$J$3,-SUMIF(Anlagen!$B$6:$B$105,$A12,Anlagen!$J$6:$J$105))))) -> 0 | K12: =IF($A12="","",IF(OR($C12="Aktiv",$C12="Aufwand"),$G12+$H12-$I12+$J12,$G12+$I12-$H12+$J12)) -> 0 | M12: FINA/FINE Finanzaufwand/-ertrag · AO/AOE ausserordentlich
A13: 1500 | B13: Maschinen & Werkstatteinrichtung | C13: Aktiv | D13: AV | G13: 60000 | H13: =IF($A13="",0,SUMIFS(Journal!$M$5:$M$1504,Journal!$D$5:$D$1504,$A13)+IF($A13=1170,SUMIFS(Journal!$K$5:$K$1504,Journal!$J$5:$J$1504,"V",Journal!$G$5:$G$1504,"<>VI81"),0)+IF($A13=1171,SUMIFS(Journal!$K$5:$K$1504,Journal!$J$5:$J$1504,"V",Journal!$G$5:$G$1504,"VI81"),0)) -> 0 | I13: =IF($A13="",0,SUMIFS(Journal!$N$5:$N$1504,Journal!$E$5:$E$1504,$A13)+IF($A13=2200,SUMIFS(Journal!$K$5:$K$1504,Journal!$J$5:$J$1504,"U"),0)) -> 0 | J13: =IF($A13="",0,IF($A13=3809,-MWST!$H$13,IF($A13=2200,MWST!$H$13,IF($A13=6800,Anlagen!$J$3,-SUMIF(Anlagen!$B$6:$B$105,$A13,Anlagen!$J$6:$J$105))))) -> -18000 | K13: =IF($A13="","",IF(OR($C13="Aktiv",$C13="Aufwand"),$G13+$H13-$I13+$J13,$G13+$I13-$H13+$J13)) -> 42000 | M13: Saldosatz-Gruppe: 1 = Werkstatt-Satz, 2 = Fahrzeughandel-Satz (nur Ertragskonten)
A14: 1510 | B14: Werkzeuge | C14: Aktiv | D14: AV | G14: 12000 | H14: =IF($A14="",0,SUMIFS(Journal!$M$5:$M$1504,Journal!$D$5:$D$1504,$A14)+IF($A14=1170,SUMIFS(Journal!$K$5:$K$1504,Journal!$J$5:$J$1504,"V",Journal!$G$5:$G$1504,"<>VI81"),0)+IF($A14=1171,SUMIFS(Journal!$K$5:$K$1504,Journal!$J$5:$J$1504,"V",Journal!$G$5:$G$1504,"VI81"),0)) -> 0 | I14: =IF($A14="",0,SUMIFS(Journal!$N$5:$N$1504,Journal!$E$5:$E$1504,$A14)+IF($A14=2200,SUMIFS(Journal!$K$5:$K$1504,Journal!$J$5:$J$1504,"U"),0)) -> 0 | J14: =IF($A14="",0,IF($A14=3809,-MWST!$H$13,IF($A14=2200,MWST!$H$13,IF($A14=6800,Anlagen!$J$3,-SUMIF(Anlagen!$B$6:$B$105,$A14,Anlagen!$J$6:$J$105))))) -> -5400 | K14: =IF($A14="","",IF(OR($C14="Aktiv",$C14="Aufwand"),$G14+$H14-$I14+$J14,$G14+$I14-$H14+$J14)) -> 6600
A15: 1520 | B15: Büro, Mobiliar & EDV | C15: Aktiv | D15: AV | G15: 0 | H15: =IF($A15="",0,SUMIFS(Journal!$M$5:$M$1504,Journal!$D$5:$D$1504,$A15)+IF($A15=1170,SUMIFS(Journal!$K$5:$K$1504,Journal!$J$5:$J$1504,"V",Journal!$G$5:$G$1504,"<>VI81"),0)+IF($A15=1171,SUMIFS(Journal!$K$5:$K$1504,Journal!$J$5:$J$1504,"V",Journal!$G$5:$G$1504,"VI81"),0)) -> 0 | I15: =IF($A15="",0,SUMIFS(Journal!$N$5:$N$1504,Journal!$E$5:$E$1504,$A15)+IF($A15=2200,SUMIFS(Journal!$K$5:$K$1504,Journal!$J$5:$J$1504,"U"),0)) -> 0 | J15: =IF($A15="",0,IF($A15=3809,-MWST!$H$13,IF($A15=2200,MWST!$H$13,IF($A15=6800,Anlagen!$J$3,-SUMIF(Anlagen!$B$6:$B$105,$A15,Anlagen!$J$6:$J$105))))) -> 0 | K15: =IF($A15="","",IF(OR($C15="Aktiv",$C15="Aufwand"),$G15+$H15-$I15+$J15,$G15+$I15-$H15+$J15)) -> 0
A16: 1530 | B16: Fahrzeuge (Service-/Abschleppwagen) | C16: Aktiv | D16: AV | G16: 25000 | H16: =IF($A16="",0,SUMIFS(Journal!$M$5:$M$1504,Journal!$D$5:$D$1504,$A16)+IF($A16=1170,SUMIFS(Journal!$K$5:$K$1504,Journal!$J$5:$J$1504,"V",Journal!$G$5:$G$1504,"<>VI81"),0)+IF($A16=1171,SUMIFS(Journal!$K$5:$K$1504,Journal!$J$5:$J$1504,"V",Journal!$G$5:$G$1504,"VI81"),0)) -> 0 | I16: =IF($A16="",0,SUMIFS(Journal!$N$5:$N$1504,Journal!$E$5:$E$1504,$A16)+IF($A16=2200,SUMIFS(Journal!$K$5:$K$1504,Journal!$J$5:$J$1504,"U"),0)) -> 0 | J16: =IF($A16="",0,IF($A16=3809,-MWST!$H$13,IF($A16=2200,MWST!$H$13,IF($A16=6800,Anlagen!$J$3,-SUMIF(Anlagen!$B$6:$B$105,$A16,Anlagen!$J$6:$J$105))))) -> -10000 | K16: =IF($A16="","",IF(OR($C16="Aktiv",$C16="Aufwand"),$G16+$H16-$I16+$J16,$G16+$I16-$H16+$J16)) -> 15000
A17: 2000 | B17: Verbindlichkeiten Lieferanten (Kreditoren) | C17: Passiv | D17: FKK | G17: 0 | H17: =IF($A17="",0,SUMIFS(Journal!$M$5:$M$1504,Journal!$D$5:$D$1504,$A17)+IF($A17=1170,SUMIFS(Journal!$K$5:$K$1504,Journal!$J$5:$J$1504,"V",Journal!$G$5:$G$1504,"<>VI81"),0)+IF($A17=1171,SUMIFS(Journal!$K$5:$K$1504,Journal!$J$5:$J$1504,"V",Journal!$G$5:$G$1504,"VI81"),0)) -> 0 | I17: =IF($A17="",0,SUMIFS(Journal!$N$5:$N$1504,Journal!$E$5:$E$1504,$A17)+IF($A17=2200,SUMIFS(Journal!$K$5:$K$1504,Journal!$J$5:$J$1504,"U"),0)) -> 1297.2 | J17: =IF($A17="",0,IF($A17=3809,-MWST!$H$13,IF($A17=2200,MWST!$H$13,IF($A17=6800,Anlagen!$J$3,-SUMIF(Anlagen!$B$6:$B$105,$A17,Anlagen!$J$6:$J$105))))) -> 0 | K17: =IF($A17="","",IF(OR($C17="Aktiv",$C17="Aufwand"),$G17+$H17-$I17+$J17,$G17+$I17-$H17+$J17)) -> 1297.2
A18: 2200 | B18: Geschuldete MWST | C18: Passiv | D18: FKK | G18: 0 | H18: =IF($A18="",0,SUMIFS(Journal!$M$5:$M$1504,Journal!$D$5:$D$1504,$A18)+IF($A18=1170,SUMIFS(Journal!$K$5:$K$1504,Journal!$J$5:$J$1504,"V",Journal!$G$5:$G$1504,"<>VI81"),0)+IF($A18=1171,SUMIFS(Journal!$K$5:$K$1504,Journal!$J$5:$J$1504,"V",Journal!$G$5:$G$1504,"VI81"),0)) -> 0 | I18: =IF($A18="",0,SUMIFS(Journal!$N$5:$N$1504,Journal!$E$5:$E$1504,$A18)+IF($A18=2200,SUMIFS(Journal!$K$5:$K$1504,Journal!$J$5:$J$1504,"U"),0)) -> 0 | J18: =IF($A18="",0,IF($A18=3809,-MWST!$H$13,IF($A18=2200,MWST!$H$13,IF($A18=6800,Anlagen!$J$3,-SUMIF(Anlagen!$B$6:$B$105,$A18,Anlagen!$J$6:$J$105))))) -> 173.59 | K18: =IF($A18="","",IF(OR($C18="Aktiv",$C18="Aufwand"),$G18+$H18-$I18+$J18,$G18+$I18-$H18+$J18)) -> 173.59
A19: 2270 | B19: Sozialversicherungen (AHV, UVG, BVG) | C19: Passiv | D19: FKK | G19: 0 | H19: =IF($A19="",0,SUMIFS(Journal!$M$5:$M$1504,Journal!$D$5:$D$1504,$A19)+IF($A19=1170,SUMIFS(Journal!$K$5:$K$1504,Journal!$J$5:$J$1504,"V",Journal!$G$5:$G$1504,"<>VI81"),0)+IF($A19=1171,SUMIFS(Journal!$K$5:$K$1504,Journal!$J$5:$J$1504,"V",Journal!$G$5:$G$1504,"VI81"),0)) -> 0 | I19: =IF($A19="",0,SUMIFS(Journal!$N$5:$N$1504,Journal!$E$5:$E$1504,$A19)+IF($A19=2200,SUMIFS(Journal!$K$5:$K$1504,Journal!$J$5:$J$1504,"U"),0)) -> 1330 | J19: =IF($A19="",0,IF($A19=3809,-MWST!$H$13,IF($A19=2200,MWST!$H$13,IF($A19=6800,Anlagen!$J$3,-SUMIF(Anlagen!$B$6:$B$105,$A19,Anlagen!$J$6:$J$105))))) -> 0 | K19: =IF($A19="","",IF(OR($C19="Aktiv",$C19="Aufwand"),$G19+$H19-$I19+$J19,$G19+$I19-$H19+$J19)) -> 1330
A20: 2300 | B20: Passive Rechnungsabgrenzung | C20: Passiv | D20: FKK | G20: 0 | H20: =IF($A20="",0,SUMIFS(Journal!$M$5:$M$1504,Journal!$D$5:$D$1504,$A20)+IF($A20=1170,SUMIFS(Journal!$K$5:$K$1504,Journal!$J$5:$J$1504,"V",Journal!$G$5:$G$1504,"<>VI81"),0)+IF($A20=1171,SUMIFS(Journal!$K$5:$K$1504,Journal!$J$5:$J$1504,"V",Journal!$G$5:$G$1504,"VI81"),0)) -> 0 | I20: =IF($A20="",0,SUMIFS(Journal!$N$5:$N$1504,Journal!$E$5:$E$1504,$A20)+IF($A20=2200,SUMIFS(Journal!$K$5:$K$1504,Journal!$J$5:$J$1504,"U"),0)) -> 0 | J20: =IF($A20="",0,IF($A20=3809,-MWST!$H$13,IF($A20=2200,MWST!$H$13,IF($A20=6800,Anlagen!$J$3,-SUMIF(Anlagen!$B$6:$B$105,$A20,Anlagen!$J$6:$J$105))))) -> 0 | K20: =IF($A20="","",IF(OR($C20="Aktiv",$C20="Aufwand"),$G20+$H20-$I20+$J20,$G20+$I20-$H20+$J20)) -> 0
A21: 2400 | B21: Bankdarlehen | C21: Passiv | D21: FKL | G21: 40000 | H21: =IF($A21="",0,SUMIFS(Journal!$M$5:$M$1504,Journal!$D$5:$D$1504,$A21)+IF($A21=1170,SUMIFS(Journal!$K$5:$K$1504,Journal!$J$5:$J$1504,"V",Journal!$G$5:$G$1504,"<>VI81"),0)+IF($A21=1171,SUMIFS(Journal!$K$5:$K$1504,Journal!$J$5:$J$1504,"V",Journal!$G$5:$G$1504,"VI81"),0)) -> 0 | I21: =IF($A21="",0,SUMIFS(Journal!$N$5:$N$1504,Journal!$E$5:$E$1504,$A21)+IF($A21=2200,SUMIFS(Journal!$K$5:$K$1504,Journal!$J$5:$J$1504,"U"),0)) -> 0 | J21: =IF($A21="",0,IF($A21=3809,-MWST!$H$13,IF($A21=2200,MWST!$H$13,IF($A21=6800,Anlagen!$J$3,-SUMIF(Anlagen!$B$6:$B$105,$A21,Anlagen!$J$6:$J$105))))) -> 0 | K21: =IF($A21="","",IF(OR($C21="Aktiv",$C21="Aufwand"),$G21+$H21-$I21+$J21,$G21+$I21-$H21+$J21)) -> 40000
A22: 2450 | B22: Darlehen Dritte | C22: Passiv | D22: FKL | G22: 0 | H22: =IF($A22="",0,SUMIFS(Journal!$M$5:$M$1504,Journal!$D$5:$D$1504,$A22)+IF($A22=1170,SUMIFS(Journal!$K$5:$K$1504,Journal!$J$5:$J$1504,"V",Journal!$G$5:$G$1504,"<>VI81"),0)+IF($A22=1171,SUMIFS(Journal!$K$5:$K$1504,Journal!$J$5:$J$1504,"V",Journal!$G$5:$G$1504,"VI81"),0)) -> 0 | I22: =IF($A22="",0,SUMIFS(Journal!$N$5:$N$1504,Journal!$E$5:$E$1504,$A22)+IF($A22=2200,SUMIFS(Journal!$K$5:$K$1504,Journal!$J$5:$J$1504,"U"),0)) -> 0 | J22: =IF($A22="",0,IF($A22=3809,-MWST!$H$13,IF($A22=2200,MWST!$H$13,IF($A22=6800,Anlagen!$J$3,-SUMIF(Anlagen!$B$6:$B$105,$A22,Anlagen!$J$6:$J$105))))) -> 0 | K22: =IF($A22="","",IF(OR($C22="Aktiv",$C22="Aufwand"),$G22+$H22-$I22+$J22,$G22+$I22-$H22+$J22)) -> 0
A23: 2800 | B23: Eigenkapital | C23: Passiv | D23: EK | G23: 122000 | H23: =IF($A23="",0,SUMIFS(Journal!$M$5:$M$1504,Journal!$D$5:$D$1504,$A23)+IF($A23=1170,SUMIFS(Journal!$K$5:$K$1504,Journal!$J$5:$J$1504,"V",Journal!$G$5:$G$1504,"<>VI81"),0)+IF($A23=1171,SUMIFS(Journal!$K$5:$K$1504,Journal!$J$5:$J$1504,"V",Journal!$G$5:$G$1504,"VI81"),0)) -> 0 | I23: =IF($A23="",0,SUMIFS(Journal!$N$5:$N$1504,Journal!$E$5:$E$1504,$A23)+IF($A23=2200,SUMIFS(Journal!$K$5:$K$1504,Journal!$J$5:$J$1504,"U"),0)) -> 0 | J23: =IF($A23="",0,IF($A23=3809,-MWST!$H$13,IF($A23=2200,MWST!$H$13,IF($A23=6800,Anlagen!$J$3,-SUMIF(Anlagen!$B$6:$B$105,$A23,Anlagen!$J$6:$J$105))))) -> 0 | K23: =IF($A23="","",IF(OR($C23="Aktiv",$C23="Aufwand"),$G23+$H23-$I23+$J23,$G23+$I23-$H23+$J23)) -> 122000
A24: 2850 | B24: Privatkonto (Bezüge/Einlagen) | C24: Passiv | D24: EK | G24: 0 | H24: =IF($A24="",0,SUMIFS(Journal!$M$5:$M$1504,Journal!$D$5:$D$1504,$A24)+IF($A24=1170,SUMIFS(Journal!$K$5:$K$1504,Journal!$J$5:$J$1504,"V",Journal!$G$5:$G$1504,"<>VI81"),0)+IF($A24=1171,SUMIFS(Journal!$K$5:$K$1504,Journal!$J$5:$J$1504,"V",Journal!$G$5:$G$1504,"VI81"),0)) -> 4000 | I24: =IF($A24="",0,SUMIFS(Journal!$N$5:$N$1504,Journal!$E$5:$E$1504,$A24)+IF($A24=2200,SUMIFS(Journal!$K$5:$K$1504,Journal!$J$5:$J$1504,"U"),0)) -> 0 | J24: =IF($A24="",0,IF($A24=3809,-MWST!$H$13,IF($A24=2200,MWST!$H$13,IF($A24=6800,Anlagen!$J$3,-SUMIF(Anlagen!$B$6:$B$105,$A24,Anlagen!$J$6:$J$105))))) -> 0 | K24: =IF($A24="","",IF(OR($C24="Aktiv",$C24="Aufwand"),$G24+$H24-$I24+$J24,$G24+$I24-$H24+$J24)) -> -4000
A25: 3000 | B25: Werkstattarbeiten (Arbeitsstunden) | C25: Ertrag | D25: ERT | E25: Werkstatt | F25: 1 | G25: 0 | H25: =IF($A25="",0,SUMIFS(Journal!$M$5:$M$1504,Journal!$D$5:$D$1504,$A25)+IF($A25=1170,SUMIFS(Journal!$K$5:$K$1504,Journal!$J$5:$J$1504,"V",Journal!$G$5:$G$1504,"<>VI81"),0)+IF($A25=1171,SUMIFS(Journal!$K$5:$K$1504,Journal!$J$5:$J$1504,"V",Journal!$G$5:$G$1504,"VI81"),0)) -> 0 | I25: =IF($A25="",0,SUMIFS(Journal!$N$5:$N$1504,Journal!$E$5:$E$1504,$A25)+IF($A25=2200,SUMIFS(Journal!$K$5:$K$1504,Journal!$J$5:$J$1504,"U"),0)) -> 1621.5 | J25: =IF($A25="",0,IF($A25=3809,-MWST!$H$13,IF($A25=2200,MWST!$H$13,IF($A25=6800,Anlagen!$J$3,-SUMIF(Anlagen!$B$6:$B$105,$A25,Anlagen!$J$6:$J$105))))) -> 0 | K25: =IF($A25="","",IF(OR($C25="Aktiv",$C25="Aufwand"),$G25+$H25-$I25+$J25,$G25+$I25-$H25+$J25)) -> 1621.5
A26: 3010 | B26: Service, MFK-Vorbereitung, Klima | C26: Ertrag | D26: ERT | E26: Werkstatt | F26: 1 | G26: 0 | H26: =IF($A26="",0,SUMIFS(Journal!$M$5:$M$1504,Journal!$D$5:$D$1504,$A26)+IF($A26=1170,SUMIFS(Journal!$K$5:$K$1504,Journal!$J$5:$J$1504,"V",Journal!$G$5:$G$1504,"<>VI81"),0)+IF($A26=1171,SUMIFS(Journal!$K$5:$K$1504,Journal!$J$5:$J$1504,"V",Journal!$G$5:$G$1504,"VI81"),0)) -> 0 | I26: =IF($A26="",0,SUMIFS(Journal!$N$5:$N$1504,Journal!$E$5:$E$1504,$A26)+IF($A26=2200,SUMIFS(Journal!$K$5:$K$1504,Journal!$J$5:$J$1504,"U"),0)) -> 0 | J26: =IF($A26="",0,IF($A26=3809,-MWST!$H$13,IF($A26=2200,MWST!$H$13,IF($A26=6800,Anlagen!$J$3,-SUMIF(Anlagen!$B$6:$B$105,$A26,Anlagen!$J$6:$J$105))))) -> 0 | K26: =IF($A26="","",IF(OR($C26="Aktiv",$C26="Aufwand"),$G26+$H26-$I26+$J26,$G26+$I26-$H26+$J26)) -> 0
A27: 3200 | B27: Verkauf Ersatzteile & Zubehör | C27: Ertrag | D27: ERT | E27: Teile | F27: 1 | G27: 0 | H27: =IF($A27="",0,SUMIFS(Journal!$M$5:$M$1504,Journal!$D$5:$D$1504,$A27)+IF($A27=1170,SUMIFS(Journal!$K$5:$K$1504,Journal!$J$5:$J$1504,"V",Journal!$G$5:$G$1504,"<>VI81"),0)+IF($A27=1171,SUMIFS(Journal!$K$5:$K$1504,Journal!$J$5:$J$1504,"V",Journal!$G$5:$G$1504,"VI81"),0)) -> 0 | I27: =IF($A27="",0,SUMIFS(Journal!$N$5:$N$1504,Journal!$E$5:$E$1504,$A27)+IF($A27=2200,SUMIFS(Journal!$K$5:$K$1504,Journal!$J$5:$J$1504,"U"),0)) -> 864.8 | J27: =IF($A27="",0,IF($A27=3809,-MWST!$H$13,IF($A27=2200,MWST!$H$13,IF($A27=6800,Anlagen!$J$3,-SUMIF(Anlagen!$B$6:$B$105,$A27,Anlagen!$J$6:$J$105))))) -> 0 | K27: =IF($A27="","",IF(OR($C27="Aktiv",$C27="Aufwand"),$G27+$H27-$I27+$J27,$G27+$I27-$H27+$J27)) -> 864.8
A28: 3210 | B28: Verkauf Pneus & Pneuhotel | C28: Ertrag | D28: ERT | E28: Teile | F28: 1 | G28: 0 | H28: =IF($A28="",0,SUMIFS(Journal!$M$5:$M$1504,Journal!$D$5:$D$1504,$A28)+IF($A28=1170,SUMIFS(Journal!$K$5:$K$1504,Journal!$J$5:$J$1504,"V",Journal!$G$5:$G$1504,"<>VI81"),0)+IF($A28=1171,SUMIFS(Journal!$K$5:$K$1504,Journal!$J$5:$J$1504,"V",Journal!$G$5:$G$1504,"VI81"),0)) -> 0 | I28: =IF($A28="",0,SUMIFS(Journal!$N$5:$N$1504,Journal!$E$5:$E$1504,$A28)+IF($A28=2200,SUMIFS(Journal!$K$5:$K$1504,Journal!$J$5:$J$1504,"U"),0)) -> 120 | J28: =IF($A28="",0,IF($A28=3809,-MWST!$H$13,IF($A28=2200,MWST!$H$13,IF($A28=6800,Anlagen!$J$3,-SUMIF(Anlagen!$B$6:$B$105,$A28,Anlagen!$J$6:$J$105))))) -> 0 | K28: =IF($A28="","",IF(OR($C28="Aktiv",$C28="Aufwand"),$G28+$H28-$I28+$J28,$G28+$I28-$H28+$J28)) -> 120
A29: 3400 | B29: Verkauf Occasionen | C29: Ertrag | D29: ERT | E29: Fahrzeuge | F29: 2 | G29: 0 | H29: =IF($A29="",0,SUMIFS(Journal!$M$5:$M$1504,Journal!$D$5:$D$1504,$A29)+IF($A29=1170,SUMIFS(Journal!$K$5:$K$1504,Journal!$J$5:$J$1504,"V",Journal!$G$5:$G$1504,"<>VI81"),0)+IF($A29=1171,SUMIFS(Journal!$K$5:$K$1504,Journal!$J$5:$J$1504,"V",Journal!$G$5:$G$1504,"VI81"),0)) -> 0 | I29: =IF($A29="",0,SUMIFS(Journal!$N$5:$N$1504,Journal!$E$5:$E$1504,$A29)+IF($A29=2200,SUMIFS(Journal!$K$5:$K$1504,Journal!$J$5:$J$1504,"U"),0)) -> 15900 | J29: =IF($A29="",0,IF($A29=3809,-MWST!$H$13,IF($A29=2200,MWST!$H$13,IF($A29=6800,Anlagen!$J$3,-SUMIF(Anlagen!$B$6:$B$105,$A29,Anlagen!$J$6:$J$105))))) -> 0 | K29: =IF($A29="","",IF(OR($C29="Aktiv",$C29="Aufwand"),$G29+$H29-$I29+$J29,$G29+$I29-$H29+$J29)) -> 15900
A30: 3410 | B30: Verkauf Neuwagen | C30: Ertrag | D30: ERT | E30: Fahrzeuge | F30: 2 | G30: 0 | H30: =IF($A30="",0,SUMIFS(Journal!$M$5:$M$1504,Journal!$D$5:$D$1504,$A30)+IF($A30=1170,SUMIFS(Journal!$K$5:$K$1504,Journal!$J$5:$J$1504,"V",Journal!$G$5:$G$1504,"<>VI81"),0)+IF($A30=1171,SUMIFS(Journal!$K$5:$K$1504,Journal!$J$5:$J$1504,"V",Journal!$G$5:$G$1504,"VI81"),0)) -> 0 | I30: =IF($A30="",0,SUMIFS(Journal!$N$5:$N$1504,Journal!$E$5:$E$1504,$A30)+IF($A30=2200,SUMIFS(Journal!$K$5:$K$1504,Journal!$J$5:$J$1504,"U"),0)) -> 0 | J30: =IF($A30="",0,IF($A30=3809,-MWST!$H$13,IF($A30=2200,MWST!$H$13,IF($A30=6800,Anlagen!$J$3,-SUMIF(Anlagen!$B$6:$B$105,$A30,Anlagen!$J$6:$J$105))))) -> 0 | K30: =IF($A30="","",IF(OR($C30="Aktiv",$C30="Aufwand"),$G30+$H30-$I30+$J30,$G30+$I30-$H30+$J30)) -> 0
A31: 3600 | B31: Übriger Ertrag (Abschleppdienst, Vermietung) | C31: Ertrag | D31: ERT | E31: Allgemein | F31: 1 | G31: 0 | H31: =IF($A31="",0,SUMIFS(Journal!$M$5:$M$1504,Journal!$D$5:$D$1504,$A31)+IF($A31=1170,SUMIFS(Journal!$K$5:$K$1504,Journal!$J$5:$J$1504,"V",Journal!$G$5:$G$1504,"<>VI81"),0)+IF($A31=1171,SUMIFS(Journal!$K$5:$K$1504,Journal!$J$5:$J$1504,"V",Journal!$G$5:$G$1504,"VI81"),0)) -> 0 | I31: =IF($A31="",0,SUMIFS(Journal!$N$5:$N$1504,Journal!$E$5:$E$1504,$A31)+IF($A31=2200,SUMIFS(Journal!$K$5:$K$1504,Journal!$J$5:$J$1504,"U"),0)) -> 0 | J31: =IF($A31="",0,IF($A31=3809,-MWST!$H$13,IF($A31=2200,MWST!$H$13,IF($A31=6800,Anlagen!$J$3,-SUMIF(Anlagen!$B$6:$B$105,$A31,Anlagen!$J$6:$J$105))))) -> 0 | K31: =IF($A31="","",IF(OR($C31="Aktiv",$C31="Aufwand"),$G31+$H31-$I31+$J31,$G31+$I31-$H31+$J31)) -> 0
A32: 3800 | B32: Rabatte & Skonti an Kunden | C32: Ertrag | D32: ERT | E32: Allgemein | F32: 1 | G32: 0 | H32: =IF($A32="",0,SUMIFS(Journal!$M$5:$M$1504,Journal!$D$5:$D$1504,$A32)+IF($A32=1170,SUMIFS(Journal!$K$5:$K$1504,Journal!$J$5:$J$1504,"V",Journal!$G$5:$G$1504,"<>VI81"),0)+IF($A32=1171,SUMIFS(Journal!$K$5:$K$1504,Journal!$J$5:$J$1504,"V",Journal!$G$5:$G$1504,"VI81"),0)) -> 0 | I32: =IF($A32="",0,SUMIFS(Journal!$N$5:$N$1504,Journal!$E$5:$E$1504,$A32)+IF($A32=2200,SUMIFS(Journal!$K$5:$K$1504,Journal!$J$5:$J$1504,"U"),0)) -> 0 | J32: =IF($A32="",0,IF($A32=3809,-MWST!$H$13,IF($A32=2200,MWST!$H$13,IF($A32=6800,Anlagen!$J$3,-SUMIF(Anlagen!$B$6:$B$105,$A32,Anlagen!$J$6:$J$105))))) -> 0 | K32: =IF($A32="","",IF(OR($C32="Aktiv",$C32="Aufwand"),$G32+$H32-$I32+$J32,$G32+$I32-$H32+$J32)) -> 0
A33: 3805 | B33: Debitorenverluste | C33: Ertrag | D33: ERT | E33: Allgemein | F33: 1 | G33: 0 | H33: =IF($A33="",0,SUMIFS(Journal!$M$5:$M$1504,Journal!$D$5:$D$1504,$A33)+IF($A33=1170,SUMIFS(Journal!$K$5:$K$1504,Journal!$J$5:$J$1504,"V",Journal!$G$5:$G$1504,"<>VI81"),0)+IF($A33=1171,SUMIFS(Journal!$K$5:$K$1504,Journal!$J$5:$J$1504,"V",Journal!$G$5:$G$1504,"VI81"),0)) -> 0 | I33: =IF($A33="",0,SUMIFS(Journal!$N$5:$N$1504,Journal!$E$5:$E$1504,$A33)+IF($A33=2200,SUMIFS(Journal!$K$5:$K$1504,Journal!$J$5:$J$1504,"U"),0)) -> 0 | J33: =IF($A33="",0,IF($A33=3809,-MWST!$H$13,IF($A33=2200,MWST!$H$13,IF($A33=6800,Anlagen!$J$3,-SUMIF(Anlagen!$B$6:$B$105,$A33,Anlagen!$J$6:$J$105))))) -> 0 | K33: =IF($A33="","",IF(OR($C33="Aktiv",$C33="Aufwand"),$G33+$H33-$I33+$J33,$G33+$I33-$H33+$J33)) -> 0
A34: 3809 | B34: MWST Saldosteuersatz (automatisch) | C34: Ertrag | D34: ERT | E34: Allgemein | G34: 0 | H34: =IF($A34="",0,SUMIFS(Journal!$M$5:$M$1504,Journal!$D$5:$D$1504,$A34)+IF($A34=1170,SUMIFS(Journal!$K$5:$K$1504,Journal!$J$5:$J$1504,"V",Journal!$G$5:$G$1504,"<>VI81"),0)+IF($A34=1171,SUMIFS(Journal!$K$5:$K$1504,Journal!$J$5:$J$1504,"V",Journal!$G$5:$G$1504,"VI81"),0)) -> 0 | I34: =IF($A34="",0,SUMIFS(Journal!$N$5:$N$1504,Journal!$E$5:$E$1504,$A34)+IF($A34=2200,SUMIFS(Journal!$K$5:$K$1504,Journal!$J$5:$J$1504,"U"),0)) -> 0 | J34: =IF($A34="",0,IF($A34=3809,-MWST!$H$13,IF($A34=2200,MWST!$H$13,IF($A34=6800,Anlagen!$J$3,-SUMIF(Anlagen!$B$6:$B$105,$A34,Anlagen!$J$6:$J$105))))) -> -173.59 | K34: =IF($A34="","",IF(OR($C34="Aktiv",$C34="Aufwand"),$G34+$H34-$I34+$J34,$G34+$I34-$H34+$J34)) -> -173.59
A35: 4000 | B35: Einkauf Ersatzteile & Zubehör | C35: Aufwand | D35: MAT | E35: Teile | G35: 0 | H35: =IF($A35="",0,SUMIFS(Journal!$M$5:$M$1504,Journal!$D$5:$D$1504,$A35)+IF($A35=1170,SUMIFS(Journal!$K$5:$K$1504,Journal!$J$5:$J$1504,"V",Journal!$G$5:$G$1504,"<>VI81"),0)+IF($A35=1171,SUMIFS(Journal!$K$5:$K$1504,Journal!$J$5:$J$1504,"V",Journal!$G$5:$G$1504,"VI81"),0)) -> 1297.2 | I35: =IF($A35="",0,SUMIFS(Journal!$N$5:$N$1504,Journal!$E$5:$E$1504,$A35)+IF($A35=2200,SUMIFS(Journal!$K$5:$K$1504,Journal!$J$5:$J$1504,"U"),0)) -> 0 | J35: =IF($A35="",0,IF($A35=3809,-MWST!$H$13,IF($A35=2200,MWST!$H$13,IF($A35=6800,Anlagen!$J$3,-SUMIF(Anlagen!$B$6:$B$105,$A35,Anlagen!$J$6:$J$105))))) -> 0 | K35: =IF($A35="","",IF(OR($C35="Aktiv",$C35="Aufwand"),$G35+$H35-$I35+$J35,$G35+$I35-$H35+$J35)) -> 1297.2
A36: 4010 | B36: Einkauf Pneus | C36: Aufwand | D36: MAT | E36: Teile | G36: 0 | H36: =IF($A36="",0,SUMIFS(Journal!$M$5:$M$1504,Journal!$D$5:$D$1504,$A36)+IF($A36=1170,SUMIFS(Journal!$K$5:$K$1504,Journal!$J$5:$J$1504,"V",Journal!$G$5:$G$1504,"<>VI81"),0)+IF($A36=1171,SUMIFS(Journal!$K$5:$K$1504,Journal!$J$5:$J$1504,"V",Journal!$G$5:$G$1504,"VI81"),0)) -> 0 | I36: =IF($A36="",0,SUMIFS(Journal!$N$5:$N$1504,Journal!$E$5:$E$1504,$A36)+IF($A36=2200,SUMIFS(Journal!$K$5:$K$1504,Journal!$J$5:$J$1504,"U"),0)) -> 0 | J36: =IF($A36="",0,IF($A36=3809,-MWST!$H$13,IF($A36=2200,MWST!$H$13,IF($A36=6800,Anlagen!$J$3,-SUMIF(Anlagen!$B$6:$B$105,$A36,Anlagen!$J$6:$J$105))))) -> 0 | K36: =IF($A36="","",IF(OR($C36="Aktiv",$C36="Aufwand"),$G36+$H36-$I36+$J36,$G36+$I36-$H36+$J36)) -> 0
A37: 4200 | B37: Einkauf Fahrzeuge | C37: Aufwand | D37: MAT | E37: Fahrzeuge | G37: 0 | H37: =IF($A37="",0,SUMIFS(Journal!$M$5:$M$1504,Journal!$D$5:$D$1504,$A37)+IF($A37=1170,SUMIFS(Journal!$K$5:$K$1504,Journal!$J$5:$J$1504,"V",Journal!$G$5:$G$1504,"<>VI81"),0)+IF($A37=1171,SUMIFS(Journal!$K$5:$K$1504,Journal!$J$5:$J$1504,"V",Journal!$G$5:$G$1504,"VI81"),0)) -> 12000 | I37: =IF($A37="",0,SUMIFS(Journal!$N$5:$N$1504,Journal!$E$5:$E$1504,$A37)+IF($A37=2200,SUMIFS(Journal!$K$5:$K$1504,Journal!$J$5:$J$1504,"U"),0)) -> 0 | J37: =IF($A37="",0,IF($A37=3809,-MWST!$H$13,IF($A37=2200,MWST!$H$13,IF($A37=6800,Anlagen!$J$3,-SUMIF(Anlagen!$B$6:$B$105,$A37,Anlagen!$J$6:$J$105))))) -> 0 | K37: =IF($A37="","",IF(OR($C37="Aktiv",$C37="Aufwand"),$G37+$H37-$I37+$J37,$G37+$I37-$H37+$J37)) -> 12000
A38: 4210 | B38: Aufbereitung/Reparatur Handelsfahrzeuge (fremd) | C38: Aufwand | D38: MAT | E38: Fahrzeuge | G38: 0 | H38: =IF($A38="",0,SUMIFS(Journal!$M$5:$M$1504,Journal!$D$5:$D$1504,$A38)+IF($A38=1170,SUMIFS(Journal!$K$5:$K$1504,Journal!$J$5:$J$1504,"V",Journal!$G$5:$G$1504,"<>VI81"),0)+IF($A38=1171,SUMIFS(Journal!$K$5:$K$1504,Journal!$J$5:$J$1504,"V",Journal!$G$5:$G$1504,"VI81"),0)) -> 0 | I38: =IF($A38="",0,SUMIFS(Journal!$N$5:$N$1504,Journal!$E$5:$E$1504,$A38)+IF($A38=2200,SUMIFS(Journal!$K$5:$K$1504,Journal!$J$5:$J$1504,"U"),0)) -> 0 | J38: =IF($A38="",0,IF($A38=3809,-MWST!$H$13,IF($A38=2200,MWST!$H$13,IF($A38=6800,Anlagen!$J$3,-SUMIF(Anlagen!$B$6:$B$105,$A38,Anlagen!$J$6:$J$105))))) -> 0 | K38: =IF($A38="","",IF(OR($C38="Aktiv",$C38="Aufwand"),$G38+$H38-$I38+$J38,$G38+$I38-$H38+$J38)) -> 0
A39: 4400 | B39: Fremdarbeiten (Karosserie, Lack, Elektronik) | C39: Aufwand | D39: MAT | E39: Werkstatt | G39: 0 | H39: =IF($A39="",0,SUMIFS(Journal!$M$5:$M$1504,Journal!$D$5:$D$1504,$A39)+IF($A39=1170,SUMIFS(Journal!$K$5:$K$1504,Journal!$J$5:$J$1504,"V",Journal!$G$5:$G$1504,"<>VI81"),0)+IF($A39=1171,SUMIFS(Journal!$K$5:$K$1504,Journal!$J$5:$J$1504,"V",Journal!$G$5:$G$1504,"VI81"),0)) -> 0 | I39: =IF($A39="",0,SUMIFS(Journal!$N$5:$N$1504,Journal!$E$5:$E$1504,$A39)+IF($A39=2200,SUMIFS(Journal!$K$5:$K$1504,Journal!$J$5:$J$1504,"U"),0)) -> 0 | J39: =IF($A39="",0,IF($A39=3809,-MWST!$H$13,IF($A39=2200,MWST!$H$13,IF($A39=6800,Anlagen!$J$3,-SUMIF(Anlagen!$B$6:$B$105,$A39,Anlagen!$J$6:$J$105))))) -> 0 | K39: =IF($A39="","",IF(OR($C39="Aktiv",$C39="Aufwand"),$G39+$H39-$I39+$J39,$G39+$I39-$H39+$J39)) -> 0
A40: 4500 | B40: Betriebsmaterial (Öl, Verbrauch) | C40: Aufwand | D40: MAT | E40: Werkstatt | G40: 0 | H40: =IF($A40="",0,SUMIFS(Journal!$M$5:$M$1504,Journal!$D$5:$D$1504,$A40)+IF($A40=1170,SUMIFS(Journal!$K$5:$K$1504,Journal!$J$5:$J$1504,"V",Journal!$G$5:$G$1504,"<>VI81"),0)+IF($A40=1171,SUMIFS(Journal!$K$5:$K$1504,Journal!$J$5:$J$1504,"V",Journal!$G$5:$G$1504,"VI81"),0)) -> 0 | I40: =IF($A40="",0,SUMIFS(Journal!$N$5:$N$1504,Journal!$E$5:$E$1504,$A40)+IF($A40=2200,SUMIFS(Journal!$K$5:$K$1504,Journal!$J$5:$J$1504,"U"),0)) -> 0 | J40: =IF($A40="",0,IF($A40=3809,-MWST!$H$13,IF($A40=2200,MWST!$H$13,IF($A40=6800,Anlagen!$J$3,-SUMIF(Anlagen!$B$6:$B$105,$A40,Anlagen!$J$6:$J$105))))) -> 0 | K40: =IF($A40="","",IF(OR($C40="Aktiv",$C40="Aufwand"),$G40+$H40-$I40+$J40,$G40+$I40-$H40+$J40)) -> 0
A41: 4900 | B41: Lieferantenskonti & Rabatte | C41: Aufwand | D41: MAT | E41: Teile | G41: 0 | H41: =IF($A41="",0,SUMIFS(Journal!$M$5:$M$1504,Journal!$D$5:$D$1504,$A41)+IF($A41=1170,SUMIFS(Journal!$K$5:$K$1504,Journal!$J$5:$J$1504,"V",Journal!$G$5:$G$1504,"<>VI81"),0)+IF($A41=1171,SUMIFS(Journal!$K$5:$K$1504,Journal!$J$5:$J$1504,"V",Journal!$G$5:$G$1504,"VI81"),0)) -> 0 | I41: =IF($A41="",0,SUMIFS(Journal!$N$5:$N$1504,Journal!$E$5:$E$1504,$A41)+IF($A41=2200,SUMIFS(Journal!$K$5:$K$1504,Journal!$J$5:$J$1504,"U"),0)) -> 0 | J41: =IF($A41="",0,IF($A41=3809,-MWST!$H$13,IF($A41=2200,MWST!$H$13,IF($A41=6800,Anlagen!$J$3,-SUMIF(Anlagen!$B$6:$B$105,$A41,Anlagen!$J$6:$J$105))))) -> 0 | K41: =IF($A41="","",IF(OR($C41="Aktiv",$C41="Aufwand"),$G41+$H41-$I41+$J41,$G41+$I41-$H41+$J41)) -> 0
A42: 5000 | B42: Löhne Mitarbeitende | C42: Aufwand | D42: PERS | E42: Werkstatt | G42: 0 | H42: =IF($A42="",0,SUMIFS(Journal!$M$5:$M$1504,Journal!$D$5:$D$1504,$A42)+IF($A42=1170,SUMIFS(Journal!$K$5:$K$1504,Journal!$J$5:$J$1504,"V",Journal!$G$5:$G$1504,"<>VI81"),0)+IF($A42=1171,SUMIFS(Journal!$K$5:$K$1504,Journal!$J$5:$J$1504,"V",Journal!$G$5:$G$1504,"VI81"),0)) -> 5200 | I42: =IF($A42="",0,SUMIFS(Journal!$N$5:$N$1504,Journal!$E$5:$E$1504,$A42)+IF($A42=2200,SUMIFS(Journal!$K$5:$K$1504,Journal!$J$5:$J$1504,"U"),0)) -> 0 | J42: =IF($A42="",0,IF($A42=3809,-MWST!$H$13,IF($A42=2200,MWST!$H$13,IF($A42=6800,Anlagen!$J$3,-SUMIF(Anlagen!$B$6:$B$105,$A42,Anlagen!$J$6:$J$105))))) -> 0 | K42: =IF($A42="","",IF(OR($C42="Aktiv",$C42="Aufwand"),$G42+$H42-$I42+$J42,$G42+$I42-$H42+$J42)) -> 5200
A43: 5700 | B43: Sozialversicherungen Arbeitgeber | C43: Aufwand | D43: PERS | E43: Werkstatt | G43: 0 | H43: =IF($A43="",0,SUMIFS(Journal!$M$5:$M$1504,Journal!$D$5:$D$1504,$A43)+IF($A43=1170,SUMIFS(Journal!$K$5:$K$1504,Journal!$J$5:$J$1504,"V",Journal!$G$5:$G$1504,"<>VI81"),0)+IF($A43=1171,SUMIFS(Journal!$K$5:$K$1504,Journal!$J$5:$J$1504,"V",Journal!$G$5:$G$1504,"VI81"),0)) -> 780 | I43: =IF($A43="",0,SUMIFS(Journal!$N$5:$N$1504,Journal!$E$5:$E$1504,$A43)+IF($A43=2200,SUMIFS(Journal!$K$5:$K$1504,Journal!$J$5:$J$1504,"U"),0)) -> 0 | J43: =IF($A43="",0,IF($A43=3809,-MWST!$H$13,IF($A43=2200,MWST!$H$13,IF($A43=6800,Anlagen!$J$3,-SUMIF(Anlagen!$B$6:$B$105,$A43,Anlagen!$J$6:$J$105))))) -> 0 | K43: =IF($A43="","",IF(OR($C43="Aktiv",$C43="Aufwand"),$G43+$H43-$I43+$J43,$G43+$I43-$H43+$J43)) -> 780
A44: 5800 | B44: Übriger Personalaufwand (Weiterbildung, Spesen) | C44: Aufwand | D44: PERS | E44: Allgemein | G44: 0 | H44: =IF($A44="",0,SUMIFS(Journal!$M$5:$M$1504,Journal!$D$5:$D$1504,$A44)+IF($A44=1170,SUMIFS(Journal!$K$5:$K$1504,Journal!$J$5:$J$1504,"V",Journal!$G$5:$G$1504,"<>VI81"),0)+IF($A44=1171,SUMIFS(Journal!$K$5:$K$1504,Journal!$J$5:$J$1504,"V",Journal!$G$5:$G$1504,"VI81"),0)) -> 0 | I44: =IF($A44="",0,SUMIFS(Journal!$N$5:$N$1504,Journal!$E$5:$E$1504,$A44)+IF($A44=2200,SUMIFS(Journal!$K$5:$K$1504,Journal!$J$5:$J$1504,"U"),0)) -> 0 | J44: =IF($A44="",0,IF($A44=3809,-MWST!$H$13,IF($A44=2200,MWST!$H$13,IF($A44=6800,Anlagen!$J$3,-SUMIF(Anlagen!$B$6:$B$105,$A44,Anlagen!$J$6:$J$105))))) -> 0 | K44: =IF($A44="","",IF(OR($C44="Aktiv",$C44="Aufwand"),$G44+$H44-$I44+$J44,$G44+$I44-$H44+$J44)) -> 0
A45: 6000 | B45: Miete Werkstatt & Abstellplätze | C45: Aufwand | D45: BA | E45: Allgemein | G45: 0 | H45: =IF($A45="",0,SUMIFS(Journal!$M$5:$M$1504,Journal!$D$5:$D$1504,$A45)+IF($A45=1170,SUMIFS(Journal!$K$5:$K$1504,Journal!$J$5:$J$1504,"V",Journal!$G$5:$G$1504,"<>VI81"),0)+IF($A45=1171,SUMIFS(Journal!$K$5:$K$1504,Journal!$J$5:$J$1504,"V",Journal!$G$5:$G$1504,"VI81"),0)) -> 3500 | I45: =IF($A45="",0,SUMIFS(Journal!$N$5:$N$1504,Journal!$E$5:$E$1504,$A45)+IF($A45=2200,SUMIFS(Journal!$K$5:$K$1504,Journal!$J$5:$J$1504,"U"),0)) -> 0 | J45: =IF($A45="",0,IF($A45=3809,-MWST!$H$13,IF($A45=2200,MWST!$H$13,IF($A45=6800,Anlagen!$J$3,-SUMIF(Anlagen!$B$6:$B$105,$A45,Anlagen!$J$6:$J$105))))) -> 0 | K45: =IF($A45="","",IF(OR($C45="Aktiv",$C45="Aufwand"),$G45+$H45-$I45+$J45,$G45+$I45-$H45+$J45)) -> 3500
... A57: 8100 | B57: Ausserordentlicher Ertrag | C57: Ertrag | D57: AOE | E57: Allgemein | G57: 0 | H57: =IF($A57="",0,SUMIFS(Journal!$M$5:$M$1504,Journal!$D$5:$D$1504,$A57)+IF($A57=1170,SUMIFS(Journal!$K$5:$K$1504,Journal!$J$5:$J$1504,"V",Journal!$G$5:$G$1504,"<>VI81"),0)+IF($A57=1171,SUMIFS(Journal!$K$5:$K$1504,Journal!$J$5:$J$1504,"V",Journal!$G$5:$G$1504,"VI81"),0)) -> 0 | I57: =IF($A57="",0,SUMIFS(Journal!$N$5:$N$1504,Journal!$E$5:$E$1504,$A57)+IF($A57=2200,SUMIFS(Journal!$K$5:$K$1504,Journal!$J$5:$J$1504,"U"),0)) -> 0 | J57: =IF($A57="",0,IF($A57=3809,-MWST!$H$13,IF($A57=2200,MWST!$H$13,IF($A57=6800,Anlagen!$J$3,-SUMIF(Anlagen!$B$6:$B$105,$A57,Anlagen!$J$6:$J$105))))) -> 0 | K57: =IF($A57="","",IF(OR($C57="Aktiv",$C57="Aufwand"),$G57+$H57-$I57+$J57,$G57+$I57-$H57+$J57)) -> 0
H58: =IF($A58="",0,SUMIFS(Journal!$M$5:$M$1504,Journal!$D$5:$D$1504,$A58)+IF($A58=1170,SUMIFS(Journal!$K$5:$K$1504,Journal!$J$5:$J$1504,"V",Journal!$G$5:$G$1504,"<>VI81"),0)+IF($A58=1171,SUMIFS(Journal!$K$5:$K$1504,Journal!$J$5:$J$1504,"V",Journal!$G$5:$G$1504,"VI81"),0)) -> 0 | I58: =IF($A58="",0,SUMIFS(Journal!$N$5:$N$1504,Journal!$E$5:$E$1504,$A58)+IF($A58=2200,SUMIFS(Journal!$K$5:$K$1504,Journal!$J$5:$J$1504,"U"),0)) -> 0 | J58: =IF($A58="",0,IF($A58=3809,-MWST!$H$13,IF($A58=2200,MWST!$H$13,IF($A58=6800,Anlagen!$J$3,-SUMIF(Anlagen!$B$6:$B$105,$A58,Anlagen!$J$6:$J$105))))) -> 0 | K58: =IF($A58="","",IF(OR($C58="Aktiv",$C58="Aufwand"),$G58+$H58-$I58+$J58,$G58+$I58-$H58+$J58))
H59: =IF($A59="",0,SUMIFS(Journal!$M$5:$M$1504,Journal!$D$5:$D$1504,$A59)+IF($A59=1170,SUMIFS(Journal!$K$5:$K$1504,Journal!$J$5:$J$1504,"V",Journal!$G$5:$G$1504,"<>VI81"),0)+IF($A59=1171,SUMIFS(Journal!$K$5:$K$1504,Journal!$J$5:$J$1504,"V",Journal!$G$5:$G$1504,"VI81"),0)) -> 0 | I59: =IF($A59="",0,SUMIFS(Journal!$N$5:$N$1504,Journal!$E$5:$E$1504,$A59)+IF($A59=2200,SUMIFS(Journal!$K$5:$K$1504,Journal!$J$5:$J$1504,"U"),0)) -> 0 | J59: =IF($A59="",0,IF($A59=3809,-MWST!$H$13,IF($A59=2200,MWST!$H$13,IF($A59=6800,Anlagen!$J$3,-SUMIF(Anlagen!$B$6:$B$105,$A59,Anlagen!$J$6:$J$105))))) -> 0 | K59: =IF($A59="","",IF(OR($C59="Aktiv",$C59="Aufwand"),$G59+$H59-$I59+$J59,$G59+$I59-$H59+$J59))
H60: =IF($A60="",0,SUMIFS(Journal!$M$5:$M$1504,Journal!$D$5:$D$1504,$A60)+IF($A60=1170,SUMIFS(Journal!$K$5:$K$1504,Journal!$J$5:$J$1504,"V",Journal!$G$5:$G$1504,"<>VI81"),0)+IF($A60=1171,SUMIFS(Journal!$K$5:$K$1504,Journal!$J$5:$J$1504,"V",Journal!$G$5:$G$1504,"VI81"),0)) -> 0 | I60: =IF($A60="",0,SUMIFS(Journal!$N$5:$N$1504,Journal!$E$5:$E$1504,$A60)+IF($A60=2200,SUMIFS(Journal!$K$5:$K$1504,Journal!$J$5:$J$1504,"U"),0)) -> 0 | J60: =IF($A60="",0,IF($A60=3809,-MWST!$H$13,IF($A60=2200,MWST!$H$13,IF($A60=6800,Anlagen!$J$3,-SUMIF(Anlagen!$B$6:$B$105,$A60,Anlagen!$J$6:$J$105))))) -> 0 | K60: =IF($A60="","",IF(OR($C60="Aktiv",$C60="Aufwand"),$G60+$H60-$I60+$J60,$G60+$I60-$H60+$J60))
H61: =IF($A61="",0,SUMIFS(Journal!$M$5:$M$1504,Journal!$D$5:$D$1504,$A61)+IF($A61=1170,SUMIFS(Journal!$K$5:$K$1504,Journal!$J$5:$J$1504,"V",Journal!$G$5:$G$1504,"<>VI81"),0)+IF($A61=1171,SUMIFS(Journal!$K$5:$K$1504,Journal!$J$5:$J$1504,"V",Journal!$G$5:$G$1504,"VI81"),0)) -> 0 | I61: =IF($A61="",0,SUMIFS(Journal!$N$5:$N$1504,Journal!$E$5:$E$1504,$A61)+IF($A61=2200,SUMIFS(Journal!$K$5:$K$1504,Journal!$J$5:$J$1504,"U"),0)) -> 0 | J61: =IF($A61="",0,IF($A61=3809,-MWST!$H$13,IF($A61=2200,MWST!$H$13,IF($A61=6800,Anlagen!$J$3,-SUMIF(Anlagen!$B$6:$B$105,$A61,Anlagen!$J$6:$J$105))))) -> 0 | K61: =IF($A61="","",IF(OR($C61="Aktiv",$C61="Aufwand"),$G61+$H61-$I61+$J61,$G61+$I61-$H61+$J61))
H62: =IF($A62="",0,SUMIFS(Journal!$M$5:$M$1504,Journal!$D$5:$D$1504,$A62)+IF($A62=1170,SUMIFS(Journal!$K$5:$K$1504,Journal!$J$5:$J$1504,"V",Journal!$G$5:$G$1504,"<>VI81"),0)+IF($A62=1171,SUMIFS(Journal!$K$5:$K$1504,Journal!$J$5:$J$1504,"V",Journal!$G$5:$G$1504,"VI81"),0)) -> 0 | I62: =IF($A62="",0,SUMIFS(Journal!$N$5:$N$1504,Journal!$E$5:$E$1504,$A62)+IF($A62=2200,SUMIFS(Journal!$K$5:$K$1504,Journal!$J$5:$J$1504,"U"),0)) -> 0 | J62: =IF($A62="",0,IF($A62=3809,-MWST!$H$13,IF($A62=2200,MWST!$H$13,IF($A62=6800,Anlagen!$J$3,-SUMIF(Anlagen!$B$6:$B$105,$A62,Anlagen!$J$6:$J$105))))) -> 0 | K62: =IF($A62="","",IF(OR($C62="Aktiv",$C62="Aufwand"),$G62+$H62-$I62+$J62,$G62+$I62-$H62+$J62))
H63: =IF($A63="",0,SUMIFS(Journal!$M$5:$M$1504,Journal!$D$5:$D$1504,$A63)+IF($A63=1170,SUMIFS(Journal!$K$5:$K$1504,Journal!$J$5:$J$1504,"V",Journal!$G$5:$G$1504,"<>VI81"),0)+IF($A63=1171,SUMIFS(Journal!$K$5:$K$1504,Journal!$J$5:$J$1504,"V",Journal!$G$5:$G$1504,"VI81"),0)) -> 0 | I63: =IF($A63="",0,SUMIFS(Journal!$N$5:$N$1504,Journal!$E$5:$E$1504,$A63)+IF($A63=2200,SUMIFS(Journal!$K$5:$K$1504,Journal!$J$5:$J$1504,"U"),0)) -> 0 | J63: =IF($A63="",0,IF($A63=3809,-MWST!$H$13,IF($A63=2200,MWST!$H$13,IF($A63=6800,Anlagen!$J$3,-SUMIF(Anlagen!$B$6:$B$105,$A63,Anlagen!$J$6:$J$105))))) -> 0 | K63: =IF($A63="","",IF(OR($C63="Aktiv",$C63="Aufwand"),$G63+$H63-$I63+$J63,$G63+$I63-$H63+$J63))
H64: =IF($A64="",0,SUMIFS(Journal!$M$5:$M$1504,Journal!$D$5:$D$1504,$A64)+IF($A64=1170,SUMIFS(Journal!$K$5:$K$1504,Journal!$J$5:$J$1504,"V",Journal!$G$5:$G$1504,"<>VI81"),0)+IF($A64=1171,SUMIFS(Journal!$K$5:$K$1504,Journal!$J$5:$J$1504,"V",Journal!$G$5:$G$1504,"VI81"),0)) -> 0 | I64: =IF($A64="",0,SUMIFS(Journal!$N$5:$N$1504,Journal!$E$5:$E$1504,$A64)+IF($A64=2200,SUMIFS(Journal!$K$5:$K$1504,Journal!$J$5:$J$1504,"U"),0)) -> 0 | J64: =IF($A64="",0,IF($A64=3809,-MWST!$H$13,IF($A64=2200,MWST!$H$13,IF($A64=6800,Anlagen!$J$3,-SUMIF(Anlagen!$B$6:$B$105,$A64,Anlagen!$J$6:$J$105))))) -> 0 | K64: =IF($A64="","",IF(OR($C64="Aktiv",$C64="Aufwand"),$G64+$H64-$I64+$J64,$G64+$I64-$H64+$J64))
H65: =IF($A65="",0,SUMIFS(Journal!$M$5:$M$1504,Journal!$D$5:$D$1504,$A65)+IF($A65=1170,SUMIFS(Journal!$K$5:$K$1504,Journal!$J$5:$J$1504,"V",Journal!$G$5:$G$1504,"<>VI81"),0)+IF($A65=1171,SUMIFS(Journal!$K$5:$K$1504,Journal!$J$5:$J$1504,"V",Journal!$G$5:$G$1504,"VI81"),0)) -> 0 | I65: =IF($A65="",0,SUMIFS(Journal!$N$5:$N$1504,Journal!$E$5:$E$1504,$A65)+IF($A65=2200,SUMIFS(Journal!$K$5:$K$1504,Journal!$J$5:$J$1504,"U"),0)) -> 0 | J65: =IF($A65="",0,IF($A65=3809,-MWST!$H$13,IF($A65=2200,MWST!$H$13,IF($A65=6800,Anlagen!$J$3,-SUMIF(Anlagen!$B$6:$B$105,$A65,Anlagen!$J$6:$J$105))))) -> 0 | K65: =IF($A65="","",IF(OR($C65="Aktiv",$C65="Aufwand"),$G65+$H65-$I65+$J65,$G65+$I65-$H65+$J65))
H66: =IF($A66="",0,SUMIFS(Journal!$M$5:$M$1504,Journal!$D$5:$D$1504,$A66)+IF($A66=1170,SUMIFS(Journal!$K$5:$K$1504,Journal!$J$5:$J$1504,"V",Journal!$G$5:$G$1504,"<>VI81"),0)+IF($A66=1171,SUMIFS(Journal!$K$5:$K$1504,Journal!$J$5:$J$1504,"V",Journal!$G$5:$G$1504,"VI81"),0)) -> 0 | I66: =IF($A66="",0,SUMIFS(Journal!$N$5:$N$1504,Journal!$E$5:$E$1504,$A66)+IF($A66=2200,SUMIFS(Journal!$K$5:$K$1504,Journal!$J$5:$J$1504,"U"),0)) -> 0 | J66: =IF($A66="",0,IF($A66=3809,-MWST!$H$13,IF($A66=2200,MWST!$H$13,IF($A66=6800,Anlagen!$J$3,-SUMIF(Anlagen!$B$6:$B$105,$A66,Anlagen!$J$6:$J$105))))) -> 0 | K66: =IF($A66="","",IF(OR($C66="Aktiv",$C66="Aufwand"),$G66+$H66-$I66+$J66,$G66+$I66-$H66+$J66))
H67: =IF($A67="",0,SUMIFS(Journal!$M$5:$M$1504,Journal!$D$5:$D$1504,$A67)+IF($A67=1170,SUMIFS(Journal!$K$5:$K$1504,Journal!$J$5:$J$1504,"V",Journal!$G$5:$G$1504,"<>VI81"),0)+IF($A67=1171,SUMIFS(Journal!$K$5:$K$1504,Journal!$J$5:$J$1504,"V",Journal!$G$5:$G$1504,"VI81"),0)) -> 0 | I67: =IF($A67="",0,SUMIFS(Journal!$N$5:$N$1504,Journal!$E$5:$E$1504,$A67)+IF($A67=2200,SUMIFS(Journal!$K$5:$K$1504,Journal!$J$5:$J$1504,"U"),0)) -> 0 | J67: =IF($A67="",0,IF($A67=3809,-MWST!$H$13,IF($A67=2200,MWST!$H$13,IF($A67=6800,Anlagen!$J$3,-SUMIF(Anlagen!$B$6:$B$105,$A67,Anlagen!$J$6:$J$105))))) -> 0 | K67: =IF($A67="","",IF(OR($C67="Aktiv",$C67="Aufwand"),$G67+$H67-$I67+$J67,$G67+$I67-$H67+$J67))
H68: =IF($A68="",0,SUMIFS(Journal!$M$5:$M$1504,Journal!$D$5:$D$1504,$A68)+IF($A68=1170,SUMIFS(Journal!$K$5:$K$1504,Journal!$J$5:$J$1504,"V",Journal!$G$5:$G$1504,"<>VI81"),0)+IF($A68=1171,SUMIFS(Journal!$K$5:$K$1504,Journal!$J$5:$J$1504,"V",Journal!$G$5:$G$1504,"VI81"),0)) -> 0 | I68: =IF($A68="",0,SUMIFS(Journal!$N$5:$N$1504,Journal!$E$5:$E$1504,$A68)+IF($A68=2200,SUMIFS(Journal!$K$5:$K$1504,Journal!$J$5:$J$1504,"U"),0)) -> 0 | J68: =IF($A68="",0,IF($A68=3809,-MWST!$H$13,IF($A68=2200,MWST!$H$13,IF($A68=6800,Anlagen!$J$3,-SUMIF(Anlagen!$B$6:$B$105,$A68,Anlagen!$J$6:$J$105))))) -> 0 | K68: =IF($A68="","",IF(OR($C68="Aktiv",$C68="Aufwand"),$G68+$H68-$I68+$J68,$G68+$I68-$H68+$J68))
H69: =IF($A69="",0,SUMIFS(Journal!$M$5:$M$1504,Journal!$D$5:$D$1504,$A69)+IF($A69=1170,SUMIFS(Journal!$K$5:$K$1504,Journal!$J$5:$J$1504,"V",Journal!$G$5:$G$1504,"<>VI81"),0)+IF($A69=1171,SUMIFS(Journal!$K$5:$K$1504,Journal!$J$5:$J$1504,"V",Journal!$G$5:$G$1504,"VI81"),0)) -> 0 | I69: =IF($A69="",0,SUMIFS(Journal!$N$5:$N$1504,Journal!$E$5:$E$1504,$A69)+IF($A69=2200,SUMIFS(Journal!$K$5:$K$1504,Journal!$J$5:$J$1504,"U"),0)) -> 0 | J69: =IF($A69="",0,IF($A69=3809,-MWST!$H$13,IF($A69=2200,MWST!$H$13,IF($A69=6800,Anlagen!$J$3,-SUMIF(Anlagen!$B$6:$B$105,$A69,Anlagen!$J$6:$J$105))))) -> 0 | K69: =IF($A69="","",IF(OR($C69="Aktiv",$C69="Aufwand"),$G69+$H69-$I69+$J69,$G69+$I69-$H69+$J69))
... H90: =IF($A90="",0,SUMIFS(Journal!$M$5:$M$1504,Journal!$D$5:$D$1504,$A90)+IF($A90=1170,SUMIFS(Journal!$K$5:$K$1504,Journal!$J$5:$J$1504,"V",Journal!$G$5:$G$1504,"<>VI81"),0)+IF($A90=1171,SUMIFS(Journal!$K$5:$K$1504,Journal!$J$5:$J$1504,"V",Journal!$G$5:$G$1504,"VI81"),0)) -> 0 | I90: =IF($A90="",0,SUMIFS(Journal!$N$5:$N$1504,Journal!$E$5:$E$1504,$A90)+IF($A90=2200,SUMIFS(Journal!$K$5:$K$1504,Journal!$J$5:$J$1504,"U"),0)) -> 0 | J90: =IF($A90="",0,IF($A90=3809,-MWST!$H$13,IF($A90=2200,MWST!$H$13,IF($A90=6800,Anlagen!$J$3,-SUMIF(Anlagen!$B$6:$B$105,$A90,Anlagen!$J$6:$J$105))))) -> 0 | K90: =IF($A90="","",IF(OR($C90="Aktiv",$C90="Aufwand"),$G90+$H90-$I90+$J90,$G90+$I90-$H90+$J90))

Sheet Journal
A1: Journal – alle Buchungen
A2: Pro Beleg eine Zeile: Soll-Konto an Haben-Konto, Betrag INKL. MWST, MWST-Code. Grau = automatisch.
A3: Beispiel: Kunde zahlt Rechnung bar → Soll 1000 (Kasse), Haben 3000 (Werkstatt). Einkauf Teile auf Rechnung → Soll 4000, Haben 2000. Die Zeilen 'BEISPIEL' löschen, sobald du eigene Daten erfasst.
A4: Datum | B4: Beleg-Nr. | C4: Buchungstext | D4: Soll-Konto | E4: Haben-Konto | F4: Betrag inkl. MWST | G4: MWST-Code | H4: MWST-Satz | I4: Art | J4: Art (aktiv) | K4: MWST-Betrag | L4: Netto | M4: Soll-Buchung | N4: Haben-Buchung | O4: Monat | P4: Quartal | Q4: Semester | R4: Saldo-Grp Haben | S4: Saldo-Grp Soll | T4: Typ Soll | U4: Typ Haben | V4: Prüfung | W4: Auszug-Nr
A5: 46031 | B5: R-001 | C5: BEISPIEL Service + Bremsen VW Polo, Arbeit | D5: 1100 | E5: 3000 | F5: 1621.5 | G5: U81 | H5: =IF($G5="",0,IFERROR(INDEX(Einstellungen!$G$5:$G$11,MATCH($G5,Einstellungen!$E$5:$E$11,0)),0)) -> 0.081 | I5: =IF($G5="","-",IFERROR(INDEX(Einstellungen!$H$5:$H$11,MATCH($G5,Einstellungen!$E$5:$E$11,0)),"-")) -> U | J5: =IF(AND(Einstellungen!$B$8="Ja",Einstellungen!$B$9="Effektiv"),$I5,"-") -> - | K5: =IF(OR($F5="",$J5="-"),0,ROUND($F5-$F5/(1+$H5),2)) -> 0 | L5: =IF($F5="",0,$F5-$K5) -> 1621.5 | M5: =IF($F5="",0,IF($J5="V",$L5,$F5)) -> 1621.5 | N5: =IF($F5="",0,IF($J5="U",$L5,$F5)) -> 1621.5 | O5: =IF($A5="","",MONTH($A5)) -> 1 | P5: =IF($A5="","",ROUNDUP(MONTH($A5)/3,0)) -> 1 | Q5: =IF($A5="","",IF(MONTH($A5)<=6,1,2)) -> 1 | R5: =IF($E5="","",IFERROR(INDEX(Kontenplan!$F$5:$F$90,MATCH($E5,Kontenplan!$A$5:$A$90,0)),"")) -> 1 | S5: =IF($D5="","",IFERROR(INDEX(Kontenplan!$F$5:$F$90,MATCH($D5,Kontenplan!$A$5:$A$90,0)),"")) -> 0 | T5: =IF($D5="","",IFERROR(INDEX(Kontenplan!$C$5:$C$90,MATCH($D5,Kontenplan!$A$5:$A$90,0)),"?")) -> Aktiv | U5: =IF($E5="","",IFERROR(INDEX(Kontenplan!$C$5:$C$90,MATCH($E5,Kontenplan!$A$5:$A$90,0)),"?")) -> Ertrag | V5: =IF($F5="","",IF(OR($D5="",$E5="",$T5="?",$U5="?"),"Konto prüfen!",IF($A5="","Datum fehlt",IF(YEAR($A5)<>Einstellungen!$B$7,"anderes Jahr!",IF($G5="","MWST-Code fehlt","OK"))))) -> OK | W5: =IF($F5="","",IF(OR($D5=Kontoauszug!$C$4,$E5=Kontoauszug!$C$4),MAX(W$4:W4)+1,""))
A6: 46031 | B6: R-001 | C6: BEISPIEL Service VW Polo, Ersatzteile | D6: 1100 | E6: 3200 | F6: 864.8 | G6: U81 | H6: =IF($G6="",0,IFERROR(INDEX(Einstellungen!$G$5:$G$11,MATCH($G6,Einstellungen!$E$5:$E$11,0)),0)) -> 0.081 | I6: =IF($G6="","-",IFERROR(INDEX(Einstellungen!$H$5:$H$11,MATCH($G6,Einstellungen!$E$5:$E$11,0)),"-")) -> U | J6: =IF(AND(Einstellungen!$B$8="Ja",Einstellungen!$B$9="Effektiv"),$I6,"-") -> - | K6: =IF(OR($F6="",$J6="-"),0,ROUND($F6-$F6/(1+$H6),2)) -> 0 | L6: =IF($F6="",0,$F6-$K6) -> 864.8 | M6: =IF($F6="",0,IF($J6="V",$L6,$F6)) -> 864.8 | N6: =IF($F6="",0,IF($J6="U",$L6,$F6)) -> 864.8 | O6: =IF($A6="","",MONTH($A6)) -> 1 | P6: =IF($A6="","",ROUNDUP(MONTH($A6)/3,0)) -> 1 | Q6: =IF($A6="","",IF(MONTH($A6)<=6,1,2)) -> 1 | R6: =IF($E6="","",IFERROR(INDEX(Kontenplan!$F$5:$F$90,MATCH($E6,Kontenplan!$A$5:$A$90,0)),"")) -> 1 | S6: =IF($D6="","",IFERROR(INDEX(Kontenplan!$F$5:$F$90,MATCH($D6,Kontenplan!$A$5:$A$90,0)),"")) -> 0 | T6: =IF($D6="","",IFERROR(INDEX(Kontenplan!$C$5:$C$90,MATCH($D6,Kontenplan!$A$5:$A$90,0)),"?")) -> Aktiv | U6: =IF($E6="","",IFERROR(INDEX(Kontenplan!$C$5:$C$90,MATCH($E6,Kontenplan!$A$5:$A$90,0)),"?")) -> Ertrag | V6: =IF($F6="","",IF(OR($D6="",$E6="",$T6="?",$U6="?"),"Konto prüfen!",IF($A6="","Datum fehlt",IF(YEAR($A6)<>Einstellungen!$B$7,"anderes Jahr!",IF($G6="","MWST-Code fehlt","OK"))))) -> OK | W6: =IF($F6="","",IF(OR($D6=Kontoauszug!$C$4,$E6=Kontoauszug!$C$4),MAX(W$4:W5)+1,""))
A7: 46034 | B7: K-001 | C7: BEISPIEL Einkauf Ersatzteile Grosshändler | D7: 4000 | E7: 2000 | F7: 1297.2 | G7: V81 | H7: =IF($G7="",0,IFERROR(INDEX(Einstellungen!$G$5:$G$11,MATCH($G7,Einstellungen!$E$5:$E$11,0)),0)) -> 0.081 | I7: =IF($G7="","-",IFERROR(INDEX(Einstellungen!$H$5:$H$11,MATCH($G7,Einstellungen!$E$5:$E$11,0)),"-")) -> V | J7: =IF(AND(Einstellungen!$B$8="Ja",Einstellungen!$B$9="Effektiv"),$I7,"-") -> - | K7: =IF(OR($F7="",$J7="-"),0,ROUND($F7-$F7/(1+$H7),2)) -> 0 | L7: =IF($F7="",0,$F7-$K7) -> 1297.2 | M7: =IF($F7="",0,IF($J7="V",$L7,$F7)) -> 1297.2 | N7: =IF($F7="",0,IF($J7="U",$L7,$F7)) -> 1297.2 | O7: =IF($A7="","",MONTH($A7)) -> 1 | P7: =IF($A7="","",ROUNDUP(MONTH($A7)/3,0)) -> 1 | Q7: =IF($A7="","",IF(MONTH($A7)<=6,1,2)) -> 1 | R7: =IF($E7="","",IFERROR(INDEX(Kontenplan!$F$5:$F$90,MATCH($E7,Kontenplan!$A$5:$A$90,0)),"")) -> 0 | S7: =IF($D7="","",IFERROR(INDEX(Kontenplan!$F$5:$F$90,MATCH($D7,Kontenplan!$A$5:$A$90,0)),"")) -> 0 | T7: =IF($D7="","",IFERROR(INDEX(Kontenplan!$C$5:$C$90,MATCH($D7,Kontenplan!$A$5:$A$90,0)),"?")) -> Aufwand | U7: =IF($E7="","",IFERROR(INDEX(Kontenplan!$C$5:$C$90,MATCH($E7,Kontenplan!$A$5:$A$90,0)),"?")) -> Passiv | V7: =IF($F7="","",IF(OR($D7="",$E7="",$T7="?",$U7="?"),"Konto prüfen!",IF($A7="","Datum fehlt",IF(YEAR($A7)<>Einstellungen!$B$7,"anderes Jahr!",IF($G7="","MWST-Code fehlt","OK"))))) -> OK | W7: =IF($F7="","",IF(OR($D7=Kontoauszug!$C$4,$E7=Kontoauszug!$C$4),MAX(W$4:W6)+1,""))
A8: 46037 | B8: Q-001 | C8: BEISPIEL Barverkauf Pneuwechsel | D8: 1000 | E8: 3210 | F8: 120 | G8: U81 | H8: =IF($G8="",0,IFERROR(INDEX(Einstellungen!$G$5:$G$11,MATCH($G8,Einstellungen!$E$5:$E$11,0)),0)) -> 0.081 | I8: =IF($G8="","-",IFERROR(INDEX(Einstellungen!$H$5:$H$11,MATCH($G8,Einstellungen!$E$5:$E$11,0)),"-")) -> U | J8: =IF(AND(Einstellungen!$B$8="Ja",Einstellungen!$B$9="Effektiv"),$I8,"-") -> - | K8: =IF(OR($F8="",$J8="-"),0,ROUND($F8-$F8/(1+$H8),2)) -> 0 | L8: =IF($F8="",0,$F8-$K8) -> 120 | M8: =IF($F8="",0,IF($J8="V",$L8,$F8)) -> 120 | N8: =IF($F8="",0,IF($J8="U",$L8,$F8)) -> 120 | O8: =IF($A8="","",MONTH($A8)) -> 1 | P8: =IF($A8="","",ROUNDUP(MONTH($A8)/3,0)) -> 1 | Q8: =IF($A8="","",IF(MONTH($A8)<=6,1,2)) -> 1 | R8: =IF($E8="","",IFERROR(INDEX(Kontenplan!$F$5:$F$90,MATCH($E8,Kontenplan!$A$5:$A$90,0)),"")) -> 1 | S8: =IF($D8="","",IFERROR(INDEX(Kontenplan!$F$5:$F$90,MATCH($D8,Kontenplan!$A$5:$A$90,0)),"")) -> 0 | T8: =IF($D8="","",IFERROR(INDEX(Kontenplan!$C$5:$C$90,MATCH($D8,Kontenplan!$A$5:$A$90,0)),"?")) -> Aktiv | U8: =IF($E8="","",IFERROR(INDEX(Kontenplan!$C$5:$C$90,MATCH($E8,Kontenplan!$A$5:$A$90,0)),"?")) -> Ertrag | V8: =IF($F8="","",IF(OR($D8="",$E8="",$T8="?",$U8="?"),"Konto prüfen!",IF($A8="","Datum fehlt",IF(YEAR($A8)<>Einstellungen!$B$7,"anderes Jahr!",IF($G8="","MWST-Code fehlt","OK"))))) -> OK | W8: =IF($F8="","",IF(OR($D8=Kontoauszug!$C$4,$E8=Kontoauszug!$C$4),MAX(W$4:W7)+1,""))
A9: 46047 | B9: L-001 | C9: BEISPIEL Lohn Mechaniker Januar (netto) | D9: 5000 | E9: 1020 | F9: 4650 | G9: - | H9: =IF($G9="",0,IFERROR(INDEX(Einstellungen!$G$5:$G$11,MATCH($G9,Einstellungen!$E$5:$E$11,0)),0)) -> 0 | I9: =IF($G9="","-",IFERROR(INDEX(Einstellungen!$H$5:$H$11,MATCH($G9,Einstellungen!$E$5:$E$11,0)),"-")) -> - | J9: =IF(AND(Einstellungen!$B$8="Ja",Einstellungen!$B$9="Effektiv"),$I9,"-") -> - | K9: =IF(OR($F9="",$J9="-"),0,ROUND($F9-$F9/(1+$H9),2)) -> 0 | L9: =IF($F9="",0,$F9-$K9) -> 4650 | M9: =IF($F9="",0,IF($J9="V",$L9,$F9)) -> 4650 | N9: =IF($F9="",0,IF($J9="U",$L9,$F9)) -> 4650 | O9: =IF($A9="","",MONTH($A9)) -> 1 | P9: =IF($A9="","",ROUNDUP(MONTH($A9)/3,0)) -> 1 | Q9: =IF($A9="","",IF(MONTH($A9)<=6,1,2)) -> 1 | R9: =IF($E9="","",IFERROR(INDEX(Kontenplan!$F$5:$F$90,MATCH($E9,Kontenplan!$A$5:$A$90,0)),"")) -> 0 | S9: =IF($D9="","",IFERROR(INDEX(Kontenplan!$F$5:$F$90,MATCH($D9,Kontenplan!$A$5:$A$90,0)),"")) -> 0 | T9: =IF($D9="","",IFERROR(INDEX(Kontenplan!$C$5:$C$90,MATCH($D9,Kontenplan!$A$5:$A$90,0)),"?")) -> Aufwand | U9: =IF($E9="","",IFERROR(INDEX(Kontenplan!$C$5:$C$90,MATCH($E9,Kontenplan!$A$5:$A$90,0)),"?")) -> Aktiv | V9: =IF($F9="","",IF(OR($D9="",$E9="",$T9="?",$U9="?"),"Konto prüfen!",IF($A9="","Datum fehlt",IF(YEAR($A9)<>Einstellungen!$B$7,"anderes Jahr!",IF($G9="","MWST-Code fehlt","OK"))))) -> OK | W9: =IF($F9="","",IF(OR($D9=Kontoauszug!$C$4,$E9=Kontoauszug!$C$4),MAX(W$4:W8)+1,"")) -> 1
A10: 46047 | B10: L-001 | C10: BEISPIEL AN-Abzüge Mechaniker Januar | D10: 5000 | E10: 2270 | F10: 550 | G10: - | H10: =IF($G10="",0,IFERROR(INDEX(Einstellungen!$G$5:$G$11,MATCH($G10,Einstellungen!$E$5:$E$11,0)),0)) -> 0 | I10: =IF($G10="","-",IFERROR(INDEX(Einstellungen!$H$5:$H$11,MATCH($G10,Einstellungen!$E$5:$E$11,0)),"-")) -> - | J10: =IF(AND(Einstellungen!$B$8="Ja",Einstellungen!$B$9="Effektiv"),$I10,"-") -> - | K10: =IF(OR($F10="",$J10="-"),0,ROUND($F10-$F10/(1+$H10),2)) -> 0 | L10: =IF($F10="",0,$F10-$K10) -> 550 | M10: =IF($F10="",0,IF($J10="V",$L10,$F10)) -> 550 | N10: =IF($F10="",0,IF($J10="U",$L10,$F10)) -> 550 | O10: =IF($A10="","",MONTH($A10)) -> 1 | P10: =IF($A10="","",ROUNDUP(MONTH($A10)/3,0)) -> 1 | Q10: =IF($A10="","",IF(MONTH($A10)<=6,1,2)) -> 1 | R10: =IF($E10="","",IFERROR(INDEX(Kontenplan!$F$5:$F$90,MATCH($E10,Kontenplan!$A$5:$A$90,0)),"")) -> 0 | S10: =IF($D10="","",IFERROR(INDEX(Kontenplan!$F$5:$F$90,MATCH($D10,Kontenplan!$A$5:$A$90,0)),"")) -> 0 | T10: =IF($D10="","",IFERROR(INDEX(Kontenplan!$C$5:$C$90,MATCH($D10,Kontenplan!$A$5:$A$90,0)),"?")) -> Aufwand | U10: =IF($E10="","",IFERROR(INDEX(Kontenplan!$C$5:$C$90,MATCH($E10,Kontenplan!$A$5:$A$90,0)),"?")) -> Passiv | V10: =IF($F10="","",IF(OR($D10="",$E10="",$T10="?",$U10="?"),"Konto prüfen!",IF($A10="","Datum fehlt",IF(YEAR($A10)<>Einstellungen!$B$7,"anderes Jahr!",IF($G10="","MWST-Code fehlt","OK"))))) -> OK | W10: =IF($F10="","",IF(OR($D10=Kontoauszug!$C$4,$E10=Kontoauszug!$C$4),MAX(W$4:W9)+1,""))
A11: 46047 | B11: L-001 | C11: BEISPIEL AG-Beiträge Sozialversicherungen Jan. | D11: 5700 | E11: 2270 | F11: 780 | G11: - | H11: =IF($G11="",0,IFERROR(INDEX(Einstellungen!$G$5:$G$11,MATCH($G11,Einstellungen!$E$5:$E$11,0)),0)) -> 0 | I11: =IF($G11="","-",IFERROR(INDEX(Einstellungen!$H$5:$H$11,MATCH($G11,Einstellungen!$E$5:$E$11,0)),"-")) -> - | J11: =IF(AND(Einstellungen!$B$8="Ja",Einstellungen!$B$9="Effektiv"),$I11,"-") -> - | K11: =IF(OR($F11="",$J11="-"),0,ROUND($F11-$F11/(1+$H11),2)) -> 0 | L11: =IF($F11="",0,$F11-$K11) -> 780 | M11: =IF($F11="",0,IF($J11="V",$L11,$F11)) -> 780 | N11: =IF($F11="",0,IF($J11="U",$L11,$F11)) -> 780 | O11: =IF($A11="","",MONTH($A11)) -> 1 | P11: =IF($A11="","",ROUNDUP(MONTH($A11)/3,0)) -> 1 | Q11: =IF($A11="","",IF(MONTH($A11)<=6,1,2)) -> 1 | R11: =IF($E11="","",IFERROR(INDEX(Kontenplan!$F$5:$F$90,MATCH($E11,Kontenplan!$A$5:$A$90,0)),"")) -> 0 | S11: =IF($D11="","",IFERROR(INDEX(Kontenplan!$F$5:$F$90,MATCH($D11,Kontenplan!$A$5:$A$90,0)),"")) -> 0 | T11: =IF($D11="","",IFERROR(INDEX(Kontenplan!$C$5:$C$90,MATCH($D11,Kontenplan!$A$5:$A$90,0)),"?")) -> Aufwand | U11: =IF($E11="","",IFERROR(INDEX(Kontenplan!$C$5:$C$90,MATCH($E11,Kontenplan!$A$5:$A$90,0)),"?")) -> Passiv | V11: =IF($F11="","",IF(OR($D11="",$E11="",$T11="?",$U11="?"),"Konto prüfen!",IF($A11="","Datum fehlt",IF(YEAR($A11)<>Einstellungen!$B$7,"anderes Jahr!",IF($G11="","MWST-Code fehlt","OK"))))) -> OK | W11: =IF($F11="","",IF(OR($D11=Kontoauszug!$C$4,$E11=Kontoauszug!$C$4),MAX(W$4:W10)+1,""))
A12: 46053 | B12: B-001 | C12: BEISPIEL Miete Werkstatt Januar | D12: 6000 | E12: 1020 | F12: 3500 | G12: - | H12: =IF($G12="",0,IFERROR(INDEX(Einstellungen!$G$5:$G$11,MATCH($G12,Einstellungen!$E$5:$E$11,0)),0)) -> 0 | I12: =IF($G12="","-",IFERROR(INDEX(Einstellungen!$H$5:$H$11,MATCH($G12,Einstellungen!$E$5:$E$11,0)),"-")) -> - | J12: =IF(AND(Einstellungen!$B$8="Ja",Einstellungen!$B$9="Effektiv"),$I12,"-") -> - | K12: =IF(OR($F12="",$J12="-"),0,ROUND($F12-$F12/(1+$H12),2)) -> 0 | L12: =IF($F12="",0,$F12-$K12) -> 3500 | M12: =IF($F12="",0,IF($J12="V",$L12,$F12)) -> 3500 | N12: =IF($F12="",0,IF($J12="U",$L12,$F12)) -> 3500 | O12: =IF($A12="","",MONTH($A12)) -> 1 | P12: =IF($A12="","",ROUNDUP(MONTH($A12)/3,0)) -> 1 | Q12: =IF($A12="","",IF(MONTH($A12)<=6,1,2)) -> 1 | R12: =IF($E12="","",IFERROR(INDEX(Kontenplan!$F$5:$F$90,MATCH($E12,Kontenplan!$A$5:$A$90,0)),"")) -> 0 | S12: =IF($D12="","",IFERROR(INDEX(Kontenplan!$F$5:$F$90,MATCH($D12,Kontenplan!$A$5:$A$90,0)),"")) -> 0 | T12: =IF($D12="","",IFERROR(INDEX(Kontenplan!$C$5:$C$90,MATCH($D12,Kontenplan!$A$5:$A$90,0)),"?")) -> Aufwand | U12: =IF($E12="","",IFERROR(INDEX(Kontenplan!$C$5:$C$90,MATCH($E12,Kontenplan!$A$5:$A$90,0)),"?")) -> Aktiv | V12: =IF($F12="","",IF(OR($D12="",$E12="",$T12="?",$U12="?"),"Konto prüfen!",IF($A12="","Datum fehlt",IF(YEAR($A12)<>Einstellungen!$B$7,"anderes Jahr!",IF($G12="","MWST-Code fehlt","OK"))))) -> OK | W12: =IF($F12="","",IF(OR($D12=Kontoauszug!$C$4,$E12=Kontoauszug!$C$4),MAX(W$4:W11)+1,"")) -> 2
A13: 46056 | B13: B-002 | C13: BEISPIEL Strom Januar | D13: 6400 | E13: 1020 | F13: 486.6 | G13: V81 | H13: =IF($G13="",0,IFERROR(INDEX(Einstellungen!$G$5:$G$11,MATCH($G13,Einstellungen!$E$5:$E$11,0)),0)) -> 0.081 | I13: =IF($G13="","-",IFERROR(INDEX(Einstellungen!$H$5:$H$11,MATCH($G13,Einstellungen!$E$5:$E$11,0)),"-")) -> V | J13: =IF(AND(Einstellungen!$B$8="Ja",Einstellungen!$B$9="Effektiv"),$I13,"-") -> - | K13: =IF(OR($F13="",$J13="-"),0,ROUND($F13-$F13/(1+$H13),2)) -> 0 | L13: =IF($F13="",0,$F13-$K13) -> 486.6 | M13: =IF($F13="",0,IF($J13="V",$L13,$F13)) -> 486.6 | N13: =IF($F13="",0,IF($J13="U",$L13,$F13)) -> 486.6 | O13: =IF($A13="","",MONTH($A13)) -> 2 | P13: =IF($A13="","",ROUNDUP(MONTH($A13)/3,0)) -> 1 | Q13: =IF($A13="","",IF(MONTH($A13)<=6,1,2)) -> 1 | R13: =IF($E13="","",IFERROR(INDEX(Kontenplan!$F$5:$F$90,MATCH($E13,Kontenplan!$A$5:$A$90,0)),"")) -> 0 | S13: =IF($D13="","",IFERROR(INDEX(Kontenplan!$F$5:$F$90,MATCH($D13,Kontenplan!$A$5:$A$90,0)),"")) -> 0 | T13: =IF($D13="","",IFERROR(INDEX(Kontenplan!$C$5:$C$90,MATCH($D13,Kontenplan!$A$5:$A$90,0)),"?")) -> Aufwand | U13: =IF($E13="","",IFERROR(INDEX(Kontenplan!$C$5:$C$90,MATCH($E13,Kontenplan!$A$5:$A$90,0)),"?")) -> Aktiv | V13: =IF($F13="","",IF(OR($D13="",$E13="",$T13="?",$U13="?"),"Konto prüfen!",IF($A13="","Datum fehlt",IF(YEAR($A13)<>Einstellungen!$B$7,"anderes Jahr!",IF($G13="","MWST-Code fehlt","OK"))))) -> OK | W13: =IF($F13="","",IF(OR($D13=Kontoauszug!$C$4,$E13=Kontoauszug!$C$4),MAX(W$4:W12)+1,"")) -> 3
A14: 46058 | B14: B-003 | C14: BEISPIEL Zahlungseingang R-001 | D14: 1020 | E14: 1100 | F14: 2486.3 | G14: - | H14: =IF($G14="",0,IFERROR(INDEX(Einstellungen!$G$5:$G$11,MATCH($G14,Einstellungen!$E$5:$E$11,0)),0)) -> 0 | I14: =IF($G14="","-",IFERROR(INDEX(Einstellungen!$H$5:$H$11,MATCH($G14,Einstellungen!$E$5:$E$11,0)),"-")) -> - | J14: =IF(AND(Einstellungen!$B$8="Ja",Einstellungen!$B$9="Effektiv"),$I14,"-") -> - | K14: =IF(OR($F14="",$J14="-"),0,ROUND($F14-$F14/(1+$H14),2)) -> 0 | L14: =IF($F14="",0,$F14-$K14) -> 2486.3 | M14: =IF($F14="",0,IF($J14="V",$L14,$F14)) -> 2486.3 | N14: =IF($F14="",0,IF($J14="U",$L14,$F14)) -> 2486.3 | O14: =IF($A14="","",MONTH($A14)) -> 2 | P14: =IF($A14="","",ROUNDUP(MONTH($A14)/3,0)) -> 1 | Q14: =IF($A14="","",IF(MONTH($A14)<=6,1,2)) -> 1 | R14: =IF($E14="","",IFERROR(INDEX(Kontenplan!$F$5:$F$90,MATCH($E14,Kontenplan!$A$5:$A$90,0)),"")) -> 0 | S14: =IF($D14="","",IFERROR(INDEX(Kontenplan!$F$5:$F$90,MATCH($D14,Kontenplan!$A$5:$A$90,0)),"")) -> 0 | T14: =IF($D14="","",IFERROR(INDEX(Kontenplan!$C$5:$C$90,MATCH($D14,Kontenplan!$A$5:$A$90,0)),"?")) -> Aktiv | U14: =IF($E14="","",IFERROR(INDEX(Kontenplan!$C$5:$C$90,MATCH($E14,Kontenplan!$A$5:$A$90,0)),"?")) -> Aktiv | V14: =IF($F14="","",IF(OR($D14="",$E14="",$T14="?",$U14="?"),"Konto prüfen!",IF($A14="","Datum fehlt",IF(YEAR($A14)<>Einstellungen!$B$7,"anderes Jahr!",IF($G14="","MWST-Code fehlt","OK"))))) -> OK | W14: =IF($F14="","",IF(OR($D14=Kontoauszug!$C$4,$E14=Kontoauszug!$C$4),MAX(W$4:W13)+1,"")) -> 4
A15: 46063 | B15: F-001 | C15: BEISPIEL Ankauf Occasion VW Golf von Privat | D15: 4200 | E15: 1020 | F15: 12000 | G15: - | H15: =IF($G15="",0,IFERROR(INDEX(Einstellungen!$G$5:$G$11,MATCH($G15,Einstellungen!$E$5:$E$11,0)),0)) -> 0 | I15: =IF($G15="","-",IFERROR(INDEX(Einstellungen!$H$5:$H$11,MATCH($G15,Einstellungen!$E$5:$E$11,0)),"-")) -> - | J15: =IF(AND(Einstellungen!$B$8="Ja",Einstellungen!$B$9="Effektiv"),$I15,"-") -> - | K15: =IF(OR($F15="",$J15="-"),0,ROUND($F15-$F15/(1+$H15),2)) -> 0 | L15: =IF($F15="",0,$F15-$K15) -> 12000 | M15: =IF($F15="",0,IF($J15="V",$L15,$F15)) -> 12000 | N15: =IF($F15="",0,IF($J15="U",$L15,$F15)) -> 12000 | O15: =IF($A15="","",MONTH($A15)) -> 2 | P15: =IF($A15="","",ROUNDUP(MONTH($A15)/3,0)) -> 1 | Q15: =IF($A15="","",IF(MONTH($A15)<=6,1,2)) -> 1 | R15: =IF($E15="","",IFERROR(INDEX(Kontenplan!$F$5:$F$90,MATCH($E15,Kontenplan!$A$5:$A$90,0)),"")) -> 0 | S15: =IF($D15="","",IFERROR(INDEX(Kontenplan!$F$5:$F$90,MATCH($D15,Kontenplan!$A$5:$A$90,0)),"")) -> 0 | T15: =IF($D15="","",IFERROR(INDEX(Kontenplan!$C$5:$C$90,MATCH($D15,Kontenplan!$A$5:$A$90,0)),"?")) -> Aufwand | U15: =IF($E15="","",IFERROR(INDEX(Kontenplan!$C$5:$C$90,MATCH($E15,Kontenplan!$A$5:$A$90,0)),"?")) -> Aktiv | V15: =IF($F15="","",IF(OR($D15="",$E15="",$T15="?",$U15="?"),"Konto prüfen!",IF($A15="","Datum fehlt",IF(YEAR($A15)<>Einstellungen!$B$7,"anderes Jahr!",IF($G15="","MWST-Code fehlt","OK"))))) -> OK | W15: =IF($F15="","",IF(OR($D15=Kontoauszug!$C$4,$E15=Kontoauszug!$C$4),MAX(W$4:W14)+1,"")) -> 5
A16: 46073 | B16: B-004 | C16: BEISPIEL Betriebshaftpflicht 2026 | D16: 6300 | E16: 1020 | F16: 2400 | G16: - | H16: =IF($G16="",0,IFERROR(INDEX(Einstellungen!$G$5:$G$11,MATCH($G16,Einstellungen!$E$5:$E$11,0)),0)) -> 0 | I16: =IF($G16="","-",IFERROR(INDEX(Einstellungen!$H$5:$H$11,MATCH($G16,Einstellungen!$E$5:$E$11,0)),"-")) -> - | J16: =IF(AND(Einstellungen!$B$8="Ja",Einstellungen!$B$9="Effektiv"),$I16,"-") -> - | K16: =IF(OR($F16="",$J16="-"),0,ROUND($F16-$F16/(1+$H16),2)) -> 0 | L16: =IF($F16="",0,$F16-$K16) -> 2400 | M16: =IF($F16="",0,IF($J16="V",$L16,$F16)) -> 2400 | N16: =IF($F16="",0,IF($J16="U",$L16,$F16)) -> 2400 | O16: =IF($A16="","",MONTH($A16)) -> 2 | P16: =IF($A16="","",ROUNDUP(MONTH($A16)/3,0)) -> 1 | Q16: =IF($A16="","",IF(MONTH($A16)<=6,1,2)) -> 1 | R16: =IF($E16="","",IFERROR(INDEX(Kontenplan!$F$5:$F$90,MATCH($E16,Kontenplan!$A$5:$A$90,0)),"")) -> 0 | S16: =IF($D16="","",IFERROR(INDEX(Kontenplan!$F$5:$F$90,MATCH($D16,Kontenplan!$A$5:$A$90,0)),"")) -> 0 | T16: =IF($D16="","",IFERROR(INDEX(Kontenplan!$C$5:$C$90,MATCH($D16,Kontenplan!$A$5:$A$90,0)),"?")) -> Aufwand | U16: =IF($E16="","",IFERROR(INDEX(Kontenplan!$C$5:$C$90,MATCH($E16,Kontenplan!$A$5:$A$90,0)),"?")) -> Aktiv | V16: =IF($F16="","",IF(OR($D16="",$E16="",$T16="?",$U16="?"),"Konto prüfen!",IF($A16="","Datum fehlt",IF(YEAR($A16)<>Einstellungen!$B$7,"anderes Jahr!",IF($G16="","MWST-Code fehlt","OK"))))) -> OK | W16: =IF($F16="","",IF(OR($D16=Kontoauszug!$C$4,$E16=Kontoauszug!$C$4),MAX(W$4:W15)+1,"")) -> 6
... A20: 46112 | B20: B-006 | C20: BEISPIEL Bankspesen/Zins Q1 | D20: 6900 | E20: 1020 | F20: 85 | G20: - | H20: =IF($G20="",0,IFERROR(INDEX(Einstellungen!$G$5:$G$11,MATCH($G20,Einstellungen!$E$5:$E$11,0)),0)) -> 0 | I20: =IF($G20="","-",IFERROR(INDEX(Einstellungen!$H$5:$H$11,MATCH($G20,Einstellungen!$E$5:$E$11,0)),"-")) -> - | J20: =IF(AND(Einstellungen!$B$8="Ja",Einstellungen!$B$9="Effektiv"),$I20,"-") -> - | K20: =IF(OR($F20="",$J20="-"),0,ROUND($F20-$F20/(1+$H20),2)) -> 0 | L20: =IF($F20="",0,$F20-$K20) -> 85 | M20: =IF($F20="",0,IF($J20="V",$L20,$F20)) -> 85 | N20: =IF($F20="",0,IF($J20="U",$L20,$F20)) -> 85 | O20: =IF($A20="","",MONTH($A20)) -> 3 | P20: =IF($A20="","",ROUNDUP(MONTH($A20)/3,0)) -> 1 | Q20: =IF($A20="","",IF(MONTH($A20)<=6,1,2)) -> 1 | R20: =IF($E20="","",IFERROR(INDEX(Kontenplan!$F$5:$F$90,MATCH($E20,Kontenplan!$A$5:$A$90,0)),"")) -> 0 | S20: =IF($D20="","",IFERROR(INDEX(Kontenplan!$F$5:$F$90,MATCH($D20,Kontenplan!$A$5:$A$90,0)),"")) -> 0 | T20: =IF($D20="","",IFERROR(INDEX(Kontenplan!$C$5:$C$90,MATCH($D20,Kontenplan!$A$5:$A$90,0)),"?")) -> Aufwand | U20: =IF($E20="","",IFERROR(INDEX(Kontenplan!$C$5:$C$90,MATCH($E20,Kontenplan!$A$5:$A$90,0)),"?")) -> Aktiv | V20: =IF($F20="","",IF(OR($D20="",$E20="",$T20="?",$U20="?"),"Konto prüfen!",IF($A20="","Datum fehlt",IF(YEAR($A20)<>Einstellungen!$B$7,"anderes Jahr!",IF($G20="","MWST-Code fehlt","OK"))))) -> OK | W20: =IF($F20="","",IF(OR($D20=Kontoauszug!$C$4,$E20=Kontoauszug!$C$4),MAX(W$4:W19)+1,"")) -> 10
H21: =IF($G21="",0,IFERROR(INDEX(Einstellungen!$G$5:$G$11,MATCH($G21,Einstellungen!$E$5:$E$11,0)),0)) -> 0 | I21: =IF($G21="","-",IFERROR(INDEX(Einstellungen!$H$5:$H$11,MATCH($G21,Einstellungen!$E$5:$E$11,0)),"-")) -> - | J21: =IF(AND(Einstellungen!$B$8="Ja",Einstellungen!$B$9="Effektiv"),$I21,"-") -> - | K21: =IF(OR($F21="",$J21="-"),0,ROUND($F21-$F21/(1+$H21),2)) -> 0 | L21: =IF($F21="",0,$F21-$K21) -> 0 | M21: =IF($F21="",0,IF($J21="V",$L21,$F21)) -> 0 | N21: =IF($F21="",0,IF($J21="U",$L21,$F21)) -> 0 | O21: =IF($A21="","",MONTH($A21)) | P21: =IF($A21="","",ROUNDUP(MONTH($A21)/3,0)) | Q21: =IF($A21="","",IF(MONTH($A21)<=6,1,2)) | R21: =IF($E21="","",IFERROR(INDEX(Kontenplan!$F$5:$F$90,MATCH($E21,Kontenplan!$A$5:$A$90,0)),"")) | S21: =IF($D21="","",IFERROR(INDEX(Kontenplan!$F$5:$F$90,MATCH($D21,Kontenplan!$A$5:$A$90,0)),"")) | T21: =IF($D21="","",IFERROR(INDEX(Kontenplan!$C$5:$C$90,MATCH($D21,Kontenplan!$A$5:$A$90,0)),"?")) | U21: =IF($E21="","",IFERROR(INDEX(Kontenplan!$C$5:$C$90,MATCH($E21,Kontenplan!$A$5:$A$90,0)),"?")) | V21: =IF($F21="","",IF(OR($D21="",$E21="",$T21="?",$U21="?"),"Konto prüfen!",IF($A21="","Datum fehlt",IF(YEAR($A21)<>Einstellungen!$B$7,"anderes Jahr!",IF($G21="","MWST-Code fehlt","OK"))))) | W21: =IF($F21="","",IF(OR($D21=Kontoauszug!$C$4,$E21=Kontoauszug!$C$4),MAX(W$4:W20)+1,""))
H22: =IF($G22="",0,IFERROR(INDEX(Einstellungen!$G$5:$G$11,MATCH($G22,Einstellungen!$E$5:$E$11,0)),0)) -> 0 | I22: =IF($G22="","-",IFERROR(INDEX(Einstellungen!$H$5:$H$11,MATCH($G22,Einstellungen!$E$5:$E$11,0)),"-")) -> - | J22: =IF(AND(Einstellungen!$B$8="Ja",Einstellungen!$B$9="Effektiv"),$I22,"-") -> - | K22: =IF(OR($F22="",$J22="-"),0,ROUND($F22-$F22/(1+$H22),2)) -> 0 | L22: =IF($F22="",0,$F22-$K22) -> 0 | M22: =IF($F22="",0,IF($J22="V",$L22,$F22)) -> 0 | N22: =IF($F22="",0,IF($J22="U",$L22,$F22)) -> 0 | O22: =IF($A22="","",MONTH($A22)) | P22: =IF($A22="","",ROUNDUP(MONTH($A22)/3,0)) | Q22: =IF($A22="","",IF(MONTH($A22)<=6,1,2)) | R22: =IF($E22="","",IFERROR(INDEX(Kontenplan!$F$5:$F$90,MATCH($E22,Kontenplan!$A$5:$A$90,0)),"")) | S22: =IF($D22="","",IFERROR(INDEX(Kontenplan!$F$5:$F$90,MATCH($D22,Kontenplan!$A$5:$A$90,0)),"")) | T22: =IF($D22="","",IFERROR(INDEX(Kontenplan!$C$5:$C$90,MATCH($D22,Kontenplan!$A$5:$A$90,0)),"?")) | U22: =IF($E22="","",IFERROR(INDEX(Kontenplan!$C$5:$C$90,MATCH($E22,Kontenplan!$A$5:$A$90,0)),"?")) | V22: =IF($F22="","",IF(OR($D22="",$E22="",$T22="?",$U22="?"),"Konto prüfen!",IF($A22="","Datum fehlt",IF(YEAR($A22)<>Einstellungen!$B$7,"anderes Jahr!",IF($G22="","MWST-Code fehlt","OK"))))) | W22: =IF($F22="","",IF(OR($D22=Kontoauszug!$C$4,$E22=Kontoauszug!$C$4),MAX(W$4:W21)+1,""))
H23: =IF($G23="",0,IFERROR(INDEX(Einstellungen!$G$5:$G$11,MATCH($G23,Einstellungen!$E$5:$E$11,0)),0)) -> 0 | I23: =IF($G23="","-",IFERROR(INDEX(Einstellungen!$H$5:$H$11,MATCH($G23,Einstellungen!$E$5:$E$11,0)),"-")) -> - | J23: =IF(AND(Einstellungen!$B$8="Ja",Einstellungen!$B$9="Effektiv"),$I23,"-") -> - | K23: =IF(OR($F23="",$J23="-"),0,ROUND($F23-$F23/(1+$H23),2)) -> 0 | L23: =IF($F23="",0,$F23-$K23) -> 0 | M23: =IF($F23="",0,IF($J23="V",$L23,$F23)) -> 0 | N23: =IF($F23="",0,IF($J23="U",$L23,$F23)) -> 0 | O23: =IF($A23="","",MONTH($A23)) | P23: =IF($A23="","",ROUNDUP(MONTH($A23)/3,0)) | Q23: =IF($A23="","",IF(MONTH($A23)<=6,1,2)) | R23: =IF($E23="","",IFERROR(INDEX(Kontenplan!$F$5:$F$90,MATCH($E23,Kontenplan!$A$5:$A$90,0)),"")) | S23: =IF($D23="","",IFERROR(INDEX(Kontenplan!$F$5:$F$90,MATCH($D23,Kontenplan!$A$5:$A$90,0)),"")) | T23: =IF($D23="","",IFERROR(INDEX(Kontenplan!$C$5:$C$90,MATCH($D23,Kontenplan!$A$5:$A$90,0)),"?")) | U23: =IF($E23="","",IFERROR(INDEX(Kontenplan!$C$5:$C$90,MATCH($E23,Kontenplan!$A$5:$A$90,0)),"?")) | V23: =IF($F23="","",IF(OR($D23="",$E23="",$T23="?",$U23="?"),"Konto prüfen!",IF($A23="","Datum fehlt",IF(YEAR($A23)<>Einstellungen!$B$7,"anderes Jahr!",IF($G23="","MWST-Code fehlt","OK"))))) | W23: =IF($F23="","",IF(OR($D23=Kontoauszug!$C$4,$E23=Kontoauszug!$C$4),MAX(W$4:W22)+1,""))
H24: =IF($G24="",0,IFERROR(INDEX(Einstellungen!$G$5:$G$11,MATCH($G24,Einstellungen!$E$5:$E$11,0)),0)) -> 0 | I24: =IF($G24="","-",IFERROR(INDEX(Einstellungen!$H$5:$H$11,MATCH($G24,Einstellungen!$E$5:$E$11,0)),"-")) -> - | J24: =IF(AND(Einstellungen!$B$8="Ja",Einstellungen!$B$9="Effektiv"),$I24,"-") -> - | K24: =IF(OR($F24="",$J24="-"),0,ROUND($F24-$F24/(1+$H24),2)) -> 0 | L24: =IF($F24="",0,$F24-$K24) -> 0 | M24: =IF($F24="",0,IF($J24="V",$L24,$F24)) -> 0 | N24: =IF($F24="",0,IF($J24="U",$L24,$F24)) -> 0 | O24: =IF($A24="","",MONTH($A24)) | P24: =IF($A24="","",ROUNDUP(MONTH($A24)/3,0)) | Q24: =IF($A24="","",IF(MONTH($A24)<=6,1,2)) | R24: =IF($E24="","",IFERROR(INDEX(Kontenplan!$F$5:$F$90,MATCH($E24,Kontenplan!$A$5:$A$90,0)),"")) | S24: =IF($D24="","",IFERROR(INDEX(Kontenplan!$F$5:$F$90,MATCH($D24,Kontenplan!$A$5:$A$90,0)),"")) | T24: =IF($D24="","",IFERROR(INDEX(Kontenplan!$C$5:$C$90,MATCH($D24,Kontenplan!$A$5:$A$90,0)),"?")) | U24: =IF($E24="","",IFERROR(INDEX(Kontenplan!$C$5:$C$90,MATCH($E24,Kontenplan!$A$5:$A$90,0)),"?")) | V24: =IF($F24="","",IF(OR($D24="",$E24="",$T24="?",$U24="?"),"Konto prüfen!",IF($A24="","Datum fehlt",IF(YEAR($A24)<>Einstellungen!$B$7,"anderes Jahr!",IF($G24="","MWST-Code fehlt","OK"))))) | W24: =IF($F24="","",IF(OR($D24=Kontoauszug!$C$4,$E24=Kontoauszug!$C$4),MAX(W$4:W23)+1,""))
H25: =IF($G25="",0,IFERROR(INDEX(Einstellungen!$G$5:$G$11,MATCH($G25,Einstellungen!$E$5:$E$11,0)),0)) -> 0 | I25: =IF($G25="","-",IFERROR(INDEX(Einstellungen!$H$5:$H$11,MATCH($G25,Einstellungen!$E$5:$E$11,0)),"-")) -> - | J25: =IF(AND(Einstellungen!$B$8="Ja",Einstellungen!$B$9="Effektiv"),$I25,"-") -> - | K25: =IF(OR($F25="",$J25="-"),0,ROUND($F25-$F25/(1+$H25),2)) -> 0 | L25: =IF($F25="",0,$F25-$K25) -> 0 | M25: =IF($F25="",0,IF($J25="V",$L25,$F25)) -> 0 | N25: =IF($F25="",0,IF($J25="U",$L25,$F25)) -> 0 | O25: =IF($A25="","",MONTH($A25)) | P25: =IF($A25="","",ROUNDUP(MONTH($A25)/3,0)) | Q25: =IF($A25="","",IF(MONTH($A25)<=6,1,2)) | R25: =IF($E25="","",IFERROR(INDEX(Kontenplan!$F$5:$F$90,MATCH($E25,Kontenplan!$A$5:$A$90,0)),"")) | S25: =IF($D25="","",IFERROR(INDEX(Kontenplan!$F$5:$F$90,MATCH($D25,Kontenplan!$A$5:$A$90,0)),"")) | T25: =IF($D25="","",IFERROR(INDEX(Kontenplan!$C$5:$C$90,MATCH($D25,Kontenplan!$A$5:$A$90,0)),"?")) | U25: =IF($E25="","",IFERROR(INDEX(Kontenplan!$C$5:$C$90,MATCH($E25,Kontenplan!$A$5:$A$90,0)),"?")) | V25: =IF($F25="","",IF(OR($D25="",$E25="",$T25="?",$U25="?"),"Konto prüfen!",IF($A25="","Datum fehlt",IF(YEAR($A25)<>Einstellungen!$B$7,"anderes Jahr!",IF($G25="","MWST-Code fehlt","OK"))))) | W25: =IF($F25="","",IF(OR($D25=Kontoauszug!$C$4,$E25=Kontoauszug!$C$4),MAX(W$4:W24)+1,""))
H26: =IF($G26="",0,IFERROR(INDEX(Einstellungen!$G$5:$G$11,MATCH($G26,Einstellungen!$E$5:$E$11,0)),0)) -> 0 | I26: =IF($G26="","-",IFERROR(INDEX(Einstellungen!$H$5:$H$11,MATCH($G26,Einstellungen!$E$5:$E$11,0)),"-")) -> - | J26: =IF(AND(Einstellungen!$B$8="Ja",Einstellungen!$B$9="Effektiv"),$I26,"-") -> - | K26: =IF(OR($F26="",$J26="-"),0,ROUND($F26-$F26/(1+$H26),2)) -> 0 | L26: =IF($F26="",0,$F26-$K26) -> 0 | M26: =IF($F26="",0,IF($J26="V",$L26,$F26)) -> 0 | N26: =IF($F26="",0,IF($J26="U",$L26,$F26)) -> 0 | O26: =IF($A26="","",MONTH($A26)) | P26: =IF($A26="","",ROUNDUP(MONTH($A26)/3,0)) | Q26: =IF($A26="","",IF(MONTH($A26)<=6,1,2)) | R26: =IF($E26="","",IFERROR(INDEX(Kontenplan!$F$5:$F$90,MATCH($E26,Kontenplan!$A$5:$A$90,0)),"")) | S26: =IF($D26="","",IFERROR(INDEX(Kontenplan!$F$5:$F$90,MATCH($D26,Kontenplan!$A$5:$A$90,0)),"")) | T26: =IF($D26="","",IFERROR(INDEX(Kontenplan!$C$5:$C$90,MATCH($D26,Kontenplan!$A$5:$A$90,0)),"?")) | U26: =IF($E26="","",IFERROR(INDEX(Kontenplan!$C$5:$C$90,MATCH($E26,Kontenplan!$A$5:$A$90,0)),"?")) | V26: =IF($F26="","",IF(OR($D26="",$E26="",$T26="?",$U26="?"),"Konto prüfen!",IF($A26="","Datum fehlt",IF(YEAR($A26)<>Einstellungen!$B$7,"anderes Jahr!",IF($G26="","MWST-Code fehlt","OK"))))) | W26: =IF($F26="","",IF(OR($D26=Kontoauszug!$C$4,$E26=Kontoauszug!$C$4),MAX(W$4:W25)+1,""))
H27: =IF($G27="",0,IFERROR(INDEX(Einstellungen!$G$5:$G$11,MATCH($G27,Einstellungen!$E$5:$E$11,0)),0)) -> 0 | I27: =IF($G27="","-",IFERROR(INDEX(Einstellungen!$H$5:$H$11,MATCH($G27,Einstellungen!$E$5:$E$11,0)),"-")) -> - | J27: =IF(AND(Einstellungen!$B$8="Ja",Einstellungen!$B$9="Effektiv"),$I27,"-") -> - | K27: =IF(OR($F27="",$J27="-"),0,ROUND($F27-$F27/(1+$H27),2)) -> 0 | L27: =IF($F27="",0,$F27-$K27) -> 0 | M27: =IF($F27="",0,IF($J27="V",$L27,$F27)) -> 0 | N27: =IF($F27="",0,IF($J27="U",$L27,$F27)) -> 0 | O27: =IF($A27="","",MONTH($A27)) | P27: =IF($A27="","",ROUNDUP(MONTH($A27)/3,0)) | Q27: =IF($A27="","",IF(MONTH($A27)<=6,1,2)) | R27: =IF($E27="","",IFERROR(INDEX(Kontenplan!$F$5:$F$90,MATCH($E27,Kontenplan!$A$5:$A$90,0)),"")) | S27: =IF($D27="","",IFERROR(INDEX(Kontenplan!$F$5:$F$90,MATCH($D27,Kontenplan!$A$5:$A$90,0)),"")) | T27: =IF($D27="","",IFERROR(INDEX(Kontenplan!$C$5:$C$90,MATCH($D27,Kontenplan!$A$5:$A$90,0)),"?")) | U27: =IF($E27="","",IFERROR(INDEX(Kontenplan!$C$5:$C$90,MATCH($E27,Kontenplan!$A$5:$A$90,0)),"?")) | V27: =IF($F27="","",IF(OR($D27="",$E27="",$T27="?",$U27="?"),"Konto prüfen!",IF($A27="","Datum fehlt",IF(YEAR($A27)<>Einstellungen!$B$7,"anderes Jahr!",IF($G27="","MWST-Code fehlt","OK"))))) | W27: =IF($F27="","",IF(OR($D27=Kontoauszug!$C$4,$E27=Kontoauszug!$C$4),MAX(W$4:W26)+1,""))
H28: =IF($G28="",0,IFERROR(INDEX(Einstellungen!$G$5:$G$11,MATCH($G28,Einstellungen!$E$5:$E$11,0)),0)) -> 0 | I28: =IF($G28="","-",IFERROR(INDEX(Einstellungen!$H$5:$H$11,MATCH($G28,Einstellungen!$E$5:$E$11,0)),"-")) -> - | J28: =IF(AND(Einstellungen!$B$8="Ja",Einstellungen!$B$9="Effektiv"),$I28,"-") -> - | K28: =IF(OR($F28="",$J28="-"),0,ROUND($F28-$F28/(1+$H28),2)) -> 0 | L28: =IF($F28="",0,$F28-$K28) -> 0 | M28: =IF($F28="",0,IF($J28="V",$L28,$F28)) -> 0 | N28: =IF($F28="",0,IF($J28="U",$L28,$F28)) -> 0 | O28: =IF($A28="","",MONTH($A28)) | P28: =IF($A28="","",ROUNDUP(MONTH($A28)/3,0)) | Q28: =IF($A28="","",IF(MONTH($A28)<=6,1,2)) | R28: =IF($E28="","",IFERROR(INDEX(Kontenplan!$F$5:$F$90,MATCH($E28,Kontenplan!$A$5:$A$90,0)),"")) | S28: =IF($D28="","",IFERROR(INDEX(Kontenplan!$F$5:$F$90,MATCH($D28,Kontenplan!$A$5:$A$90,0)),"")) | T28: =IF($D28="","",IFERROR(INDEX(Kontenplan!$C$5:$C$90,MATCH($D28,Kontenplan!$A$5:$A$90,0)),"?")) | U28: =IF($E28="","",IFERROR(INDEX(Kontenplan!$C$5:$C$90,MATCH($E28,Kontenplan!$A$5:$A$90,0)),"?")) | V28: =IF($F28="","",IF(OR($D28="",$E28="",$T28="?",$U28="?"),"Konto prüfen!",IF($A28="","Datum fehlt",IF(YEAR($A28)<>Einstellungen!$B$7,"anderes Jahr!",IF($G28="","MWST-Code fehlt","OK"))))) | W28: =IF($F28="","",IF(OR($D28=Kontoauszug!$C$4,$E28=Kontoauszug!$C$4),MAX(W$4:W27)+1,""))
H29: =IF($G29="",0,IFERROR(INDEX(Einstellungen!$G$5:$G$11,MATCH($G29,Einstellungen!$E$5:$E$11,0)),0)) -> 0 | I29: =IF($G29="","-",IFERROR(INDEX(Einstellungen!$H$5:$H$11,MATCH($G29,Einstellungen!$E$5:$E$11,0)),"-")) -> - | J29: =IF(AND(Einstellungen!$B$8="Ja",Einstellungen!$B$9="Effektiv"),$I29,"-") -> - | K29: =IF(OR($F29="",$J29="-"),0,ROUND($F29-$F29/(1+$H29),2)) -> 0 | L29: =IF($F29="",0,$F29-$K29) -> 0 | M29: =IF($F29="",0,IF($J29="V",$L29,$F29)) -> 0 | N29: =IF($F29="",0,IF($J29="U",$L29,$F29)) -> 0 | O29: =IF($A29="","",MONTH($A29)) | P29: =IF($A29="","",ROUNDUP(MONTH($A29)/3,0)) | Q29: =IF($A29="","",IF(MONTH($A29)<=6,1,2)) | R29: =IF($E29="","",IFERROR(INDEX(Kontenplan!$F$5:$F$90,MATCH($E29,Kontenplan!$A$5:$A$90,0)),"")) | S29: =IF($D29="","",IFERROR(INDEX(Kontenplan!$F$5:$F$90,MATCH($D29,Kontenplan!$A$5:$A$90,0)),"")) | T29: =IF($D29="","",IFERROR(INDEX(Kontenplan!$C$5:$C$90,MATCH($D29,Kontenplan!$A$5:$A$90,0)),"?")) | U29: =IF($E29="","",IFERROR(INDEX(Kontenplan!$C$5:$C$90,MATCH($E29,Kontenplan!$A$5:$A$90,0)),"?")) | V29: =IF($F29="","",IF(OR($D29="",$E29="",$T29="?",$U29="?"),"Konto prüfen!",IF($A29="","Datum fehlt",IF(YEAR($A29)<>Einstellungen!$B$7,"anderes Jahr!",IF($G29="","MWST-Code fehlt","OK"))))) | W29: =IF($F29="","",IF(OR($D29=Kontoauszug!$C$4,$E29=Kontoauszug!$C$4),MAX(W$4:W28)+1,""))
H30: =IF($G30="",0,IFERROR(INDEX(Einstellungen!$G$5:$G$11,MATCH($G30,Einstellungen!$E$5:$E$11,0)),0)) -> 0 | I30: =IF($G30="","-",IFERROR(INDEX(Einstellungen!$H$5:$H$11,MATCH($G30,Einstellungen!$E$5:$E$11,0)),"-")) -> - | J30: =IF(AND(Einstellungen!$B$8="Ja",Einstellungen!$B$9="Effektiv"),$I30,"-") -> - | K30: =IF(OR($F30="",$J30="-"),0,ROUND($F30-$F30/(1+$H30),2)) -> 0 | L30: =IF($F30="",0,$F30-$K30) -> 0 | M30: =IF($F30="",0,IF($J30="V",$L30,$F30)) -> 0 | N30: =IF($F30="",0,IF($J30="U",$L30,$F30)) -> 0 | O30: =IF($A30="","",MONTH($A30)) | P30: =IF($A30="","",ROUNDUP(MONTH($A30)/3,0)) | Q30: =IF($A30="","",IF(MONTH($A30)<=6,1,2)) | R30: =IF($E30="","",IFERROR(INDEX(Kontenplan!$F$5:$F$90,MATCH($E30,Kontenplan!$A$5:$A$90,0)),"")) | S30: =IF($D30="","",IFERROR(INDEX(Kontenplan!$F$5:$F$90,MATCH($D30,Kontenplan!$A$5:$A$90,0)),"")) | T30: =IF($D30="","",IFERROR(INDEX(Kontenplan!$C$5:$C$90,MATCH($D30,Kontenplan!$A$5:$A$90,0)),"?")) | U30: =IF($E30="","",IFERROR(INDEX(Kontenplan!$C$5:$C$90,MATCH($E30,Kontenplan!$A$5:$A$90,0)),"?")) | V30: =IF($F30="","",IF(OR($D30="",$E30="",$T30="?",$U30="?"),"Konto prüfen!",IF($A30="","Datum fehlt",IF(YEAR($A30)<>Einstellungen!$B$7,"anderes Jahr!",IF($G30="","MWST-Code fehlt","OK"))))) | W30: =IF($F30="","",IF(OR($D30=Kontoauszug!$C$4,$E30=Kontoauszug!$C$4),MAX(W$4:W29)+1,""))
H31: =IF($G31="",0,IFERROR(INDEX(Einstellungen!$G$5:$G$11,MATCH($G31,Einstellungen!$E$5:$E$11,0)),0)) -> 0 | I31: =IF($G31="","-",IFERROR(INDEX(Einstellungen!$H$5:$H$11,MATCH($G31,Einstellungen!$E$5:$E$11,0)),"-")) -> - | J31: =IF(AND(Einstellungen!$B$8="Ja",Einstellungen!$B$9="Effektiv"),$I31,"-") -> - | K31: =IF(OR($F31="",$J31="-"),0,ROUND($F31-$F31/(1+$H31),2)) -> 0 | L31: =IF($F31="",0,$F31-$K31) -> 0 | M31: =IF($F31="",0,IF($J31="V",$L31,$F31)) -> 0 | N31: =IF($F31="",0,IF($J31="U",$L31,$F31)) -> 0 | O31: =IF($A31="","",MONTH($A31)) | P31: =IF($A31="","",ROUNDUP(MONTH($A31)/3,0)) | Q31: =IF($A31="","",IF(MONTH($A31)<=6,1,2)) | R31: =IF($E31="","",IFERROR(INDEX(Kontenplan!$F$5:$F$90,MATCH($E31,Kontenplan!$A$5:$A$90,0)),"")) | S31: =IF($D31="","",IFERROR(INDEX(Kontenplan!$F$5:$F$90,MATCH($D31,Kontenplan!$A$5:$A$90,0)),"")) | T31: =IF($D31="","",IFERROR(INDEX(Kontenplan!$C$5:$C$90,MATCH($D31,Kontenplan!$A$5:$A$90,0)),"?")) | U31: =IF($E31="","",IFERROR(INDEX(Kontenplan!$C$5:$C$90,MATCH($E31,Kontenplan!$A$5:$A$90,0)),"?")) | V31: =IF($F31="","",IF(OR($D31="",$E31="",$T31="?",$U31="?"),"Konto prüfen!",IF($A31="","Datum fehlt",IF(YEAR($A31)<>Einstellungen!$B$7,"anderes Jahr!",IF($G31="","MWST-Code fehlt","OK"))))) | W31: =IF($F31="","",IF(OR($D31=Kontoauszug!$C$4,$E31=Kontoauszug!$C$4),MAX(W$4:W30)+1,""))
H32: =IF($G32="",0,IFERROR(INDEX(Einstellungen!$G$5:$G$11,MATCH($G32,Einstellungen!$E$5:$E$11,0)),0)) -> 0 | I32: =IF($G32="","-",IFERROR(INDEX(Einstellungen!$H$5:$H$11,MATCH($G32,Einstellungen!$E$5:$E$11,0)),"-")) -> - | J32: =IF(AND(Einstellungen!$B$8="Ja",Einstellungen!$B$9="Effektiv"),$I32,"-") -> - | K32: =IF(OR($F32="",$J32="-"),0,ROUND($F32-$F32/(1+$H32),2)) -> 0 | L32: =IF($F32="",0,$F32-$K32) -> 0 | M32: =IF($F32="",0,IF($J32="V",$L32,$F32)) -> 0 | N32: =IF($F32="",0,IF($J32="U",$L32,$F32)) -> 0 | O32: =IF($A32="","",MONTH($A32)) | P32: =IF($A32="","",ROUNDUP(MONTH($A32)/3,0)) | Q32: =IF($A32="","",IF(MONTH($A32)<=6,1,2)) | R32: =IF($E32="","",IFERROR(INDEX(Kontenplan!$F$5:$F$90,MATCH($E32,Kontenplan!$A$5:$A$90,0)),"")) | S32: =IF($D32="","",IFERROR(INDEX(Kontenplan!$F$5:$F$90,MATCH($D32,Kontenplan!$A$5:$A$90,0)),"")) | T32: =IF($D32="","",IFERROR(INDEX(Kontenplan!$C$5:$C$90,MATCH($D32,Kontenplan!$A$5:$A$90,0)),"?")) | U32: =IF($E32="","",IFERROR(INDEX(Kontenplan!$C$5:$C$90,MATCH($E32,Kontenplan!$A$5:$A$90,0)),"?")) | V32: =IF($F32="","",IF(OR($D32="",$E32="",$T32="?",$U32="?"),"Konto prüfen!",IF($A32="","Datum fehlt",IF(YEAR($A32)<>Einstellungen!$B$7,"anderes Jahr!",IF($G32="","MWST-Code fehlt","OK"))))) | W32: =IF($F32="","",IF(OR($D32=Kontoauszug!$C$4,$E32=Kontoauszug!$C$4),MAX(W$4:W31)+1,""))
... H1504: =IF($G1504="",0,IFERROR(INDEX(Einstellungen!$G$5:$G$11,MATCH($G1504,Einstellungen!$E$5:$E$11,0)),0)) -> 0 | I1504: =IF($G1504="","-",IFERROR(INDEX(Einstellungen!$H$5:$H$11,MATCH($G1504,Einstellungen!$E$5:$E$11,0)),"-")) -> - | J1504: =IF(AND(Einstellungen!$B$8="Ja",Einstellungen!$B$9="Effektiv"),$I1504,"-") -> - | K1504: =IF(OR($F1504="",$J1504="-"),0,ROUND($F1504-$F1504/(1+$H1504),2)) -> 0 | L1504: =IF($F1504="",0,$F1504-$K1504) -> 0 | M1504: =IF($F1504="",0,IF($J1504="V",$L1504,$F1504)) -> 0 | N1504: =IF($F1504="",0,IF($J1504="U",$L1504,$F1504)) -> 0 | O1504: =IF($A1504="","",MONTH($A1504)) | P1504: =IF($A1504="","",ROUNDUP(MONTH($A1504)/3,0)) | Q1504: =IF($A1504="","",IF(MONTH($A1504)<=6,1,2)) | R1504: =IF($E1504="","",IFERROR(INDEX(Kontenplan!$F$5:$F$90,MATCH($E1504,Kontenplan!$A$5:$A$90,0)),"")) | S1504: =IF($D1504="","",IFERROR(INDEX(Kontenplan!$F$5:$F$90,MATCH($D1504,Kontenplan!$A$5:$A$90,0)),"")) | T1504: =IF($D1504="","",IFERROR(INDEX(Kontenplan!$C$5:$C$90,MATCH($D1504,Kontenplan!$A$5:$A$90,0)),"?")) | U1504: =IF($E1504="","",IFERROR(INDEX(Kontenplan!$C$5:$C$90,MATCH($E1504,Kontenplan!$A$5:$A$90,0)),"?")) | V1504: =IF($F1504="","",IF(OR($D1504="",$E1504="",$T1504="?",$U1504="?"),"Konto prüfen!",IF($A1504="","Datum fehlt",IF(YEAR($A1504)<>Einstellungen!$B$7,"anderes Jahr!",IF($G1504="","MWST-Code fehlt","OK"))))) | W1504: =IF($F1504="","",IF(OR($D1504=Kontoauszug!$C$4,$E1504=Kontoauszug!$C$4),MAX(W$4:W1503)+1,""))

Sheet Erfolgsrechnung
A1: Erfolgsrechnung (mehrstufig)
A2: Alles automatisch aus Journal, Anlagen und MWST. Vorjahr optional eintragen.
A4: Konto | B4: Position | C4: Betrag CHF | D4: % vom Nettoerlös | E4: Vorjahr (Eingabe) | F4: Veränderung
A5: BETRIEBSERTRAG
A6: 3000 | B6: Werkstattarbeiten (Arbeitsstunden) | C6: =SUMIF(Kontenplan!$A$5:$A$90,A6,Kontenplan!$K$5:$K$90) -> 1621.5 | D6: =IF($C$17=0,"",C6/$C$17) -> 0.088448462 | F6: =IF(E6="","",C6-E6)
A7: 3010 | B7: Service, MFK-Vorbereitung, Klima | C7: =SUMIF(Kontenplan!$A$5:$A$90,A7,Kontenplan!$K$5:$K$90) -> 0 | D7: =IF($C$17=0,"",C7/$C$17) -> 0 | F7: =IF(E7="","",C7-E7)
A8: 3200 | B8: Verkauf Ersatzteile & Zubehör | C8: =SUMIF(Kontenplan!$A$5:$A$90,A8,Kontenplan!$K$5:$K$90) -> 864.8 | D8: =IF($C$17=0,"",C8/$C$17) -> 0.047172513 | F8: =IF(E8="","",C8-E8)
A9: 3210 | B9: Verkauf Pneus & Pneuhotel | C9: =SUMIF(Kontenplan!$A$5:$A$90,A9,Kontenplan!$K$5:$K$90) -> 120 | D9: =IF($C$17=0,"",C9/$C$17) -> 0.0065456771 | F9: =IF(E9="","",C9-E9)
A10: 3400 | B10: Verkauf Occasionen | C10: =SUMIF(Kontenplan!$A$5:$A$90,A10,Kontenplan!$K$5:$K$90) -> 15900 | D10: =IF($C$17=0,"",C10/$C$17) -> 0.86730222 | F10: =IF(E10="","",C10-E10)
A11: 3410 | B11: Verkauf Neuwagen | C11: =SUMIF(Kontenplan!$A$5:$A$90,A11,Kontenplan!$K$5:$K$90) -> 0 | D11: =IF($C$17=0,"",C11/$C$17) -> 0 | F11: =IF(E11="","",C11-E11)
A12: 3600 | B12: Übriger Ertrag (Abschleppdienst, Vermietung) | C12: =SUMIF(Kontenplan!$A$5:$A$90,A12,Kontenplan!$K$5:$K$90) -> 0 | D12: =IF($C$17=0,"",C12/$C$17) -> 0 | F12: =IF(E12="","",C12-E12)
A13: 3800 | B13: Rabatte & Skonti an Kunden | C13: =SUMIF(Kontenplan!$A$5:$A$90,A13,Kontenplan!$K$5:$K$90) -> 0 | D13: =IF($C$17=0,"",C13/$C$17) -> 0 | F13: =IF(E13="","",C13-E13)
A14: 3805 | B14: Debitorenverluste | C14: =SUMIF(Kontenplan!$A$5:$A$90,A14,Kontenplan!$K$5:$K$90) -> 0 | D14: =IF($C$17=0,"",C14/$C$17) -> 0 | F14: =IF(E14="","",C14-E14)
A15: 3809 | B15: MWST Saldosteuersatz (automatisch) | C15: =SUMIF(Kontenplan!$A$5:$A$90,A15,Kontenplan!$K$5:$K$90) -> -173.59 | D15: =IF($C$17=0,"",C15/$C$17) -> -0.0094688674 | F15: =IF(E15="","",C15-E15)
B16: übrige Konten dieser Gruppe | C16: =SUMIF(Kontenplan!$D$5:$D$90,"ERT",Kontenplan!$K$5:$K$90)-SUM(C6:C15) -> 0 | D16: =IF($C$17=0,"",C16/$C$17) -> 0 | F16: =IF(E16="","",C16-E16)
B17: Nettoerlös aus Lieferungen und Leistungen | C17: =SUM(C6:C16) -> 18332.71 | D17: =IF($C$17=0,"",C17/$C$17) -> 1 | F17: =IF(E17="","",C17-E17)
A19: MATERIAL- UND WARENAUFWAND
A20: 4000 | B20: Einkauf Ersatzteile & Zubehör | C20: =-SUMIF(Kontenplan!$A$5:$A$90,A20,Kontenplan!$K$5:$K$90) -> -1297.2 | D20: =IF($C$17=0,"",C20/$C$17) -> -0.070758769 | F20: =IF(E20="","",C20-E20)
A21: 4010 | B21: Einkauf Pneus | C21: =-SUMIF(Kontenplan!$A$5:$A$90,A21,Kontenplan!$K$5:$K$90) -> 0 | D21: =IF($C$17=0,"",C21/$C$17) -> 0 | F21: =IF(E21="","",C21-E21)
A22: 4200 | B22: Einkauf Fahrzeuge | C22: =-SUMIF(Kontenplan!$A$5:$A$90,A22,Kontenplan!$K$5:$K$90) -> -12000 | D22: =IF($C$17=0,"",C22/$C$17) -> -0.65456771 | F22: =IF(E22="","",C22-E22)
A23: 4210 | B23: Aufbereitung/Reparatur Handelsfahrzeuge (fremd) | C23: =-SUMIF(Kontenplan!$A$5:$A$90,A23,Kontenplan!$K$5:$K$90) -> 0 | D23: =IF($C$17=0,"",C23/$C$17) -> 0 | F23: =IF(E23="","",C23-E23)
A24: 4400 | B24: Fremdarbeiten (Karosserie, Lack, Elektronik) | C24: =-SUMIF(Kontenplan!$A$5:$A$90,A24,Kontenplan!$K$5:$K$90) -> 0 | D24: =IF($C$17=0,"",C24/$C$17) -> 0 | F24: =IF(E24="","",C24-E24)
A25: 4500 | B25: Betriebsmaterial (Öl, Verbrauch) | C25: =-SUMIF(Kontenplan!$A$5:$A$90,A25,Kontenplan!$K$5:$K$90) -> 0 | D25: =IF($C$17=0,"",C25/$C$17) -> 0 | F25: =IF(E25="","",C25-E25)
A26: 4900 | B26: Lieferantenskonti & Rabatte | C26: =-SUMIF(Kontenplan!$A$5:$A$90,A26,Kontenplan!$K$5:$K$90) -> 0 | D26: =IF($C$17=0,"",C26/$C$17) -> 0 | F26: =IF(E26="","",C26-E26)
B27: übrige Konten dieser Gruppe | C27: =-SUMIF(Kontenplan!$D$5:$D$90,"MAT",Kontenplan!$K$5:$K$90)-SUM(C20:C26) -> 0 | D27: =IF($C$17=0,"",C27/$C$17) -> 0 | F27: =IF(E27="","",C27-E27)
B28: Total Material-/Warenaufwand | C28: =SUM(C20:C27) -> -13297.2 | D28: =IF($C$17=0,"",C28/$C$17) -> -0.72532648 | F28: =IF(E28="","",C28-E28)
B29: BRUTTOGEWINN (Bruttomarge) | C29: =C17+C28 -> 5035.51 | D29: =IF($C$17=0,"",C29/$C$17) -> 0.27467352 | F29: =IF(E29="","",C29-E29)
A31: PERSONALAUFWAND
A32: 5000 | B32: Löhne Mitarbeitende | C32: =-SUMIF(Kontenplan!$A$5:$A$90,A32,Kontenplan!$K$5:$K$90) -> -5200 | D32: =IF($C$17=0,"",C32/$C$17) -> -0.28364601 | F32: =IF(E32="","",C32-E32)
A33: 5700 | B33: Sozialversicherungen Arbeitgeber | C33: =-SUMIF(Kontenplan!$A$5:$A$90,A33,Kontenplan!$K$5:$K$90) -> -780 | D33: =IF($C$17=0,"",C33/$C$17) -> -0.042546901 | F33: =IF(E33="","",C33-E33)
A34: 5800 | B34: Übriger Personalaufwand (Weiterbildung, Spesen) | C34: =-SUMIF(Kontenplan!$A$5:$A$90,A34,Kontenplan!$K$5:$K$90) -> 0 | D34: =IF($C$17=0,"",C34/$C$17) -> 0 | F34: =IF(E34="","",C34-E34)
B35: übrige Konten dieser Gruppe | C35: =-SUMIF(Kontenplan!$D$5:$D$90,"PERS",Kontenplan!$K$5:$K$90)-SUM(C32:C34) -> 0 | D35: =IF($C$17=0,"",C35/$C$17) -> 0 | F35: =IF(E35="","",C35-E35)
B36: Total Personalaufwand | C36: =SUM(C32:C35) -> -5980 | D36: =IF($C$17=0,"",C36/$C$17) -> -0.32619291 | F36: =IF(E36="","",C36-E36)
B37: BRUTTOGEWINN II (nach Personal) | C37: =C29+C36 -> -944.49 | D37: =IF($C$17=0,"",C37/$C$17) -> -0.051519388 | F37: =IF(E37="","",C37-E37)
A39: ÜBRIGER BETRIEBSAUFWAND
A40: 6000 | B40: Miete Werkstatt & Abstellplätze | C40: =-SUMIF(Kontenplan!$A$5:$A$90,A40,Kontenplan!$K$5:$K$90) -> -3500 | D40: =IF($C$17=0,"",C40/$C$17) -> -0.19091558 | F40: =IF(E40="","",C40-E40)
A41: 6100 | B41: Unterhalt & Reparatur Einrichtungen | C41: =-SUMIF(Kontenplan!$A$5:$A$90,A41,Kontenplan!$K$5:$K$90) -> 0 | D41: =IF($C$17=0,"",C41/$C$17) -> 0 | F41: =IF(E41="","",C41-E41)
A42: 6200 | B42: Fahrzeugaufwand (eigene Fahrzeuge) | C42: =-SUMIF(Kontenplan!$A$5:$A$90,A42,Kontenplan!$K$5:$K$90) -> 0 | D42: =IF($C$17=0,"",C42/$C$17) -> 0 | F42: =IF(E42="","",C42-E42)
A43: 6300 | B43: Versicherungen (Betriebshaftpflicht, Sach) | C43: =-SUMIF(Kontenplan!$A$5:$A$90,A43,Kontenplan!$K$5:$K$90) -> -2400 | D43: =IF($C$17=0,"",C43/$C$17) -> -0.13091354 | F43: =IF(E43="","",C43-E43)
A44: 6400 | B44: Energie & Entsorgung (Strom, Altöl) | C44: =-SUMIF(Kontenplan!$A$5:$A$90,A44,Kontenplan!$K$5:$K$90) -> -486.6 | D44: =IF($C$17=0,"",C44/$C$17) -> -0.026542721 | F44: =IF(E44="","",C44-E44)
A45: 6500 | B45: Verwaltung (Büro, Telefon, Software, Treuhand) | C45: =-SUMIF(Kontenplan!$A$5:$A$90,A45,Kontenplan!$K$5:$K$90) -> 0 | D45: =IF($C$17=0,"",C45/$C$17) -> 0 | F45: =IF(E45="","",C45-E45)
A46: 6600 | B46: Werbung & Inserate | C46: =-SUMIF(Kontenplan!$A$5:$A$90,A46,Kontenplan!$K$5:$K$90) -> -540 | D46: =IF($C$17=0,"",C46/$C$17) -> -0.029455547 | F46: =IF(E46="","",C46-E46)
A47: 6700 | B47: Übriger Aufwand (Gebühren, Verbände) | C47: =-SUMIF(Kontenplan!$A$5:$A$90,A47,Kontenplan!$K$5:$K$90) -> 0 | D47: =IF($C$17=0,"",C47/$C$17) -> 0 | F47: =IF(E47="","",C47-E47)
B48: übrige Konten dieser Gruppe | C48: =-SUMIF(Kontenplan!$D$5:$D$90,"BA",Kontenplan!$K$5:$K$90)-SUM(C40:C47) -> 0 | D48: =IF($C$17=0,"",C48/$C$17) -> 0 | F48: =IF(E48="","",C48-E48)
B49: Total übriger Betriebsaufwand | C49: =SUM(C40:C48) -> -6926.6 | D49: =IF($C$17=0,"",C49/$C$17) -> -0.37782739 | F49: =IF(E49="","",C49-E49)
B50: BETRIEBSERGEBNIS vor Abschreibungen (EBITDA) | C50: =C37+C49 -> -7871.09 | D50: =IF($C$17=0,"",C50/$C$17) -> -0.42934678 | F50: =IF(E50="","",C50-E50)
A52: ABSCHREIBUNGEN
A53: 6800 | B53: Abschreibungen (automatisch aus Anlagen) | C53: =-SUMIF(Kontenplan!$A$5:$A$90,A53,Kontenplan!$K$5:$K$90) -> -33400 | D53: =IF($C$17=0,"",C53/$C$17) -> -1.8218801 | F53: =IF(E53="","",C53-E53)
B54: übrige Konten dieser Gruppe | C54: =-SUMIF(Kontenplan!$D$5:$D$90,"ABS",Kontenplan!$K$5:$K$90)-SUM(C53:C53) -> 0 | D54: =IF($C$17=0,"",C54/$C$17) -> 0 | F54: =IF(E54="","",C54-E54)
B55: Total Abschreibungen | C55: =SUM(C53:C54) -> -33400 | D55: =IF($C$17=0,"",C55/$C$17) -> -1.8218801 | F55: =IF(E55="","",C55-E55)
B56: BETRIEBSERGEBNIS (EBIT) | C56: =C50+C55 -> -41271.09 | D56: =IF($C$17=0,"",C56/$C$17) -> -2.2512269 | F56: =IF(E56="","",C56-E56)
A58: FINANZERFOLG
A59: 6900 | B59: Finanzaufwand (Zinsen, Bankspesen) | C59: =-SUMIF(Kontenplan!$A$5:$A$90,A59,Kontenplan!$K$5:$K$90) -> -85 | D59: =IF($C$17=0,"",C59/$C$17) -> -0.0046365213 | F59: =IF(E59="","",C59-E59)
B60: übrige Konten dieser Gruppe | C60: =-SUMIF(Kontenplan!$D$5:$D$90,"FINA",Kontenplan!$K$5:$K$90)-SUM(C59:C59) -> 0 | D60: =IF($C$17=0,"",C60/$C$17) -> 0 | F60: =IF(E60="","",C60-E60)
B61: Finanzaufwand | C61: =SUM(C59:C60) -> -85 | D61: =IF($C$17=0,"",C61/$C$17) -> -0.0046365213 | F61: =IF(E61="","",C61-E61)
A62: 6950 | B62: Finanzertrag | C62: =SUMIF(Kontenplan!$A$5:$A$90,A62,Kontenplan!$K$5:$K$90) -> 0 | D62: =IF($C$17=0,"",C62/$C$17) -> 0 | F62: =IF(E62="","",C62-E62)
B63: übrige Konten dieser Gruppe | C63: =SUMIF(Kontenplan!$D$5:$D$90,"FINE",Kontenplan!$K$5:$K$90)-SUM(C62:C62) -> 0 | D63: =IF($C$17=0,"",C63/$C$17) -> 0 | F63: =IF(E63="","",C63-E63)
B64: Finanzertrag | C64: =SUM(C62:C63) -> 0 | D64: =IF($C$17=0,"",C64/$C$17) -> 0 | F64: =IF(E64="","",C64-E64)
A65: AUSSERORDENTLICHES
A66: 8000 | B66: Ausserordentlicher Aufwand | C66: =-SUMIF(Kontenplan!$A$5:$A$90,A66,Kontenplan!$K$5:$K$90) -> 0 | D66: =IF($C$17=0,"",C66/$C$17) -> 0 | F66: =IF(E66="","",C66-E66)
B67: übrige Konten dieser Gruppe | C67: =-SUMIF(Kontenplan!$D$5:$D$90,"AO",Kontenplan!$K$5:$K$90)-SUM(C66:C66) -> 0 | D67: =IF($C$17=0,"",C67/$C$17) -> 0 | F67: =IF(E67="","",C67-E67)
B68: A.o. Aufwand | C68: =SUM(C66:C67) -> 0 | D68: =IF($C$17=0,"",C68/$C$17) -> 0 | F68: =IF(E68="","",C68-E68)
A69: 8100 | B69: Ausserordentlicher Ertrag | C69: =SUMIF(Kontenplan!$A$5:$A$90,A69,Kontenplan!$K$5:$K$90) -> 0 | D69: =IF($C$17=0,"",C69/$C$17) -> 0 | F69: =IF(E69="","",C69-E69)
B70: übrige Konten dieser Gruppe | C70: =SUMIF(Kontenplan!$D$5:$D$90,"AOE",Kontenplan!$K$5:$K$90)-SUM(C69:C69) -> 0 | D70: =IF($C$17=0,"",C70/$C$17) -> 0 | F70: =IF(E70="","",C70-E70)
B71: A.o. Ertrag | C71: =SUM(C69:C70) -> 0 | D71: =IF($C$17=0,"",C71/$C$17) -> 0 | F71: =IF(E71="","",C71-E71)
B72: JAHRESGEWINN / -VERLUST | C72: =C56+C61+C64+C68+C71 -> -41356.09 | D72: =IF($C$17=0,"",C72/$C$17) -> -2.2558634 | F72: =IF(E72="","",C72-E72)
A75: Aufwände sind negativ dargestellt. Der Gewinn einer Einzelfirma ist dein Einkommen – AHV und Steuern darauf siehe Blatt 'Steuern'.

Sheet Bilanz
A1: Bilanz per 31.12.
A2: Automatisch. Kontrollzeile unten muss 0 sein.
A4: Konto | B4: AKTIVEN | C4: CHF | E4: Konto | F4: PASSIVEN | G4: CHF
B5: UMLAUFVERMÖGEN | F5: KURZFRISTIGES FREMDKAPITAL
A6: 1000 | B6: Kasse | C6: =SUMIF(Kontenplan!$A$5:$A$90,A6,Kontenplan!$K$5:$K$90) -> 2120 | E6: 2000 | F6: Verbindlichkeiten Lieferanten (Kreditoren) | G6: =SUMIF(Kontenplan!$A$5:$A$90,E6,Kontenplan!$K$5:$K$90) -> 1297.2
A7: 1020 | B7: Bank | C7: =SUMIF(Kontenplan!$A$5:$A$90,A7,Kontenplan!$K$5:$K$90) -> 35724.7 | E7: 2200 | F7: Geschuldete MWST | G7: =SUMIF(Kontenplan!$A$5:$A$90,E7,Kontenplan!$K$5:$K$90) -> 173.59
A8: 1100 | B8: Forderungen Kunden (Debitoren) | C8: =SUMIF(Kontenplan!$A$5:$A$90,A8,Kontenplan!$K$5:$K$90) -> 0 | E8: 2270 | F8: Sozialversicherungen (AHV, UVG, BVG) | G8: =SUMIF(Kontenplan!$A$5:$A$90,E8,Kontenplan!$K$5:$K$90) -> 1330
A9: 1170 | B9: Vorsteuer MWST Material/DL | C9: =SUMIF(Kontenplan!$A$5:$A$90,A9,Kontenplan!$K$5:$K$90) -> 0 | E9: 2300 | F9: Passive Rechnungsabgrenzung | G9: =SUMIF(Kontenplan!$A$5:$A$90,E9,Kontenplan!$K$5:$K$90) -> 0
A10: 1171 | B10: Vorsteuer MWST Investitionen | C10: =SUMIF(Kontenplan!$A$5:$A$90,A10,Kontenplan!$K$5:$K$90) -> 0 | F10: übrige Konten | G10: =SUMIF(Kontenplan!$D$5:$D$90,"FKK",Kontenplan!$K$5:$K$90)-SUM(G6:G9) -> 0
A11: 1200 | B11: Lager Ersatzteile, Pneus, Öl | C11: =SUMIF(Kontenplan!$A$5:$A$90,A11,Kontenplan!$K$5:$K$90) -> 18000 | F11: Total Kurzfristiges Fremdkapital | G11: =SUM(G6:G10) -> 2800.79
A12: 1210 | B12: Lager Fahrzeuge (Occasionen) | C12: =SUMIF(Kontenplan!$A$5:$A$90,A12,Kontenplan!$K$5:$K$90) -> 0
A13: 1300 | B13: Aktive Rechnungsabgrenzung | C13: =SUMIF(Kontenplan!$A$5:$A$90,A13,Kontenplan!$K$5:$K$90) -> 0 | F13: LANGFRISTIGES FREMDKAPITAL
B14: übrige Konten | C14: =SUMIF(Kontenplan!$D$5:$D$90,"UV",Kontenplan!$K$5:$K$90)-SUM(C6:C13) -> 0 | E14: 2400 | F14: Bankdarlehen | G14: =SUMIF(Kontenplan!$A$5:$A$90,E14,Kontenplan!$K$5:$K$90) -> 40000
B15: Total Umlaufvermögen | C15: =SUM(C6:C14) -> 55844.7 | E15: 2450 | F15: Darlehen Dritte | G15: =SUMIF(Kontenplan!$A$5:$A$90,E15,Kontenplan!$K$5:$K$90) -> 0
F16: übrige Konten | G16: =SUMIF(Kontenplan!$D$5:$D$90,"FKL",Kontenplan!$K$5:$K$90)-SUM(G14:G15) -> 0
B17: ANLAGEVERMÖGEN | F17: Total Langfristiges Fremdkapital | G17: =SUM(G14:G16) -> 40000
A18: 1500 | B18: Maschinen & Werkstatteinrichtung | C18: =SUMIF(Kontenplan!$A$5:$A$90,A18,Kontenplan!$K$5:$K$90) -> 42000
A19: 1510 | B19: Werkzeuge | C19: =SUMIF(Kontenplan!$A$5:$A$90,A19,Kontenplan!$K$5:$K$90) -> 6600 | F19: EIGENKAPITAL
A20: 1520 | B20: Büro, Mobiliar & EDV | C20: =SUMIF(Kontenplan!$A$5:$A$90,A20,Kontenplan!$K$5:$K$90) -> 0 | E20: 2800 | F20: Eigenkapital | G20: =SUMIF(Kontenplan!$A$5:$A$90,E20,Kontenplan!$K$5:$K$90) -> 122000
A21: 1530 | B21: Fahrzeuge (Service-/Abschleppwagen) | C21: =SUMIF(Kontenplan!$A$5:$A$90,A21,Kontenplan!$K$5:$K$90) -> 15000 | E21: 2850 | F21: Privatkonto (Bezüge/Einlagen) | G21: =SUMIF(Kontenplan!$A$5:$A$90,E21,Kontenplan!$K$5:$K$90) -> -4000
B22: übrige Konten | C22: =SUMIF(Kontenplan!$D$5:$D$90,"AV",Kontenplan!$K$5:$K$90)-SUM(C18:C21) -> 0 | F22: übrige Konten | G22: =SUMIF(Kontenplan!$D$5:$D$90,"EK",Kontenplan!$K$5:$K$90)-SUM(G20:G21) -> 0
B23: Total Anlagevermögen | C23: =SUM(C18:C22) -> 63600 | F23: Total Eigenkapital | G23: =SUM(G20:G22) -> 118000
F24: Jahresgewinn / -verlust | G24: =Erfolgsrechnung!$C$72 -> -41356.09
F25: Eigenkapital per 31.12. inkl. Gewinn | G25: =G23+G24 -> 76643.91
B27: TOTAL AKTIVEN | C27: =C15+C23 -> 119444.7 | F27: TOTAL PASSIVEN | G27: =G11+G17+G25 -> 119444.7
B29: Kontrolle (Aktiven − Passiven) | C29: =ROUND(C27-G27,2) -> 0 | F29: =IF(ABS(C29)<0.01,"Bilanz ausgeglichen ✓","ACHTUNG: Differenz – Eröffnung/Buchungen prüfen") -> Bilanz ausgeglichen ✓
B31: Privatkonto 2850 ist negativ, wenn du mehr bezogen als eingelegt hast. Am Jahresende auf Eigenkapital 2800 übertragen (neues Jahr).

Sheet Margen
A1: Margen & Deckungsbeiträge pro Bereich
A2: Bei Saldomethode wird die MWST vom Bruttoumsatz abgezogen, damit die Margen netto stimmen.
A4: Kennzahl | B4: Werkstatt | C4: Teile & Pneus | D4: Fahrzeughandel | E4: Allgemein / Gemeinkosten | F4: TOTAL
A5: Ertrag (gebucht) | B5: =SUMIFS(Kontenplan!$K$5:$K$90,Kontenplan!$C$5:$C$90,"Ertrag",Kontenplan!$E$5:$E$90,"Werkstatt") -> 1621.5 | C5: =SUMIFS(Kontenplan!$K$5:$K$90,Kontenplan!$C$5:$C$90,"Ertrag",Kontenplan!$E$5:$E$90,"Teile") -> 984.8 | D5: =SUMIFS(Kontenplan!$K$5:$K$90,Kontenplan!$C$5:$C$90,"Ertrag",Kontenplan!$E$5:$E$90,"Fahrzeuge") -> 15900 | E5: =SUMIFS(Kontenplan!$K$5:$K$90,Kontenplan!$C$5:$C$90,"Ertrag",Kontenplan!$E$5:$E$90,"Allgemein")-SUMIF(Kontenplan!$A$5:$A$90,3809,Kontenplan!$K$5:$K$90) -> 0 | F5: =SUM(B5:E5) -> 18506.3
A6: − MWST-Anteil Saldomethode | B6: =-IF(MWST!$C$5,Einstellungen!$B$12*SUMIFS(Kontenplan!$K$5:$K$90,Kontenplan!$E$5:$E$90,"Werkstatt",Kontenplan!$F$5:$F$90,1)+Einstellungen!$B$13*SUMIFS(Kontenplan!$K$5:$K$90,Kontenplan!$E$5:$E$90,"Werkstatt",Kontenplan!$F$5:$F$90,2),0) -> -48.645 | C6: =-IF(MWST!$C$5,Einstellungen!$B$12*SUMIFS(Kontenplan!$K$5:$K$90,Kontenplan!$E$5:$E$90,"Teile",Kontenplan!$F$5:$F$90,1)+Einstellungen!$B$13*SUMIFS(Kontenplan!$K$5:$K$90,Kontenplan!$E$5:$E$90,"Teile",Kontenplan!$F$5:$F$90,2),0) -> -29.544 | D6: =-IF(MWST!$C$5,Einstellungen!$B$12*SUMIFS(Kontenplan!$K$5:$K$90,Kontenplan!$E$5:$E$90,"Fahrzeuge",Kontenplan!$F$5:$F$90,1)+Einstellungen!$B$13*SUMIFS(Kontenplan!$K$5:$K$90,Kontenplan!$E$5:$E$90,"Fahrzeuge",Kontenplan!$F$5:$F$90,2),0) -> -95.4 | E6: =-IF(MWST!$C$5,Einstellungen!$B$12*SUMIFS(Kontenplan!$K$5:$K$90,Kontenplan!$E$5:$E$90,"Allgemein",Kontenplan!$F$5:$F$90,1)+Einstellungen!$B$13*SUMIFS(Kontenplan!$K$5:$K$90,Kontenplan!$E$5:$E$90,"Allgemein",Kontenplan!$F$5:$F$90,2),0) -> 0 | F6: =SUM(B6:E6) -> -173.589
A7: → Nettoertrag | B7: =B5+B6 -> 1572.855 | C7: =C5+C6 -> 955.256 | D7: =D5+D6 -> 15804.6 | E7: =E5+E6 -> 0 | F7: =SUM(B7:E7) -> 18332.711
A8: − Direkte Kosten (Material, Fremdarbeit, Löhne) | B8: =-SUMIFS(Kontenplan!$K$5:$K$90,Kontenplan!$C$5:$C$90,"Aufwand",Kontenplan!$E$5:$E$90,"Werkstatt") -> -5980 | C8: =-SUMIFS(Kontenplan!$K$5:$K$90,Kontenplan!$C$5:$C$90,"Aufwand",Kontenplan!$E$5:$E$90,"Teile") -> -1297.2 | D8: =-SUMIFS(Kontenplan!$K$5:$K$90,Kontenplan!$C$5:$C$90,"Aufwand",Kontenplan!$E$5:$E$90,"Fahrzeuge") -> -12000 | E8: =-SUMIFS(Kontenplan!$K$5:$K$90,Kontenplan!$C$5:$C$90,"Aufwand",Kontenplan!$E$5:$E$90,"Allgemein") -> -40411.6 | F8: =SUM(B8:E8) -> -59688.8
A9: → Deckungsbeitrag (DB) | B9: =B7+B8 -> -4407.145 | C9: =C7+C8 -> -341.944 | D9: =D7+D8 -> 3804.6 | E9: =E7+E8 -> -40411.6 | F9: =SUM(B9:E9) -> -41356.089
A10: DB in % vom Nettoertrag | B10: =IF(B7=0,"",B9/B7) -> -2.8020034 | C10: =IF(C7=0,"",C9/C7) -> -0.35796059 | D10: =IF(D7=0,"",D9/D7) -> 0.24072738 | E10: ="" | F10: =IF(F7=0,"",F9/F7) -> -2.2558632
A11: Anteil am Gesamtumsatz | B11: =IF($F$7=0,"",B7/$F$7) -> 0.085795003 | C11: =IF($F$7=0,"",C7/$F$7) -> 0.052106642 | D11: =IF($F$7=0,"",D7/$F$7) -> 0.86209836 | E11: =IF($F$7=0,"",E7/$F$7) -> 0 | F11: =IF(F7=0,"",1) -> 1
A13: Jahresgewinn lt. Margenrechnung | B13: =F9 -> -41356.089
A14: Jahresgewinn lt. Erfolgsrechnung | B14: =Erfolgsrechnung!$C$72 -> -41356.09
A15: Abstimmung | B15: =IF(ABS(B13-B14)<0.01,"stimmt ✓","Differenz prüfen") -> stimmt ✓
A17: WEITERE KENNZAHLEN
A18: Teile: Aufschlag auf Einstand (Kalkulationsfaktor) | B18: =IF(C8=0,"",C7/-C8) -> 0.7363984
A19: Teile: Bruttomarge % | B19: =IF(C7=0,"",(C7+C8)/C7) -> -0.35796059
A20: Fahrzeughandel: Ø Marge pro verkauftes Fahrzeug | B20: =Fahrzeuge!$B$4 -> 2800
A21: Fahrzeughandel: Ø Standtage | B21: =Fahrzeuge!$F$3 -> 36
A22: Werkstatt: Ertrag pro Monat (Ø bisher) | B22: =IF(MAX(Journal!$O$5:$O$1504)=0,"",B7/MAX(Journal!$O$5:$O$1504)) -> 524.285
A23: Personalaufwand in % vom Nettoerlös | B23: =IF(Erfolgsrechnung!C17=0,"",-Erfolgsrechnung!C36/Erfolgsrechnung!C17) -> 0.32619291
A24: Gemeinkosten in % vom Nettoerlös | B24: =IF(F7=0,"",-E8/F7) -> 2.2043439
A26: Richtwerte Garagenbranche (Orientierung): Teile-Bruttomarge oft 25–40 %, Occasionen 8–15 % auf Verkaufspreis. Eigene Zahlen über mehrere Jahre vergleichen.

Sheet Fahrzeuge
A1: Fahrzeughandel – Marge pro Fahrzeug
A3: Verkauft | B3: =COUNT(K7:K206) -> 1 | C3: An Lager | D3: =COUNTIFS(F7:F206,"<>",K7:K206,"") -> 0 | E3: Ø Standtage | F3: =IF(COUNT(N7:N206)=0,0,AVERAGE(N7:N206)) -> 36 | H3: Buchen im Journal: Ankauf Soll 4200 / Haben 1020; Verkauf Soll 1020 / Haben 3400 (U81). Am Jahresende unverkaufte Fahrzeuge (Lagerwert) auf 1210 umbuchen: Soll 1210 / Haben 4200.
A4: Ø Marge / Fahrzeug | B4: =IF(B3=0,0,SUMIF(K7:K206,"<>",L7:L206)/B3) -> 2800 | C4: Lagerwert (Einstand) | D4: =SUMIFS(I7:I206,K7:K206,"",F7:F206,"<>") -> 0 | E4: Total Marge | F4: =SUM(L7:L206) -> 2800 | H4: 'MWST auf Marge' ist nur relevant bei effektiver Methode und Ankauf von Privaten (Margenbesteuerung).
A6: Nr. | B6: Fahrzeug (Marke, Modell, Jg.) | C6: Stamm-Nr. / VIN | D6: Einkauf am | E6: Gekauft von | F6: Einkaufs-preis | G6: Aufbereitung / Reparatur | H6: Übrige Kosten (MFK, Inserat) | I6: Einstand total | J6: Verkauft am | K6: Verkaufs-preis | L6: Marge CHF | M6: Marge % | N6: Standtage | O6: MWST auf Marge (Info) | P6: Status
A7: 1 | B7: VW Golf 1.4 TSI, 2019 | C7: 123.456.789 | D7: 46063 | E7: Privat | F7: 12000 | G7: 850 | H7: 250 | I7: =IF(F7="","",F7+G7+H7) -> 13100 | J7: 46099 | K7: 15900 | L7: =IF(OR(K7="",F7=""),"",K7-I7) -> 2800 | M7: =IF(L7="","",L7/K7) -> 0.17610063 | N7: =IF(D7="","",IF(J7="",TODAY()-D7,J7-D7)) -> 36 | O7: =IF(L7="","",IF(L7<=0,0,ROUND(L7-L7/(1+Einstellungen!$B$10),2))) -> 209.81 | P7: =IF(F7="","",IF(K7="",IF(N7>90,"an Lager >90 Tage!","an Lager"),"verkauft")) -> verkauft
I8: =IF(F8="","",F8+G8+H8) | L8: =IF(OR(K8="",F8=""),"",K8-I8) | M8: =IF(L8="","",L8/K8) | N8: =IF(D8="","",IF(J8="",TODAY()-D8,J8-D8)) | O8: =IF(L8="","",IF(L8<=0,0,ROUND(L8-L8/(1+Einstellungen!$B$10),2))) | P8: =IF(F8="","",IF(K8="",IF(N8>90,"an Lager >90 Tage!","an Lager"),"verkauft"))
I9: =IF(F9="","",F9+G9+H9) | L9: =IF(OR(K9="",F9=""),"",K9-I9) | M9: =IF(L9="","",L9/K9) | N9: =IF(D9="","",IF(J9="",TODAY()-D9,J9-D9)) | O9: =IF(L9="","",IF(L9<=0,0,ROUND(L9-L9/(1+Einstellungen!$B$10),2))) | P9: =IF(F9="","",IF(K9="",IF(N9>90,"an Lager >90 Tage!","an Lager"),"verkauft"))
I10: =IF(F10="","",F10+G10+H10) | L10: =IF(OR(K10="",F10=""),"",K10-I10) | M10: =IF(L10="","",L10/K10) | N10: =IF(D10="","",IF(J10="",TODAY()-D10,J10-D10)) | O10: =IF(L10="","",IF(L10<=0,0,ROUND(L10-L10/(1+Einstellungen!$B$10),2))) | P10: =IF(F10="","",IF(K10="",IF(N10>90,"an Lager >90 Tage!","an Lager"),"verkauft"))
I11: =IF(F11="","",F11+G11+H11) | L11: =IF(OR(K11="",F11=""),"",K11-I11) | M11: =IF(L11="","",L11/K11) | N11: =IF(D11="","",IF(J11="",TODAY()-D11,J11-D11)) | O11: =IF(L11="","",IF(L11<=0,0,ROUND(L11-L11/(1+Einstellungen!$B$10),2))) | P11: =IF(F11="","",IF(K11="",IF(N11>90,"an Lager >90 Tage!","an Lager"),"verkauft"))
I12: =IF(F12="","",F12+G12+H12) | L12: =IF(OR(K12="",F12=""),"",K12-I12) | M12: =IF(L12="","",L12/K12) | N12: =IF(D12="","",IF(J12="",TODAY()-D12,J12-D12)) | O12: =IF(L12="","",IF(L12<=0,0,ROUND(L12-L12/(1+Einstellungen!$B$10),2))) | P12: =IF(F12="","",IF(K12="",IF(N12>90,"an Lager >90 Tage!","an Lager"),"verkauft"))
I13: =IF(F13="","",F13+G13+H13) | L13: =IF(OR(K13="",F13=""),"",K13-I13) | M13: =IF(L13="","",L13/K13) | N13: =IF(D13="","",IF(J13="",TODAY()-D13,J13-D13)) | O13: =IF(L13="","",IF(L13<=0,0,ROUND(L13-L13/(1+Einstellungen!$B$10),2))) | P13: =IF(F13="","",IF(K13="",IF(N13>90,"an Lager >90 Tage!","an Lager"),"verkauft"))
I14: =IF(F14="","",F14+G14+H14) | L14: =IF(OR(K14="",F14=""),"",K14-I14) | M14: =IF(L14="","",L14/K14) | N14: =IF(D14="","",IF(J14="",TODAY()-D14,J14-D14)) | O14: =IF(L14="","",IF(L14<=0,0,ROUND(L14-L14/(1+Einstellungen!$B$10),2))) | P14: =IF(F14="","",IF(K14="",IF(N14>90,"an Lager >90 Tage!","an Lager"),"verkauft"))
I15: =IF(F15="","",F15+G15+H15) | L15: =IF(OR(K15="",F15=""),"",K15-I15) | M15: =IF(L15="","",L15/K15) | N15: =IF(D15="","",IF(J15="",TODAY()-D15,J15-D15)) | O15: =IF(L15="","",IF(L15<=0,0,ROUND(L15-L15/(1+Einstellungen!$B$10),2))) | P15: =IF(F15="","",IF(K15="",IF(N15>90,"an Lager >90 Tage!","an Lager"),"verkauft"))
I16: =IF(F16="","",F16+G16+H16) | L16: =IF(OR(K16="",F16=""),"",K16-I16) | M16: =IF(L16="","",L16/K16) | N16: =IF(D16="","",IF(J16="",TODAY()-D16,J16-D16)) | O16: =IF(L16="","",IF(L16<=0,0,ROUND(L16-L16/(1+Einstellungen!$B$10),2))) | P16: =IF(F16="","",IF(K16="",IF(N16>90,"an Lager >90 Tage!","an Lager"),"verkauft"))
I17: =IF(F17="","",F17+G17+H17) | L17: =IF(OR(K17="",F17=""),"",K17-I17) | M17: =IF(L17="","",L17/K17) | N17: =IF(D17="","",IF(J17="",TODAY()-D17,J17-D17)) | O17: =IF(L17="","",IF(L17<=0,0,ROUND(L17-L17/(1+Einstellungen!$B$10),2))) | P17: =IF(F17="","",IF(K17="",IF(N17>90,"an Lager >90 Tage!","an Lager"),"verkauft"))
I18: =IF(F18="","",F18+G18+H18) | L18: =IF(OR(K18="",F18=""),"",K18-I18) | M18: =IF(L18="","",L18/K18) | N18: =IF(D18="","",IF(J18="",TODAY()-D18,J18-D18)) | O18: =IF(L18="","",IF(L18<=0,0,ROUND(L18-L18/(1+Einstellungen!$B$10),2))) | P18: =IF(F18="","",IF(K18="",IF(N18>90,"an Lager >90 Tage!","an Lager"),"verkauft"))
I19: =IF(F19="","",F19+G19+H19) | L19: =IF(OR(K19="",F19=""),"",K19-I19) | M19: =IF(L19="","",L19/K19) | N19: =IF(D19="","",IF(J19="",TODAY()-D19,J19-D19)) | O19: =IF(L19="","",IF(L19<=0,0,ROUND(L19-L19/(1+Einstellungen!$B$10),2))) | P19: =IF(F19="","",IF(K19="",IF(N19>90,"an Lager >90 Tage!","an Lager"),"verkauft"))
... I206: =IF(F206="","",F206+G206+H206) | L206: =IF(OR(K206="",F206=""),"",K206-I206) | M206: =IF(L206="","",L206/K206) | N206: =IF(D206="","",IF(J206="",TODAY()-D206,J206-D206)) | O206: =IF(L206="","",IF(L206<=0,0,ROUND(L206-L206/(1+Einstellungen!$B$10),2))) | P206: =IF(F206="","",IF(K206="",IF(N206>90,"an Lager >90 Tage!","an Lager"),"verkauft"))

Sheet Debitoren
A1: Debitoren – offene Kundenrechnungen & Mahnwesen
A3: Total offen | C3: =SUM(J7:J506) -> 0 | E3: Saldo Konto 1100 | G3: =SUMIF(Kontenplan!$A$5:$A$90,1100,Kontenplan!$K$5:$K$90) -> 0 | I3: Rechnung buchen: Soll 1100 / Haben 3000 bzw. 3200 (U81). Zahlung: Soll 1020 / Haben 1100 (–).
A4: davon überfällig | C4: =SUMIF(K7:K506,">0",J7:J506) -> 0 | E4: Abgleich | G4: =IF(ABS(C3-G3)<1,"stimmt ✓","Differenz: Liste vs. Buchhaltung prüfen") -> stimmt ✓ | I4: Mahnstufe: 1 = bis 30 Tage überfällig, 2 = 31–60 Tage, 3 = über 60 Tage (Betreibung prüfen).
I5: Offene Rechnungen aus dem Vorjahr (Eröffnungssaldo 1100) hier ebenfalls einzeln erfassen.
A6: Rechnungs-Nr. | B6: Datum | C6: Kunde | D6: Fahrzeug / Kontrollschild | E6: Betrag inkl. MWST | F6: Zahlungsfrist (Tage) | G6: Fällig am | H6: Bezahlt am | I6: Bezahlter Betrag | J6: Offen | K6: Tage überfällig | L6: Mahnstufe | M6: Status
A7: R-001 | B7: 46031 | C7: Muster Hans, Dornach | D7: SO 12345 / VW Polo | E7: 2486.3 | F7: 30 | G7: =IF(B7="","",B7+IF(F7="",Einstellungen!$B$40,F7)) -> 46061 | H7: 46058 | I7: 2486.3 | J7: =IF(E7="","",E7-N(I7)) -> 0 | K7: =IF(OR(E7="",G7=""),"",IF(J7<=0.004,"",MAX(0,TODAY()-G7))) | L7: =IF(K7="","",IF(K7>60,3,IF(K7>30,2,IF(K7>0,1,0)))) | M7: =IF(E7="","",IF(J7<=0.004,"bezahlt",IF(N(K7)>0,"überfällig – Mahnung "&L7,"offen"))) -> bezahlt
G8: =IF(B8="","",B8+IF(F8="",Einstellungen!$B$40,F8)) | J8: =IF(E8="","",E8-N(I8)) | K8: =IF(OR(E8="",G8=""),"",IF(J8<=0.004,"",MAX(0,TODAY()-G8))) | L8: =IF(K8="","",IF(K8>60,3,IF(K8>30,2,IF(K8>0,1,0)))) | M8: =IF(E8="","",IF(J8<=0.004,"bezahlt",IF(N(K8)>0,"überfällig – Mahnung "&L8,"offen")))
G9: =IF(B9="","",B9+IF(F9="",Einstellungen!$B$40,F9)) | J9: =IF(E9="","",E9-N(I9)) | K9: =IF(OR(E9="",G9=""),"",IF(J9<=0.004,"",MAX(0,TODAY()-G9))) | L9: =IF(K9="","",IF(K9>60,3,IF(K9>30,2,IF(K9>0,1,0)))) | M9: =IF(E9="","",IF(J9<=0.004,"bezahlt",IF(N(K9)>0,"überfällig – Mahnung "&L9,"offen")))
G10: =IF(B10="","",B10+IF(F10="",Einstellungen!$B$40,F10)) | J10: =IF(E10="","",E10-N(I10)) | K10: =IF(OR(E10="",G10=""),"",IF(J10<=0.004,"",MAX(0,TODAY()-G10))) | L10: =IF(K10="","",IF(K10>60,3,IF(K10>30,2,IF(K10>0,1,0)))) | M10: =IF(E10="","",IF(J10<=0.004,"bezahlt",IF(N(K10)>0,"überfällig – Mahnung "&L10,"offen")))
G11: =IF(B11="","",B11+IF(F11="",Einstellungen!$B$40,F11)) | J11: =IF(E11="","",E11-N(I11)) | K11: =IF(OR(E11="",G11=""),"",IF(J11<=0.004,"",MAX(0,TODAY()-G11))) | L11: =IF(K11="","",IF(K11>60,3,IF(K11>30,2,IF(K11>0,1,0)))) | M11: =IF(E11="","",IF(J11<=0.004,"bezahlt",IF(N(K11)>0,"überfällig – Mahnung "&L11,"offen")))
G12: =IF(B12="","",B12+IF(F12="",Einstellungen!$B$40,F12)) | J12: =IF(E12="","",E12-N(I12)) | K12: =IF(OR(E12="",G12=""),"",IF(J12<=0.004,"",MAX(0,TODAY()-G12))) | L12: =IF(K12="","",IF(K12>60,3,IF(K12>30,2,IF(K12>0,1,0)))) | M12: =IF(E12="","",IF(J12<=0.004,"bezahlt",IF(N(K12)>0,"überfällig – Mahnung "&L12,"offen")))
G13: =IF(B13="","",B13+IF(F13="",Einstellungen!$B$40,F13)) | J13: =IF(E13="","",E13-N(I13)) | K13: =IF(OR(E13="",G13=""),"",IF(J13<=0.004,"",MAX(0,TODAY()-G13))) | L13: =IF(K13="","",IF(K13>60,3,IF(K13>30,2,IF(K13>0,1,0)))) | M13: =IF(E13="","",IF(J13<=0.004,"bezahlt",IF(N(K13)>0,"überfällig – Mahnung "&L13,"offen")))
G14: =IF(B14="","",B14+IF(F14="",Einstellungen!$B$40,F14)) | J14: =IF(E14="","",E14-N(I14)) | K14: =IF(OR(E14="",G14=""),"",IF(J14<=0.004,"",MAX(0,TODAY()-G14))) | L14: =IF(K14="","",IF(K14>60,3,IF(K14>30,2,IF(K14>0,1,0)))) | M14: =IF(E14="","",IF(J14<=0.004,"bezahlt",IF(N(K14)>0,"überfällig – Mahnung "&L14,"offen")))
G15: =IF(B15="","",B15+IF(F15="",Einstellungen!$B$40,F15)) | J15: =IF(E15="","",E15-N(I15)) | K15: =IF(OR(E15="",G15=""),"",IF(J15<=0.004,"",MAX(0,TODAY()-G15))) | L15: =IF(K15="","",IF(K15>60,3,IF(K15>30,2,IF(K15>0,1,0)))) | M15: =IF(E15="","",IF(J15<=0.004,"bezahlt",IF(N(K15)>0,"überfällig – Mahnung "&L15,"offen")))
G16: =IF(B16="","",B16+IF(F16="",Einstellungen!$B$40,F16)) | J16: =IF(E16="","",E16-N(I16)) | K16: =IF(OR(E16="",G16=""),"",IF(J16<=0.004,"",MAX(0,TODAY()-G16))) | L16: =IF(K16="","",IF(K16>60,3,IF(K16>30,2,IF(K16>0,1,0)))) | M16: =IF(E16="","",IF(J16<=0.004,"bezahlt",IF(N(K16)>0,"überfällig – Mahnung "&L16,"offen")))
G17: =IF(B17="","",B17+IF(F17="",Einstellungen!$B$40,F17)) | J17: =IF(E17="","",E17-N(I17)) | K17: =IF(OR(E17="",G17=""),"",IF(J17<=0.004,"",MAX(0,TODAY()-G17))) | L17: =IF(K17="","",IF(K17>60,3,IF(K17>30,2,IF(K17>0,1,0)))) | M17: =IF(E17="","",IF(J17<=0.004,"bezahlt",IF(N(K17)>0,"überfällig – Mahnung "&L17,"offen")))
G18: =IF(B18="","",B18+IF(F18="",Einstellungen!$B$40,F18)) | J18: =IF(E18="","",E18-N(I18)) | K18: =IF(OR(E18="",G18=""),"",IF(J18<=0.004,"",MAX(0,TODAY()-G18))) | L18: =IF(K18="","",IF(K18>60,3,IF(K18>30,2,IF(K18>0,1,0)))) | M18: =IF(E18="","",IF(J18<=0.004,"bezahlt",IF(N(K18)>0,"überfällig – Mahnung "&L18,"offen")))
G19: =IF(B19="","",B19+IF(F19="",Einstellungen!$B$40,F19)) | J19: =IF(E19="","",E19-N(I19)) | K19: =IF(OR(E19="",G19=""),"",IF(J19<=0.004,"",MAX(0,TODAY()-G19))) | L19: =IF(K19="","",IF(K19>60,3,IF(K19>30,2,IF(K19>0,1,0)))) | M19: =IF(E19="","",IF(J19<=0.004,"bezahlt",IF(N(K19)>0,"überfällig – Mahnung "&L19,"offen")))
... G506: =IF(B506="","",B506+IF(F506="",Einstellungen!$B$40,F506)) | J506: =IF(E506="","",E506-N(I506)) | K506: =IF(OR(E506="",G506=""),"",IF(J506<=0.004,"",MAX(0,TODAY()-G506))) | L506: =IF(K506="","",IF(K506>60,3,IF(K506>30,2,IF(K506>0,1,0)))) | M506: =IF(E506="","",IF(J506<=0.004,"bezahlt",IF(N(K506)>0,"überfällig – Mahnung "&L506,"offen")))

Sheet Kreditoren
A1: Kreditoren – offene Lieferantenrechnungen
A3: Total offen | C3: =SUM(L7:L506) -> 1297.2 | E3: Saldo Konto 2000 | G3: =SUMIF(Kontenplan!$A$5:$A$90,2000,Kontenplan!$K$5:$K$90) -> 1297.2 | I3: Rechnung buchen: Soll 4000 / Haben 2000 (V81). Zahlung: Soll 2000 / Haben 1020 (–). Skonto: Soll 2000 / Haben 4900.
A4: davon überfällig | C4: =SUMIF(M7:M506,"ÜBERFÄLLIG",L7:L506) -> 1297.2 | E4: Abgleich | G4: =IF(ABS(C3-G3)<1,"stimmt ✓","Differenz: Liste vs. Buchhaltung prüfen") -> stimmt ✓ | I4: Offene Rechnungen aus dem Vorjahr (Eröffnungssaldo 2000) hier ebenfalls einzeln erfassen, damit der Abgleich stimmt.
A6: Lieferant | B6: Rechnungs-Nr. | C6: Datum | D6: Betrag inkl. MWST | E6: Zahlungsfrist (Tage) | F6: Fällig am | G6: Skonto % | H6: Skonto-Frist (Tage) | I6: Zahlen bis (mit Skonto) | J6: Bezahlt am | K6: Bezahlter Betrag | L6: Offen | M6: Status
A7: Ersatzteil-Grosshandel AG | B7: INV-8812 | C7: 46034 | D7: 1297.2 | E7: 30 | F7: =IF(C7="","",C7+IF(E7="",30,E7)) -> 46064 | G7: 2 | H7: 10 | I7: =IF(OR(C7="",G7=""),"",C7+H7) -> 46044 | L7: =IF(D7="","",D7-N(K7)) -> 1297.2 | M7: =IF(D7="","",IF(L7<=0.004,"bezahlt",IF(TODAY()>F7,"ÜBERFÄLLIG",IF(AND(I7<>"",TODAY()<=I7),"Skonto nutzen bis "&TEXT(I7,"DD.MM."),"fällig in "&(F7-TODAY())&" Tagen")))) -> ÜBERFÄLLIG
F8: =IF(C8="","",C8+IF(E8="",30,E8)) | I8: =IF(OR(C8="",G8=""),"",C8+H8) | L8: =IF(D8="","",D8-N(K8)) | M8: =IF(D8="","",IF(L8<=0.004,"bezahlt",IF(TODAY()>F8,"ÜBERFÄLLIG",IF(AND(I8<>"",TODAY()<=I8),"Skonto nutzen bis "&TEXT(I8,"DD.MM."),"fällig in "&(F8-TODAY())&" Tagen"))))
F9: =IF(C9="","",C9+IF(E9="",30,E9)) | I9: =IF(OR(C9="",G9=""),"",C9+H9) | L9: =IF(D9="","",D9-N(K9)) | M9: =IF(D9="","",IF(L9<=0.004,"bezahlt",IF(TODAY()>F9,"ÜBERFÄLLIG",IF(AND(I9<>"",TODAY()<=I9),"Skonto nutzen bis "&TEXT(I9,"DD.MM."),"fällig in "&(F9-TODAY())&" Tagen"))))
F10: =IF(C10="","",C10+IF(E10="",30,E10)) | I10: =IF(OR(C10="",G10=""),"",C10+H10) | L10: =IF(D10="","",D10-N(K10)) | M10: =IF(D10="","",IF(L10<=0.004,"bezahlt",IF(TODAY()>F10,"ÜBERFÄLLIG",IF(AND(I10<>"",TODAY()<=I10),"Skonto nutzen bis "&TEXT(I10,"DD.MM."),"fällig in "&(F10-TODAY())&" Tagen"))))
F11: =IF(C11="","",C11+IF(E11="",30,E11)) | I11: =IF(OR(C11="",G11=""),"",C11+H11) | L11: =IF(D11="","",D11-N(K11)) | M11: =IF(D11="","",IF(L11<=0.004,"bezahlt",IF(TODAY()>F11,"ÜBERFÄLLIG",IF(AND(I11<>"",TODAY()<=I11),"Skonto nutzen bis "&TEXT(I11,"DD.MM."),"fällig in "&(F11-TODAY())&" Tagen"))))
F12: =IF(C12="","",C12+IF(E12="",30,E12)) | I12: =IF(OR(C12="",G12=""),"",C12+H12) | L12: =IF(D12="","",D12-N(K12)) | M12: =IF(D12="","",IF(L12<=0.004,"bezahlt",IF(TODAY()>F12,"ÜBERFÄLLIG",IF(AND(I12<>"",TODAY()<=I12),"Skonto nutzen bis "&TEXT(I12,"DD.MM."),"fällig in "&(F12-TODAY())&" Tagen"))))
F13: =IF(C13="","",C13+IF(E13="",30,E13)) | I13: =IF(OR(C13="",G13=""),"",C13+H13) | L13: =IF(D13="","",D13-N(K13)) | M13: =IF(D13="","",IF(L13<=0.004,"bezahlt",IF(TODAY()>F13,"ÜBERFÄLLIG",IF(AND(I13<>"",TODAY()<=I13),"Skonto nutzen bis "&TEXT(I13,"DD.MM."),"fällig in "&(F13-TODAY())&" Tagen"))))
F14: =IF(C14="","",C14+IF(E14="",30,E14)) | I14: =IF(OR(C14="",G14=""),"",C14+H14) | L14: =IF(D14="","",D14-N(K14)) | M14: =IF(D14="","",IF(L14<=0.004,"bezahlt",IF(TODAY()>F14,"ÜBERFÄLLIG",IF(AND(I14<>"",TODAY()<=I14),"Skonto nutzen bis "&TEXT(I14,"DD.MM."),"fällig in "&(F14-TODAY())&" Tagen"))))
F15: =IF(C15="","",C15+IF(E15="",30,E15)) | I15: =IF(OR(C15="",G15=""),"",C15+H15) | L15: =IF(D15="","",D15-N(K15)) | M15: =IF(D15="","",IF(L15<=0.004,"bezahlt",IF(TODAY()>F15,"ÜBERFÄLLIG",IF(AND(I15<>"",TODAY()<=I15),"Skonto nutzen bis "&TEXT(I15,"DD.MM."),"fällig in "&(F15-TODAY())&" Tagen"))))
F16: =IF(C16="","",C16+IF(E16="",30,E16)) | I16: =IF(OR(C16="",G16=""),"",C16+H16) | L16: =IF(D16="","",D16-N(K16)) | M16: =IF(D16="","",IF(L16<=0.004,"bezahlt",IF(TODAY()>F16,"ÜBERFÄLLIG",IF(AND(I16<>"",TODAY()<=I16),"Skonto nutzen bis "&TEXT(I16,"DD.MM."),"fällig in "&(F16-TODAY())&" Tagen"))))
F17: =IF(C17="","",C17+IF(E17="",30,E17)) | I17: =IF(OR(C17="",G17=""),"",C17+H17) | L17: =IF(D17="","",D17-N(K17)) | M17: =IF(D17="","",IF(L17<=0.004,"bezahlt",IF(TODAY()>F17,"ÜBERFÄLLIG",IF(AND(I17<>"",TODAY()<=I17),"Skonto nutzen bis "&TEXT(I17,"DD.MM."),"fällig in "&(F17-TODAY())&" Tagen"))))
F18: =IF(C18="","",C18+IF(E18="",30,E18)) | I18: =IF(OR(C18="",G18=""),"",C18+H18) | L18: =IF(D18="","",D18-N(K18)) | M18: =IF(D18="","",IF(L18<=0.004,"bezahlt",IF(TODAY()>F18,"ÜBERFÄLLIG",IF(AND(I18<>"",TODAY()<=I18),"Skonto nutzen bis "&TEXT(I18,"DD.MM."),"fällig in "&(F18-TODAY())&" Tagen"))))
F19: =IF(C19="","",C19+IF(E19="",30,E19)) | I19: =IF(OR(C19="",G19=""),"",C19+H19) | L19: =IF(D19="","",D19-N(K19)) | M19: =IF(D19="","",IF(L19<=0.004,"bezahlt",IF(TODAY()>F19,"ÜBERFÄLLIG",IF(AND(I19<>"",TODAY()<=I19),"Skonto nutzen bis "&TEXT(I19,"DD.MM."),"fällig in "&(F19-TODAY())&" Tagen"))))
... F506: =IF(C506="","",C506+IF(E506="",30,E506)) | I506: =IF(OR(C506="",G506=""),"",C506+H506) | L506: =IF(D506="","",D506-N(K506)) | M506: =IF(D506="","",IF(L506<=0.004,"bezahlt",IF(TODAY()>F506,"ÜBERFÄLLIG",IF(AND(I506<>"",TODAY()<=I506),"Skonto nutzen bis "&TEXT(I506,"DD.MM."),"fällig in "&(F506-TODAY())&" Tagen"))))

Sheet Löhne
A1: Lohnliste & Lohnkosten (Jahr)
A2: Sätze in den Einstellungen. Für Lohnausweis & AHV-Jahresmeldung.
A6: Name | B6: Funktion | C6: Eintritt | D6: Monatslohn brutto | E6: Anzahl Löhne (12/13) | F6: Jahreslohn brutto | G6: AHV/IV/EO AN | H6: ALV AN | I6: NBU AN | J6: KTG AN | K6: BVG AN pro Monat | L6: BVG AN Jahr | M6: Nettolohn Jahr | N6: Nettolohn pro Auszahlung | O6: AHV/IV/EO AG | P6: ALV AG | Q6: FAK+VK AG | R6: BU AG | S6: KTG AG | T6: BVG AG (≥ AN) | U6: Total AG-Beiträge | V6: Total Lohnkosten
A7: Mechaniker Beispiel | B7: Automobil-Mechatroniker | C7: 45139 | D7: 5200 | E7: 13 | F7: =IF(D7="",0,D7*IF(E7="",12,E7)) -> 67600 | G7: =ROUND(F7*Einstellungen!$B$32,2) -> 3582.8 | H7: =ROUND(MIN(F7,Einstellungen!$B$35)*Einstellungen!$B$34,2) -> 743.6 | I7: =ROUND(F7*Einstellungen!$B$36,2) -> 1014 | J7: =ROUND(F7*Einstellungen!$B$38,2) -> 405.6 | K7: 250 | L7: =N(K7)*12 -> 3000 | M7: =F7-G7-H7-I7-J7-L7 -> 58854 | N7: =IF(F7=0,0,M7/IF(E7="",12,E7)) -> 4527.2308 | O7: =ROUND(F7*Einstellungen!$B$33,2) -> 3582.8 | P7: =H7 -> 743.6 | Q7: =ROUND(F7*Einstellungen!$B$39,2) -> 1081.6 | R7: =ROUND(F7*Einstellungen!$B$37,2) -> 1352 | S7: =J7 -> 405.6 | T7: =L7 -> 3000 | U7: =SUM(O7:T7) -> 10165.6 | V7: =F7+U7 -> 77765.6
F8: =IF(D8="",0,D8*IF(E8="",12,E8)) -> 0 | G8: =ROUND(F8*Einstellungen!$B$32,2) -> 0 | H8: =ROUND(MIN(F8,Einstellungen!$B$35)*Einstellungen!$B$34,2) -> 0 | I8: =ROUND(F8*Einstellungen!$B$36,2) -> 0 | J8: =ROUND(F8*Einstellungen!$B$38,2) -> 0 | L8: =N(K8)*12 -> 0 | M8: =F8-G8-H8-I8-J8-L8 -> 0 | N8: =IF(F8=0,0,M8/IF(E8="",12,E8)) -> 0 | O8: =ROUND(F8*Einstellungen!$B$33,2) -> 0 | P8: =H8 -> 0 | Q8: =ROUND(F8*Einstellungen!$B$39,2) -> 0 | R8: =ROUND(F8*Einstellungen!$B$37,2) -> 0 | S8: =J8 -> 0 | T8: =L8 -> 0 | U8: =SUM(O8:T8) -> 0 | V8: =F8+U8 -> 0
F9: =IF(D9="",0,D9*IF(E9="",12,E9)) -> 0 | G9: =ROUND(F9*Einstellungen!$B$32,2) -> 0 | H9: =ROUND(MIN(F9,Einstellungen!$B$35)*Einstellungen!$B$34,2) -> 0 | I9: =ROUND(F9*Einstellungen!$B$36,2) -> 0 | J9: =ROUND(F9*Einstellungen!$B$38,2) -> 0 | L9: =N(K9)*12 -> 0 | M9: =F9-G9-H9-I9-J9-L9 -> 0 | N9: =IF(F9=0,0,M9/IF(E9="",12,E9)) -> 0 | O9: =ROUND(F9*Einstellungen!$B$33,2) -> 0 | P9: =H9 -> 0 | Q9: =ROUND(F9*Einstellungen!$B$39,2) -> 0 | R9: =ROUND(F9*Einstellungen!$B$37,2) -> 0 | S9: =J9 -> 0 | T9: =L9 -> 0 | U9: =SUM(O9:T9) -> 0 | V9: =F9+U9 -> 0
F10: =IF(D10="",0,D10*IF(E10="",12,E10)) -> 0 | G10: =ROUND(F10*Einstellungen!$B$32,2) -> 0 | H10: =ROUND(MIN(F10,Einstellungen!$B$35)*Einstellungen!$B$34,2) -> 0 | I10: =ROUND(F10*Einstellungen!$B$36,2) -> 0 | J10: =ROUND(F10*Einstellungen!$B$38,2) -> 0 | L10: =N(K10)*12 -> 0 | M10: =F10-G10-H10-I10-J10-L10 -> 0 | N10: =IF(F10=0,0,M10/IF(E10="",12,E10)) -> 0 | O10: =ROUND(F10*Einstellungen!$B$33,2) -> 0 | P10: =H10 -> 0 | Q10: =ROUND(F10*Einstellungen!$B$39,2) -> 0 | R10: =ROUND(F10*Einstellungen!$B$37,2) -> 0 | S10: =J10 -> 0 | T10: =L10 -> 0 | U10: =SUM(O10:T10) -> 0 | V10: =F10+U10 -> 0
F11: =IF(D11="",0,D11*IF(E11="",12,E11)) -> 0 | G11: =ROUND(F11*Einstellungen!$B$32,2) -> 0 | H11: =ROUND(MIN(F11,Einstellungen!$B$35)*Einstellungen!$B$34,2) -> 0 | I11: =ROUND(F11*Einstellungen!$B$36,2) -> 0 | J11: =ROUND(F11*Einstellungen!$B$38,2) -> 0 | L11: =N(K11)*12 -> 0 | M11: =F11-G11-H11-I11-J11-L11 -> 0 | N11: =IF(F11=0,0,M11/IF(E11="",12,E11)) -> 0 | O11: =ROUND(F11*Einstellungen!$B$33,2) -> 0 | P11: =H11 -> 0 | Q11: =ROUND(F11*Einstellungen!$B$39,2) -> 0 | R11: =ROUND(F11*Einstellungen!$B$37,2) -> 0 | S11: =J11 -> 0 | T11: =L11 -> 0 | U11: =SUM(O11:T11) -> 0 | V11: =F11+U11 -> 0
F12: =IF(D12="",0,D12*IF(E12="",12,E12)) -> 0 | G12: =ROUND(F12*Einstellungen!$B$32,2) -> 0 | H12: =ROUND(MIN(F12,Einstellungen!$B$35)*Einstellungen!$B$34,2) -> 0 | I12: =ROUND(F12*Einstellungen!$B$36,2) -> 0 | J12: =ROUND(F12*Einstellungen!$B$38,2) -> 0 | L12: =N(K12)*12 -> 0 | M12: =F12-G12-H12-I12-J12-L12 -> 0 | N12: =IF(F12=0,0,M12/IF(E12="",12,E12)) -> 0 | O12: =ROUND(F12*Einstellungen!$B$33,2) -> 0 | P12: =H12 -> 0 | Q12: =ROUND(F12*Einstellungen!$B$39,2) -> 0 | R12: =ROUND(F12*Einstellungen!$B$37,2) -> 0 | S12: =J12 -> 0 | T12: =L12 -> 0 | U12: =SUM(O12:T12) -> 0 | V12: =F12+U12 -> 0
F13: =IF(D13="",0,D13*IF(E13="",12,E13)) -> 0 | G13: =ROUND(F13*Einstellungen!$B$32,2) -> 0 | H13: =ROUND(MIN(F13,Einstellungen!$B$35)*Einstellungen!$B$34,2) -> 0 | I13: =ROUND(F13*Einstellungen!$B$36,2) -> 0 | J13: =ROUND(F13*Einstellungen!$B$38,2) -> 0 | L13: =N(K13)*12 -> 0 | M13: =F13-G13-H13-I13-J13-L13 -> 0 | N13: =IF(F13=0,0,M13/IF(E13="",12,E13)) -> 0 | O13: =ROUND(F13*Einstellungen!$B$33,2) -> 0 | P13: =H13 -> 0 | Q13: =ROUND(F13*Einstellungen!$B$39,2) -> 0 | R13: =ROUND(F13*Einstellungen!$B$37,2) -> 0 | S13: =J13 -> 0 | T13: =L13 -> 0 | U13: =SUM(O13:T13) -> 0 | V13: =F13+U13 -> 0
F14: =IF(D14="",0,D14*IF(E14="",12,E14)) -> 0 | G14: =ROUND(F14*Einstellungen!$B$32,2) -> 0 | H14: =ROUND(MIN(F14,Einstellungen!$B$35)*Einstellungen!$B$34,2) -> 0 | I14: =ROUND(F14*Einstellungen!$B$36,2) -> 0 | J14: =ROUND(F14*Einstellungen!$B$38,2) -> 0 | L14: =N(K14)*12 -> 0 | M14: =F14-G14-H14-I14-J14-L14 -> 0 | N14: =IF(F14=0,0,M14/IF(E14="",12,E14)) -> 0 | O14: =ROUND(F14*Einstellungen!$B$33,2) -> 0 | P14: =H14 -> 0 | Q14: =ROUND(F14*Einstellungen!$B$39,2) -> 0 | R14: =ROUND(F14*Einstellungen!$B$37,2) -> 0 | S14: =J14 -> 0 | T14: =L14 -> 0 | U14: =SUM(O14:T14) -> 0 | V14: =F14+U14 -> 0
F15: =IF(D15="",0,D15*IF(E15="",12,E15)) -> 0 | G15: =ROUND(F15*Einstellungen!$B$32,2) -> 0 | H15: =ROUND(MIN(F15,Einstellungen!$B$35)*Einstellungen!$B$34,2) -> 0 | I15: =ROUND(F15*Einstellungen!$B$36,2) -> 0 | J15: =ROUND(F15*Einstellungen!$B$38,2) -> 0 | L15: =N(K15)*12 -> 0 | M15: =F15-G15-H15-I15-J15-L15 -> 0 | N15: =IF(F15=0,0,M15/IF(E15="",12,E15)) -> 0 | O15: =ROUND(F15*Einstellungen!$B$33,2) -> 0 | P15: =H15 -> 0 | Q15: =ROUND(F15*Einstellungen!$B$39,2) -> 0 | R15: =ROUND(F15*Einstellungen!$B$37,2) -> 0 | S15: =J15 -> 0 | T15: =L15 -> 0 | U15: =SUM(O15:T15) -> 0 | V15: =F15+U15 -> 0
F16: =IF(D16="",0,D16*IF(E16="",12,E16)) -> 0 | G16: =ROUND(F16*Einstellungen!$B$32,2) -> 0 | H16: =ROUND(MIN(F16,Einstellungen!$B$35)*Einstellungen!$B$34,2) -> 0 | I16: =ROUND(F16*Einstellungen!$B$36,2) -> 0 | J16: =ROUND(F16*Einstellungen!$B$38,2) -> 0 | L16: =N(K16)*12 -> 0 | M16: =F16-G16-H16-I16-J16-L16 -> 0 | N16: =IF(F16=0,0,M16/IF(E16="",12,E16)) -> 0 | O16: =ROUND(F16*Einstellungen!$B$33,2) -> 0 | P16: =H16 -> 0 | Q16: =ROUND(F16*Einstellungen!$B$39,2) -> 0 | R16: =ROUND(F16*Einstellungen!$B$37,2) -> 0 | S16: =J16 -> 0 | T16: =L16 -> 0 | U16: =SUM(O16:T16) -> 0 | V16: =F16+U16 -> 0
F17: =IF(D17="",0,D17*IF(E17="",12,E17)) -> 0 | G17: =ROUND(F17*Einstellungen!$B$32,2) -> 0 | H17: =ROUND(MIN(F17,Einstellungen!$B$35)*Einstellungen!$B$34,2) -> 0 | I17: =ROUND(F17*Einstellungen!$B$36,2) -> 0 | J17: =ROUND(F17*Einstellungen!$B$38,2) -> 0 | L17: =N(K17)*12 -> 0 | M17: =F17-G17-H17-I17-J17-L17 -> 0 | N17: =IF(F17=0,0,M17/IF(E17="",12,E17)) -> 0 | O17: =ROUND(F17*Einstellungen!$B$33,2) -> 0 | P17: =H17 -> 0 | Q17: =ROUND(F17*Einstellungen!$B$39,2) -> 0 | R17: =ROUND(F17*Einstellungen!$B$37,2) -> 0 | S17: =J17 -> 0 | T17: =L17 -> 0 | U17: =SUM(O17:T17) -> 0 | V17: =F17+U17 -> 0
F18: =IF(D18="",0,D18*IF(E18="",12,E18)) -> 0 | G18: =ROUND(F18*Einstellungen!$B$32,2) -> 0 | H18: =ROUND(MIN(F18,Einstellungen!$B$35)*Einstellungen!$B$34,2) -> 0 | I18: =ROUND(F18*Einstellungen!$B$36,2) -> 0 | J18: =ROUND(F18*Einstellungen!$B$38,2) -> 0 | L18: =N(K18)*12 -> 0 | M18: =F18-G18-H18-I18-J18-L18 -> 0 | N18: =IF(F18=0,0,M18/IF(E18="",12,E18)) -> 0 | O18: =ROUND(F18*Einstellungen!$B$33,2) -> 0 | P18: =H18 -> 0 | Q18: =ROUND(F18*Einstellungen!$B$39,2) -> 0 | R18: =ROUND(F18*Einstellungen!$B$37,2) -> 0 | S18: =J18 -> 0 | T18: =L18 -> 0 | U18: =SUM(O18:T18) -> 0 | V18: =F18+U18 -> 0
F19: =IF(D19="",0,D19*IF(E19="",12,E19)) -> 0 | G19: =ROUND(F19*Einstellungen!$B$32,2) -> 0 | H19: =ROUND(MIN(F19,Einstellungen!$B$35)*Einstellungen!$B$34,2) -> 0 | I19: =ROUND(F19*Einstellungen!$B$36,2) -> 0 | J19: =ROUND(F19*Einstellungen!$B$38,2) -> 0 | L19: =N(K19)*12 -> 0 | M19: =F19-G19-H19-I19-J19-L19 -> 0 | N19: =IF(F19=0,0,M19/IF(E19="",12,E19)) -> 0 | O19: =ROUND(F19*Einstellungen!$B$33,2) -> 0 | P19: =H19 -> 0 | Q19: =ROUND(F19*Einstellungen!$B$39,2) -> 0 | R19: =ROUND(F19*Einstellungen!$B$37,2) -> 0 | S19: =J19 -> 0 | T19: =L19 -> 0 | U19: =SUM(O19:T19) -> 0 | V19: =F19+U19 -> 0
... F21: =IF(D21="",0,D21*IF(E21="",12,E21)) -> 0 | G21: =ROUND(F21*Einstellungen!$B$32,2) -> 0 | H21: =ROUND(MIN(F21,Einstellungen!$B$35)*Einstellungen!$B$34,2) -> 0 | I21: =ROUND(F21*Einstellungen!$B$36,2) -> 0 | J21: =ROUND(F21*Einstellungen!$B$38,2) -> 0 | L21: =N(K21)*12 -> 0 | M21: =F21-G21-H21-I21-J21-L21 -> 0 | N21: =IF(F21=0,0,M21/IF(E21="",12,E21)) -> 0 | O21: =ROUND(F21*Einstellungen!$B$33,2) -> 0 | P21: =H21 -> 0 | Q21: =ROUND(F21*Einstellungen!$B$39,2) -> 0 | R21: =ROUND(F21*Einstellungen!$B$37,2) -> 0 | S21: =J21 -> 0 | T21: =L21 -> 0 | U21: =SUM(O21:T21) -> 0 | V21: =F21+U21 -> 0
A22: TOTAL | F22: =SUM(F7:F21) -> 67600 | G22: =SUM(G7:G21) -> 3582.8 | H22: =SUM(H7:H21) -> 743.6 | I22: =SUM(I7:I21) -> 1014 | J22: =SUM(J7:J21) -> 405.6 | L22: =SUM(L7:L21) -> 3000 | M22: =SUM(M7:M21) -> 58854 | N22: =SUM(N7:N21) -> 4527.2308 | O22: =SUM(O7:O21) -> 3582.8 | P22: =SUM(P7:P21) -> 743.6 | Q22: =SUM(Q7:Q21) -> 1081.6 | R22: =SUM(R7:R21) -> 1352 | S22: =SUM(S7:S21) -> 405.6 | ... V22: =SUM(V7:V21) -> 77765.6
A24: Abgleich mit Buchhaltung (bisher gebucht)
A25: Konto 5000 Löhne | D25: =SUMIF(Kontenplan!$A$5:$A$90,5000,Kontenplan!$K$5:$K$90) -> 5200
A26: Konto 5700 Sozialversicherungen AG | D26: =SUMIF(Kontenplan!$A$5:$A$90,5700,Kontenplan!$K$5:$K$90) -> 780
A27: Budget Jahreslohn brutto lt. Liste | D27: =F22 -> 67600
A28: Budget AG-Beiträge lt. Liste | D28: =U22 -> 10165.6
A30: Buchen pro Monat: Nettolohn Soll 5000 / Haben 1020 · AN-Abzüge Soll 5000 / Haben 2270 · AG-Beiträge Soll 5700 / Haben 2270 · Zahlung an AHV/Versicherung Soll 2270 / Haben 1020.
A31: Bei Lohnausweis-Pflicht: Lohnausweise bis Ende Januar, AHV-Lohnbescheinigung an die Ausgleichskasse bis 30. Januar. Quellensteuer für ausländische MA ohne C-Bewilligung separat.
A32: Dein eigener Lohn als Inhaber gehört NICHT hierher – bei der Einzelfirma ist der Gewinn dein Einkommen (Bezüge über Privatkonto 2850).

Sheet Lager
A1: Lagerinventar (Stichtag 31.12.)
A2: Inventur am Jahresende: Menge zählen, Einstandspreis exkl. MWST. Differenz zur Buchhaltung als Bestandesänderung buchen.
A3: Inventarwert | C3: =SUM(H7:H506) -> 2992 | E3: Bestandesänderung (erst nach vollständiger Inventur buchen) | H3: =C3-C4 -> -15008 | J3: Steuerlich wird oft eine Warenreserve von 1/3 des Inventarwerts akzeptiert – mit Treuhänder/Steuerverwaltung SO klären.
A4: Buchwert Konto 1200 | C4: =SUMIF(Kontenplan!$A$5:$A$90,1200,Kontenplan!$K$5:$K$90) -> 18000 | E4: Buchung | H4: =IF(ABS(H3)<1,"keine",IF(H3>0,"Soll 1200 / Haben 4000: CHF "&TEXT(H3,"#,##0.00"),"Soll 4000 / Haben 1200: CHF "&TEXT(-H3,"#,##0.00"))) -> Soll 4000 / Haben 1200: CHF 15,008.00
A6: Artikel-Nr. | B6: Bezeichnung | C6: Kategorie | D6: Lieferant | E6: Menge | F6: Einheit | G6: Einstandspreis | H6: Lagerwert | I6: Mindestbestand | J6: Hinweis
A7: OE-5W30-208 | B7: Motorenöl 5W-30, Fass | C7: Öl & Flüssigkeiten | D7: Öl-Lieferant | E7: 150 | F7: Liter | G7: 6.8 | H7: =IF(OR(E7="",G7=""),"",E7*G7) -> 1020 | I7: 60 | J7: =IF(OR(E7="",I7=""),"",IF(E7<=I7,"nachbestellen",""))
A8: BR-VW-0012 | B8: Bremsbeläge VA VW Polo/Golf | C8: Ersatzteile | D8: Ersatzteil-Grosshandel AG | E8: 8 | F8: Satz | G8: 42.5 | H8: =IF(OR(E8="",G8=""),"",E8*G8) -> 340 | I8: 4 | J8: =IF(OR(E8="",I8=""),"",IF(E8<=I8,"nachbestellen",""))
A9: PN-20555R16 | B9: Winterpneu 205/55 R16 | C9: Pneus | D9: Pneu-Grosshandel | E9: 24 | F9: Stk | G9: 68 | H9: =IF(OR(E9="",G9=""),"",E9*G9) -> 1632 | I9: 8 | J9: =IF(OR(E9="",I9=""),"",IF(E9<=I9,"nachbestellen",""))
H10: =IF(OR(E10="",G10=""),"",E10*G10) | J10: =IF(OR(E10="",I10=""),"",IF(E10<=I10,"nachbestellen",""))
H11: =IF(OR(E11="",G11=""),"",E11*G11) | J11: =IF(OR(E11="",I11=""),"",IF(E11<=I11,"nachbestellen",""))
H12: =IF(OR(E12="",G12=""),"",E12*G12) | J12: =IF(OR(E12="",I12=""),"",IF(E12<=I12,"nachbestellen",""))
H13: =IF(OR(E13="",G13=""),"",E13*G13) | J13: =IF(OR(E13="",I13=""),"",IF(E13<=I13,"nachbestellen",""))
H14: =IF(OR(E14="",G14=""),"",E14*G14) | J14: =IF(OR(E14="",I14=""),"",IF(E14<=I14,"nachbestellen",""))
H15: =IF(OR(E15="",G15=""),"",E15*G15) | J15: =IF(OR(E15="",I15=""),"",IF(E15<=I15,"nachbestellen",""))
H16: =IF(OR(E16="",G16=""),"",E16*G16) | J16: =IF(OR(E16="",I16=""),"",IF(E16<=I16,"nachbestellen",""))
H17: =IF(OR(E17="",G17=""),"",E17*G17) | J17: =IF(OR(E17="",I17=""),"",IF(E17<=I17,"nachbestellen",""))
H18: =IF(OR(E18="",G18=""),"",E18*G18) | J18: =IF(OR(E18="",I18=""),"",IF(E18<=I18,"nachbestellen",""))
H19: =IF(OR(E19="",G19=""),"",E19*G19) | J19: =IF(OR(E19="",I19=""),"",IF(E19<=I19,"nachbestellen",""))
H20: =IF(OR(E20="",G20=""),"",E20*G20) | J20: =IF(OR(E20="",I20=""),"",IF(E20<=I20,"nachbestellen",""))
H21: =IF(OR(E21="",G21=""),"",E21*G21) | J21: =IF(OR(E21="",I21=""),"",IF(E21<=I21,"nachbestellen",""))
... H506: =IF(OR(E506="",G506=""),"",E506*G506) | J506: =IF(OR(E506="",I506=""),"",IF(E506<=I506,"nachbestellen",""))

Sheet Anlagen
A1: Anlagenverzeichnis & Abschreibungen
A2: Abschreibungen werden automatisch in Konto 6800 gebucht und vom Anlagekonto abgezogen.
I3: Total Abschreibung: | J3: =SUM(J6:J105) -> 33400
A5: Bezeichnung | B5: Konto | C5: Kategorie | D5: Anschaffung (Datum) | E5: Anschaffungs-wert | F5: Buchwert 1.1. | G5: Zugang im Jahr (Buchwert) | H5: Satz manuell (optional) | I5: Satz verwendet | J5: Abschreibung | K5: Buchwert 31.12. | M5: Konto | N5: Eröffnung lt. Kontenplan | O5: Σ Buchwert 1.1. | P5: Zugänge lt. Journal (Soll) | Q5: Σ Zugang Anlagen | R5: Status
A6: Hebebühnen (2 Stk.) | B6: 1500 | C6: Maschinen & Apparate | D6: 44652 | E6: 48000 | F6: 35000 | G6: 0 | I6: =IF($A6="","",IF($H6<>"",$H6,IFERROR(INDEX(Einstellungen!$F$15:$F$20,MATCH($C6,Einstellungen!$E$15:$E$20,0)),0))) -> 0.3 | J6: =IF($A6="",0,ROUND(($F6+$G6)*$I6,0)) -> 10500 | K6: =IF($A6="","",$F6+$G6-$J6) -> 24500 | M6: 1500 | N6: =SUMIF(Kontenplan!$A$5:$A$90,M6,Kontenplan!$G$5:$G$90) -> 60000 | O6: =SUMIF($B$6:$B$105,M6,$F$6:$F$105) -> 60000 | P6: =SUMIFS(Journal!$M$5:$M$1504,Journal!$D$5:$D$1504,M6)-SUMIFS(Journal!$N$5:$N$1504,Journal!$E$5:$E$1504,M6) -> 0 | Q6: =SUMIF($B$6:$B$105,M6,$G$6:$G$105) -> 0 | R6: =IF(AND(ABS(N6-O6)<1,ABS(P6-Q6)<1),"OK","abweichend – prüfen") -> OK
A7: Diagnosegerät & Klimaservicegerät | B7: 1500 | C7: Maschinen & Apparate | D7: 44958 | E7: 32000 | F7: 25000 | G7: 0 | I7: =IF($A7="","",IF($H7<>"",$H7,IFERROR(INDEX(Einstellungen!$F$15:$F$20,MATCH($C7,Einstellungen!$E$15:$E$20,0)),0))) -> 0.3 | J7: =IF($A7="",0,ROUND(($F7+$G7)*$I7,0)) -> 7500 | K7: =IF($A7="","",$F7+$G7-$J7) -> 17500 | M7: 1510 | N7: =SUMIF(Kontenplan!$A$5:$A$90,M7,Kontenplan!$G$5:$G$90) -> 12000 | O7: =SUMIF($B$6:$B$105,M7,$F$6:$F$105) -> 12000 | P7: =SUMIFS(Journal!$M$5:$M$1504,Journal!$D$5:$D$1504,M7)-SUMIFS(Journal!$N$5:$N$1504,Journal!$E$5:$E$1504,M7) -> 0 | Q7: =SUMIF($B$6:$B$105,M7,$G$6:$G$105) -> 0 | R7: =IF(AND(ABS(N7-O7)<1,ABS(P7-Q7)<1),"OK","abweichend – prüfen") -> OK
A8: Werkzeugsätze, Drehmomentschlüssel | B8: 1510 | C8: Werkzeuge | D8: 45292 | E8: 22000 | F8: 12000 | G8: 0 | I8: =IF($A8="","",IF($H8<>"",$H8,IFERROR(INDEX(Einstellungen!$F$15:$F$20,MATCH($C8,Einstellungen!$E$15:$E$20,0)),0))) -> 0.45 | J8: =IF($A8="",0,ROUND(($F8+$G8)*$I8,0)) -> 5400 | K8: =IF($A8="","",$F8+$G8-$J8) -> 6600 | M8: 1520 | N8: =SUMIF(Kontenplan!$A$5:$A$90,M8,Kontenplan!$G$5:$G$90) -> 0 | O8: =SUMIF($B$6:$B$105,M8,$F$6:$F$105) -> 0 | P8: =SUMIFS(Journal!$M$5:$M$1504,Journal!$D$5:$D$1504,M8)-SUMIFS(Journal!$N$5:$N$1504,Journal!$E$5:$E$1504,M8) -> 0 | Q8: =SUMIF($B$6:$B$105,M8,$G$6:$G$105) -> 0 | R8: =IF(AND(ABS(N8-O8)<1,ABS(P8-Q8)<1),"OK","abweichend – prüfen") -> OK
A9: Servicefahrzeug | B9: 1530 | C9: Fahrzeuge | D9: 45444 | E9: 42000 | F9: 25000 | G9: 0 | I9: =IF($A9="","",IF($H9<>"",$H9,IFERROR(INDEX(Einstellungen!$F$15:$F$20,MATCH($C9,Einstellungen!$E$15:$E$20,0)),0))) -> 0.4 | J9: =IF($A9="",0,ROUND(($F9+$G9)*$I9,0)) -> 10000 | K9: =IF($A9="","",$F9+$G9-$J9) -> 15000 | M9: 1530 | N9: =SUMIF(Kontenplan!$A$5:$A$90,M9,Kontenplan!$G$5:$G$90) -> 25000 | O9: =SUMIF($B$6:$B$105,M9,$F$6:$F$105) -> 25000 | P9: =SUMIFS(Journal!$M$5:$M$1504,Journal!$D$5:$D$1504,M9)-SUMIFS(Journal!$N$5:$N$1504,Journal!$E$5:$E$1504,M9) -> 0 | Q9: =SUMIF($B$6:$B$105,M9,$G$6:$G$105) -> 0 | R9: =IF(AND(ABS(N9-O9)<1,ABS(P9-Q9)<1),"OK","abweichend – prüfen") -> OK
I10: =IF($A10="","",IF($H10<>"",$H10,IFERROR(INDEX(Einstellungen!$F$15:$F$20,MATCH($C10,Einstellungen!$E$15:$E$20,0)),0))) | J10: =IF($A10="",0,ROUND(($F10+$G10)*$I10,0)) -> 0 | K10: =IF($A10="","",$F10+$G10-$J10)
I11: =IF($A11="","",IF($H11<>"",$H11,IFERROR(INDEX(Einstellungen!$F$15:$F$20,MATCH($C11,Einstellungen!$E$15:$E$20,0)),0))) | J11: =IF($A11="",0,ROUND(($F11+$G11)*$I11,0)) -> 0 | K11: =IF($A11="","",$F11+$G11-$J11) | M11: Zugang = Kauf einer neuen Anlage im Jahr (im Journal: Soll 15xx / Haben 1020 oder 2000, Code VI81). Den gleichen Betrag hier in Spalte G eintragen.
I12: =IF($A12="","",IF($H12<>"",$H12,IFERROR(INDEX(Einstellungen!$F$15:$F$20,MATCH($C12,Einstellungen!$E$15:$E$20,0)),0))) | J12: =IF($A12="",0,ROUND(($F12+$G12)*$I12,0)) -> 0 | K12: =IF($A12="","",$F12+$G12-$J12) | M12: Sätze = ESTV-Höchstsätze degressiv. Tiefere Sätze sind erlaubt (Spalte H) – z.B. um Gewinne zu glätten.
I13: =IF($A13="","",IF($H13<>"",$H13,IFERROR(INDEX(Einstellungen!$F$15:$F$20,MATCH($C13,Einstellungen!$E$15:$E$20,0)),0))) | J13: =IF($A13="",0,ROUND(($F13+$G13)*$I13,0)) -> 0 | K13: =IF($A13="","",$F13+$G13-$J13)
I14: =IF($A14="","",IF($H14<>"",$H14,IFERROR(INDEX(Einstellungen!$F$15:$F$20,MATCH($C14,Einstellungen!$E$15:$E$20,0)),0))) | J14: =IF($A14="",0,ROUND(($F14+$G14)*$I14,0)) -> 0 | K14: =IF($A14="","",$F14+$G14-$J14)
I15: =IF($A15="","",IF($H15<>"",$H15,IFERROR(INDEX(Einstellungen!$F$15:$F$20,MATCH($C15,Einstellungen!$E$15:$E$20,0)),0))) | J15: =IF($A15="",0,ROUND(($F15+$G15)*$I15,0)) -> 0 | K15: =IF($A15="","",$F15+$G15-$J15)
I16: =IF($A16="","",IF($H16<>"",$H16,IFERROR(INDEX(Einstellungen!$F$15:$F$20,MATCH($C16,Einstellungen!$E$15:$E$20,0)),0))) | J16: =IF($A16="",0,ROUND(($F16+$G16)*$I16,0)) -> 0 | K16: =IF($A16="","",$F16+$G16-$J16)
I17: =IF($A17="","",IF($H17<>"",$H17,IFERROR(INDEX(Einstellungen!$F$15:$F$20,MATCH($C17,Einstellungen!$E$15:$E$20,0)),0))) | J17: =IF($A17="",0,ROUND(($F17+$G17)*$I17,0)) -> 0 | K17: =IF($A17="","",$F17+$G17-$J17)
I18: =IF($A18="","",IF($H18<>"",$H18,IFERROR(INDEX(Einstellungen!$F$15:$F$20,MATCH($C18,Einstellungen!$E$15:$E$20,0)),0))) | J18: =IF($A18="",0,ROUND(($F18+$G18)*$I18,0)) -> 0 | K18: =IF($A18="","",$F18+$G18-$J18)
I19: =IF($A19="","",IF($H19<>"",$H19,IFERROR(INDEX(Einstellungen!$F$15:$F$20,MATCH($C19,Einstellungen!$E$15:$E$20,0)),0))) | J19: =IF($A19="",0,ROUND(($F19+$G19)*$I19,0)) -> 0 | K19: =IF($A19="","",$F19+$G19-$J19)
I20: =IF($A20="","",IF($H20<>"",$H20,IFERROR(INDEX(Einstellungen!$F$15:$F$20,MATCH($C20,Einstellungen!$E$15:$E$20,0)),0))) | J20: =IF($A20="",0,ROUND(($F20+$G20)*$I20,0)) -> 0 | K20: =IF($A20="","",$F20+$G20-$J20)
I21: =IF($A21="","",IF($H21<>"",$H21,IFERROR(INDEX(Einstellungen!$F$15:$F$20,MATCH($C21,Einstellungen!$E$15:$E$20,0)),0))) | J21: =IF($A21="",0,ROUND(($F21+$G21)*$I21,0)) -> 0 | K21: =IF($A21="","",$F21+$G21-$J21)
I22: =IF($A22="","",IF($H22<>"",$H22,IFERROR(INDEX(Einstellungen!$F$15:$F$20,MATCH($C22,Einstellungen!$E$15:$E$20,0)),0))) | J22: =IF($A22="",0,ROUND(($F22+$G22)*$I22,0)) -> 0 | K22: =IF($A22="","",$F22+$G22-$J22)
I23: =IF($A23="","",IF($H23<>"",$H23,IFERROR(INDEX(Einstellungen!$F$15:$F$20,MATCH($C23,Einstellungen!$E$15:$E$20,0)),0))) | J23: =IF($A23="",0,ROUND(($F23+$G23)*$I23,0)) -> 0 | K23: =IF($A23="","",$F23+$G23-$J23)
I24: =IF($A24="","",IF($H24<>"",$H24,IFERROR(INDEX(Einstellungen!$F$15:$F$20,MATCH($C24,Einstellungen!$E$15:$E$20,0)),0))) | J24: =IF($A24="",0,ROUND(($F24+$G24)*$I24,0)) -> 0 | K24: =IF($A24="","",$F24+$G24-$J24)
... I105: =IF($A105="","",IF($H105<>"",$H105,IFERROR(INDEX(Einstellungen!$F$15:$F$20,MATCH($C105,Einstellungen!$E$15:$E$20,0)),0))) | J105: =IF($A105="",0,ROUND(($F105+$G105)*$I105,0)) -> 0 | K105: =IF($A105="","",$F105+$G105-$J105)

Sheet MWST
A1: MWST-Abrechnung
A2: Rechnet automatisch nach der in den Einstellungen gewählten Methode.
A4: Aktive Methode | C4: =IF(Einstellungen!$B$8<>"Ja","Nicht MWST-pflichtig",Einstellungen!$B$9) -> Saldo
A5: Saldomethode aktiv | C5: =AND(Einstellungen!$B$8="Ja",Einstellungen!$B$9="Saldo") -> TRUE
A6: Effektive Methode aktiv | C6: =AND(Einstellungen!$B$8="Ja",Einstellungen!$B$9="Effektiv") -> FALSE
A8: A) SALDOSTEUERSATZ-METHODE (halbjährlich)
A10: Periode | B10: Umsatz Satz 1 (brutto) | C10: Satz 1 | D10: Steuer 1 | E10: Umsatz Satz 2 (brutto) | F10: Satz 2 | G10: Steuer 2 | H10: Total Steuer | I10: Einreichen bis
A11: 1. Semester | B11: =SUMIFS(Journal!$F$5:$F$1504,Journal!$R$5:$R$1504,1,Journal!$Q$5:$Q$1504,1)-SUMIFS(Journal!$F$5:$F$1504,Journal!$S$5:$S$1504,1,Journal!$Q$5:$Q$1504,1) -> 2606.3 | C11: =Einstellungen!$B$12 -> 0.03 | D11: =IF($C$5,ROUND(B11*C11,2),0) -> 78.19 | E11: =SUMIFS(Journal!$F$5:$F$1504,Journal!$R$5:$R$1504,2,Journal!$Q$5:$Q$1504,1)-SUMIFS(Journal!$F$5:$F$1504,Journal!$S$5:$S$1504,2,Journal!$Q$5:$Q$1504,1) -> 15900 | F11: =Einstellungen!$B$13 -> 0.006 | G11: =IF($C$5,ROUND(E11*F11,2),0) -> 95.4 | H11: =D11+G11 -> 173.59 | I11: =DATE(Einstellungen!$B$7,6,30+0)+60 -> 46263
A12: 2. Semester | B12: =SUMIFS(Journal!$F$5:$F$1504,Journal!$R$5:$R$1504,1,Journal!$Q$5:$Q$1504,2)-SUMIFS(Journal!$F$5:$F$1504,Journal!$S$5:$S$1504,1,Journal!$Q$5:$Q$1504,2) -> 0 | C12: =Einstellungen!$B$12 -> 0.03 | D12: =IF($C$5,ROUND(B12*C12,2),0) -> 0 | E12: =SUMIFS(Journal!$F$5:$F$1504,Journal!$R$5:$R$1504,2,Journal!$Q$5:$Q$1504,2)-SUMIFS(Journal!$F$5:$F$1504,Journal!$S$5:$S$1504,2,Journal!$Q$5:$Q$1504,2) -> 0 | F12: =Einstellungen!$B$13 -> 0.006 | G12: =IF($C$5,ROUND(E12*F12,2),0) -> 0 | H12: =D12+G12 -> 0 | I12: =DATE(Einstellungen!$B$7,12,30+1)+60 -> 46447
A13: Total Jahr | B13: =SUM(B11:B12) -> 2606.3 | D13: =SUM(D11:D12) -> 78.19 | E13: =SUM(E11:E12) -> 15900 | G13: =SUM(G11:G12) -> 95.4 | H13: =SUM(H11:H12) -> 173.59
A16: B) EFFEKTIVE METHODE (quartalsweise)
A18: Quartal | B18: Umsatz netto (steuerbar) | C18: MWST geschuldet | D18: Vorsteuer Material/DL | E18: Vorsteuer Investitionen | F18: Zahllast | G18: Einreichen bis
A19: Q1 | B19: =SUMIFS(Journal!$L$5:$L$1504,Journal!$J$5:$J$1504,"U",Journal!$P$5:$P$1504,1) -> 0 | C19: =SUMIFS(Journal!$K$5:$K$1504,Journal!$J$5:$J$1504,"U",Journal!$P$5:$P$1504,1) -> 0 | D19: =SUMIFS(Journal!$K$5:$K$1504,Journal!$J$5:$J$1504,"V",Journal!$P$5:$P$1504,1,Journal!$G$5:$G$1504,"<>VI81") -> 0 | E19: =SUMIFS(Journal!$K$5:$K$1504,Journal!$J$5:$J$1504,"V",Journal!$P$5:$P$1504,1,Journal!$G$5:$G$1504,"VI81") -> 0 | F19: =C19-D19-E19 -> 0 | G19: =DATE(Einstellungen!$B$7,3,31)+60 -> 46172
A20: Q2 | B20: =SUMIFS(Journal!$L$5:$L$1504,Journal!$J$5:$J$1504,"U",Journal!$P$5:$P$1504,2) -> 0 | C20: =SUMIFS(Journal!$K$5:$K$1504,Journal!$J$5:$J$1504,"U",Journal!$P$5:$P$1504,2) -> 0 | D20: =SUMIFS(Journal!$K$5:$K$1504,Journal!$J$5:$J$1504,"V",Journal!$P$5:$P$1504,2,Journal!$G$5:$G$1504,"<>VI81") -> 0 | E20: =SUMIFS(Journal!$K$5:$K$1504,Journal!$J$5:$J$1504,"V",Journal!$P$5:$P$1504,2,Journal!$G$5:$G$1504,"VI81") -> 0 | F20: =C20-D20-E20 -> 0 | G20: =DATE(Einstellungen!$B$7,6,30)+60 -> 46263
A21: Q3 | B21: =SUMIFS(Journal!$L$5:$L$1504,Journal!$J$5:$J$1504,"U",Journal!$P$5:$P$1504,3) -> 0 | C21: =SUMIFS(Journal!$K$5:$K$1504,Journal!$J$5:$J$1504,"U",Journal!$P$5:$P$1504,3) -> 0 | D21: =SUMIFS(Journal!$K$5:$K$1504,Journal!$J$5:$J$1504,"V",Journal!$P$5:$P$1504,3,Journal!$G$5:$G$1504,"<>VI81") -> 0 | E21: =SUMIFS(Journal!$K$5:$K$1504,Journal!$J$5:$J$1504,"V",Journal!$P$5:$P$1504,3,Journal!$G$5:$G$1504,"VI81") -> 0 | F21: =C21-D21-E21 -> 0 | G21: =DATE(Einstellungen!$B$7,9,30)+60 -> 46355
A22: Q4 | B22: =SUMIFS(Journal!$L$5:$L$1504,Journal!$J$5:$J$1504,"U",Journal!$P$5:$P$1504,4) -> 0 | C22: =SUMIFS(Journal!$K$5:$K$1504,Journal!$J$5:$J$1504,"U",Journal!$P$5:$P$1504,4) -> 0 | D22: =SUMIFS(Journal!$K$5:$K$1504,Journal!$J$5:$J$1504,"V",Journal!$P$5:$P$1504,4,Journal!$G$5:$G$1504,"<>VI81") -> 0 | E22: =SUMIFS(Journal!$K$5:$K$1504,Journal!$J$5:$J$1504,"V",Journal!$P$5:$P$1504,4,Journal!$G$5:$G$1504,"VI81") -> 0 | F22: =C22-D22-E22 -> 0 | G22: =DATE(Einstellungen!$B$7,12,31)+60 -> 46447
A23: Total Jahr | B23: =SUM(B19:B22) -> 0 | C23: =SUM(C19:C22) -> 0 | D23: =SUM(D19:D22) -> 0 | E23: =SUM(E19:E22) -> 0 | F23: =SUM(F19:F22) -> 0
A26: C) ÜBERSICHT
A27: MWST-Schuld Jahr (netto, nach Vorsteuer) | B27: =IF($C$5,H13,IF($C$6,F23,0)) -> 173.59
A28: Bereits an ESTV bezahlt (Soll 2200 im Journal) | B28: =SUMIFS(Journal!$M$5:$M$1504,Journal!$D$5:$D$1504,2200) -> 0
A29: Noch offen / zurückzulegen | B29: =B27-B28 -> 173.59
A30: Umsatz brutto total (alle Ertragskonten) | B30: =SUMIFS(Journal!$N$5:$N$1504,Journal!$U$5:$U$1504,"Ertrag")-SUMIFS(Journal!$M$5:$M$1504,Journal!$T$5:$T$1504,"Ertrag")+SUMIFS(Journal!$K$5:$K$1504,Journal!$J$5:$J$1504,"U") -> 18506.3
A31: Hinweis MWST-Pflicht | B31: =IF(AND(B30>=100000,Einstellungen!$B$8<>"Ja"),"Umsatz über CHF 100'000 – Anmeldung bei ESTV nötig!","")
A33: Saldomethode: Steuer = Bruttoumsatz × Saldosteuersatz; Vorsteuern sind im Satz eingerechnet. Rechnungen an Kunden trotzdem mit 8,1 % MWST.
A34: Zahlung an ESTV im Journal: Soll 2200 / Haben 1020, Code '-'. Bei effektiver Methode zusätzlich Vorsteuer verrechnen: Soll 2200 / Haben 1170 bzw. 1171.
A35: Occasionen von Privaten (effektive Methode): Margenbesteuerung möglich – MWST nur auf der Marge (siehe Blatt Fahrzeuge). Mit Treuhänder klären.

Sheet Steuern
A1: AHV-Beiträge & Steuerschätzung (Einzelfirma, Kanton Solothurn)
A2: SCHÄTZUNG zur Planung von Rückstellungen – ersetzt keine Steuererklärung. Gelbe Felder anpassen.
A4: 1. EINKOMMEN AUS SELBSTÄNDIGER ERWERBSTÄTIGKEIT
A5: Jahresgewinn lt. Erfolgsrechnung | C5: =Erfolgsrechnung!$C$72 -> -41356.09 | E5: Hinweise
A6: Kaufpreis Geschäftsauto mit Privatnutzung (exkl. MWST) | C6: 0 | E6: • Einzelfirma: Gewinn = dein Einkommen. Kein Lohn an dich selbst buchen; Bezüge über Privatkonto 2850.
A7: Monate mit Privatnutzung | C7: 12 | E7: • Die Ausgleichskasse rechnet definitiv aufgrund der rechtskräftigen Steuerveranlagung ab (oft 1–2 Jahre später).
A8: + Privatanteil Fahrzeug (0,9 % × Kaufpreis × Monate) | C8: =ROUND(C6*Einstellungen!$B$30*C7,0) -> 0 | E8: • Sinkende Skala hier linear angenähert. Verbindlich: BSV-Tabelle 'Beitragstabellen Selbständigerwerbende'.
A9: + Eigenverbrauch / Privatanteile übrige (Telefon, Reparaturen am Privatauto) | C9: 0 | E9: • Steuersätze: Ø-Sätze in Einstellungen mit dem Steuerrechner (Kanton SO bzw. ESTV) für dein Einkommen ersetzen.
A10: + Privat bezahlte Aufwände, die Geschäftsaufwand sind (−) / nicht abziehbare (+) | C10: 0 | E10: • Steuerfüsse 2026: Kanton SO 104 %, Gemeinde Dornach 92 % (rückwirkend erhöht per RRB 30.6.2026).
A11: → Einkommen aus selbständiger Erwerbstätigkeit | C11: =C5+C8+C9+C10 -> -41356.09 | E11: • Säule 3a: Ohne Pensionskasse bis 20 % des Erwerbseinkommens, max. CHF 36'288 (2026). Einzahlung bis 31.12.
E12: • Abschreibungen, Warenreserve auf Lager und Rückstellungen senken den steuerbaren Gewinn – mit Treuhänder abstimmen.
A13: 2. AHV/IV/EO-BEITRÄGE (Selbständige)
A14: Eigenkapital per 1.1. (Kontenplan 2800) | C14: =SUMIF(Kontenplan!$A$5:$A$90,2800,Kontenplan!$G$5:$G$90) -> 122000
A15: − Zinsabzug auf Eigenkapital | C15: =-MAX(0,ROUND(C14*Einstellungen!$B$22,0)) -> -1830
A16: → Beitragspflichtiges Einkommen (vereinfacht) | C16: =MAX(0,C11+C15) -> 0
A17: Beitragssatz (sinkende Skala linear angenähert) | C17: =IF(C16>=Einstellungen!$B$16,Einstellungen!$B$15,IF(C16<Einstellungen!$B$17,0,Einstellungen!$B$18+(Einstellungen!$B$15-Einstellungen!$B$18)*(C16-Einstellungen!$B$17)/(Einstellungen!$B$16-Einstellungen!$B$17))) -> 0
A18: AHV/IV/EO-Beitrag | C18: =IF(C16<Einstellungen!$B$17,Einstellungen!$B$19,ROUND(C16*C17,0)) -> 530
A19: + Verwaltungskosten Ausgleichskasse | C19: =ROUND(C18*Einstellungen!$B$20,0) -> 16
A20: + FAK-Beitrag | C20: =ROUND(C16*Einstellungen!$B$21,0) -> 0
A21: → Total Sozialversicherungsbeiträge Inhaber | C21: =C18+C19+C20 -> 546
A22: Bereits bezahlte AHV-Akontozahlungen (Eingabe) | C22: 0
A23: Voraussichtliche Nachzahlung / Guthaben | C23: =C21-C22 -> 546
A25: 3. STEUERBARES EINKOMMEN (Schätzung)
A26: Einkommen aus selbständiger Erwerbstätigkeit | C26: =C11 -> -41356.09
A27: − AHV/IV/EO/FAK-Beiträge (abziehbar) | C27: =-C21 -> -546
A28: Einzahlung Säule 3a geplant (Eingabe) | C28: 0
A29: maximal möglich (20 % des Erwerbseinkommens, max.) | C29: =MAX(0,MIN(ROUND((C11-C21)*0.2,0),Einstellungen!$B$29)) -> 0
A30: − Säule 3a (angerechnet) | C30: =-MIN(C28,C29) -> 0
A31: − BVG-Einkäufe (Eingabe) | C31: 0
A32: − Übrige Abzüge (Krankenkasse, Kinder, Schuldzinsen, Weiterbildung ...) | C32: 0
A33: + Übrige Einkünfte (Partner/in, Vermögensertrag, Nebenerwerb) | C33: 0
A34: → Steuerbares Einkommen (Schätzung) | C34: =MAX(0,C26+C27+C30-C31-C32+C33) -> 0
A36: 4. STEUERN (Schätzung)
A37: Einfache Staatssteuer (steuerb. Eink. × Ø-Satz Einstellungen) | C37: =ROUND(C34*Einstellungen!$B$27,0) -> 0
A38: Staatssteuer Kanton SO (× Steuerfuss Kanton) | C38: =ROUND(C37*Einstellungen!$B$24,0) -> 0
A39: Gemeindesteuer Dornach (× Steuerfuss Gemeinde) | C39: =ROUND(C37*Einstellungen!$B$25,0) -> 0
A40: Kirchensteuer | C40: =ROUND(C37*Einstellungen!$B$26,0) -> 0
A41: Direkte Bundessteuer | C41: =ROUND(C34*Einstellungen!$B$28,0) -> 0
A42: → Total Einkommenssteuern | C42: =SUM(C38:C41) -> 0
A43: Effektive Steuerbelastung auf steuerbarem Einkommen | C43: =IF(C34=0,"",C42/C34)
A45: 5. WAS BLEIBT DIR? / RÜCKSTELLUNGEN
A46: Gewinn (Einkommen) inkl. Privatanteile | C46: =C11 -> -41356.09
A47: − AHV/FAK total | C47: =-C21 -> -546
A48: − Steuern total | C48: =-C42 -> 0
A49: − Säule 3a (Vorsorge, bleibt dein Vermögen) | C49: =C30 -> 0
A50: → Frei verfügbar für Lebenshaltung | C50: =SUM(C46:C49) -> -41902.09
A51: Pro Monat | C51: =C50/12 -> -3491.8408
A52: Bisherige Privatbezüge (Konto 2850, Soll) | C52: =SUMIFS(Journal!$M$5:$M$1504,Journal!$D$5:$D$1504,2850) -> 4000
A53: Empfohlene Rückstellung AHV + Steuern pro Monat | C53: =(C21+C42)/12 -> 45.5

Sheet Stundensatz
A1: Stundensatz-Kalkulation Werkstatt
A2: Welchen Stundensatz brauchst du, damit alle Kosten + dein Lohn gedeckt sind?
A4: 1. VERRECHENBARE STUNDEN
A5: Anzahl produktive Personen in der Werkstatt (inkl. dir) | C5: 2
A6: Wochenstunden pro Person | C6: 42
A7: Ferienwochen pro Jahr | C7: 5
A8: Feiertage pro Jahr | C8: 9
A9: Krankheit / Weiterbildung (Tage) | C9: 6
A10: Anwesenheitsstunden pro Person | C10: =C6*(52-C7)-(C8+C9)*C6/5 -> 1848
A11: Produktivität (verrechenbarer Anteil) | C11: 0.7
A12: → Verrechenbare Stunden total pro Jahr | C12: =ROUND(C5*C10*C11,0) -> 2587
A14: 2. JAHRESKOSTEN
A15: Personalaufwand (aus Buchhaltung) | C15: =-Erfolgsrechnung!C36 -> 5980
A16: Übriger Betriebsaufwand (aus Buchhaltung) | C16: =-Erfolgsrechnung!C49 -> 6926.6
A17: Abschreibungen (aus Buchhaltung) | C17: =-Erfolgsrechnung!C55 -> 33400
A18: Finanzaufwand (aus Buchhaltung) | C18: =-Erfolgsrechnung!C61 -> 85
A19: Ist-Kosten bisher | C19: =SUM(C15:C18) -> 46391.6
A20: Budget-Jahreskosten (Eingabe, leer = hochrechnen)
A21: Monate gebucht bisher | C21: =MAX(1,MAX(Journal!$O$5:$O$1504)) -> 3
A22: Verwendete Jahreskosten | C22: =IF(C20<>"",C20,C19/C21*12) -> 185566.4
A23: Anteil Gemeinkosten, den die Werkstatt tragen soll | C23: 0.8
A24: Gewünschter Unternehmerlohn brutto (inkl. AHV, Vorsorge) | C24: 95000
A25: Gewinnzuschlag / Risiko | C25: 0.05
A26: → Zu deckende Kosten Werkstatt | C26: =(C22*C23+C24)*(1+C25) -> 255625.78
A28: 3. RESULTAT
A29: Kostendeckender Stundensatz exkl. MWST | C29: =IF(C12=0,"",C26/C12) -> 98.811664
A30: Stundensatz inkl. MWST | C30: =IF(C29="","",C29*(1+Einstellungen!$B$10)) -> 106.81541
A31: Aktueller Stundensatz exkl. MWST (Eingabe) | C31: 125
A32: Differenz pro Stunde | C32: =IF(C29="","",C31-C29) -> 26.188336
A33: Auswirkung aufs Jahr (× verrechenbare Stunden) | C33: =IF(C32="","",C32*C12) -> 67749.224
A34: =IF(C32="","",IF(C32>=0,"✓ Dein Stundensatz deckt die Kosten.","⚠ Stundensatz zu tief – Preise oder Produktivität prüfen.")) -> ✓ Dein Stundensatz deckt die Kosten.
A36: Tipp: Mit wenig gebuchten Monaten ist die Hochrechnung ungenau – dann Budget-Jahreskosten (Zeile 20) eintragen.

Sheet Kontoauszug
A1: Kontoauszug / Kassenbuch – alle Buchungen eines Kontos
A2: Konto in C4 eingeben (z.B. 1000 = Kassenbuch, 1020 = Bank).
A4: Konto: | C4: 1020 | D4: =IFERROR(INDEX(Kontenplan!$B$5:$B$90,MATCH(C4,Kontenplan!$A$5:$A$90,0)),"unbekannt") -> Bank | F4: Typ: | G4: =IFERROR(INDEX(Kontenplan!$C$5:$C$90,MATCH(C4,Kontenplan!$A$5:$A$90,0)),"") -> Aktiv | H4: Saldo lt. Kontenplan: | J4: =SUMIF(Kontenplan!$A$5:$A$90,C4,Kontenplan!$K$5:$K$90) -> 35724.7
A5: Zeigt die ersten 500 Buchungen. Automatische MWST- und Abschreibungsbuchungen erscheinen nur im Kontenplan-Saldo.
A6: Nr. | B6: Journalzeile | C6: Datum | D6: Beleg | E6: Text | F6: Gegenkonto | G6: Soll | H6: Haben | I6: Saldo
E7: Eröffnung 1.1. | I7: =SUMIF(Kontenplan!$A$5:$A$90,C4,Kontenplan!$G$5:$G$90) -> 45000
A8: 1 | B8: =IFERROR(MATCH(A8,Journal!$W$5:$W$1504,0),"") -> 5 | C8: =IF($B8="","",INDEX(Journal!$A$5:$A$1504,$B8)) -> 46047 | D8: =IF($B8="","",INDEX(Journal!$B$5:$B$1504,$B8)) -> L-001 | E8: =IF($B8="","",INDEX(Journal!$C$5:$C$1504,$B8)) -> BEISPIEL Lohn Mechaniker Januar (netto) | F8: =IF($B8="","",IF(INDEX(Journal!$D$5:$D$1504,$B8)=$C$4,INDEX(Journal!$E$5:$E$1504,$B8),INDEX(Journal!$D$5:$D$1504,$B8))) -> 5000 | G8: =IF($B8="","",IF(INDEX(Journal!$D$5:$D$1504,$B8)=$C$4,INDEX(Journal!$M$5:$M$1504,$B8),0)) -> 0 | H8: =IF($B8="","",IF(INDEX(Journal!$E$5:$E$1504,$B8)=$C$4,INDEX(Journal!$N$5:$N$1504,$B8),0)) -> 4650 | I8: =IF($B8="","",IF(OR($G$4="Aktiv",$G$4="Aufwand"),I7+G8-H8,I7+H8-G8)) -> 40350
A9: 2 | B9: =IFERROR(MATCH(A9,Journal!$W$5:$W$1504,0),"") -> 8 | C9: =IF($B9="","",INDEX(Journal!$A$5:$A$1504,$B9)) -> 46053 | D9: =IF($B9="","",INDEX(Journal!$B$5:$B$1504,$B9)) -> B-001 | E9: =IF($B9="","",INDEX(Journal!$C$5:$C$1504,$B9)) -> BEISPIEL Miete Werkstatt Januar | F9: =IF($B9="","",IF(INDEX(Journal!$D$5:$D$1504,$B9)=$C$4,INDEX(Journal!$E$5:$E$1504,$B9),INDEX(Journal!$D$5:$D$1504,$B9))) -> 6000 | G9: =IF($B9="","",IF(INDEX(Journal!$D$5:$D$1504,$B9)=$C$4,INDEX(Journal!$M$5:$M$1504,$B9),0)) -> 0 | H9: =IF($B9="","",IF(INDEX(Journal!$E$5:$E$1504,$B9)=$C$4,INDEX(Journal!$N$5:$N$1504,$B9),0)) -> 3500 | I9: =IF($B9="","",IF(OR($G$4="Aktiv",$G$4="Aufwand"),I8+G9-H9,I8+H9-G9)) -> 36850
A10: 3 | B10: =IFERROR(MATCH(A10,Journal!$W$5:$W$1504,0),"") -> 9 | C10: =IF($B10="","",INDEX(Journal!$A$5:$A$1504,$B10)) -> 46056 | D10: =IF($B10="","",INDEX(Journal!$B$5:$B$1504,$B10)) -> B-002 | E10: =IF($B10="","",INDEX(Journal!$C$5:$C$1504,$B10)) -> BEISPIEL Strom Januar | F10: =IF($B10="","",IF(INDEX(Journal!$D$5:$D$1504,$B10)=$C$4,INDEX(Journal!$E$5:$E$1504,$B10),INDEX(Journal!$D$5:$D$1504,$B10))) -> 6400 | G10: =IF($B10="","",IF(INDEX(Journal!$D$5:$D$1504,$B10)=$C$4,INDEX(Journal!$M$5:$M$1504,$B10),0)) -> 0 | H10: =IF($B10="","",IF(INDEX(Journal!$E$5:$E$1504,$B10)=$C$4,INDEX(Journal!$N$5:$N$1504,$B10),0)) -> 486.6 | I10: =IF($B10="","",IF(OR($G$4="Aktiv",$G$4="Aufwand"),I9+G10-H10,I9+H10-G10)) -> 36363.4
A11: 4 | B11: =IFERROR(MATCH(A11,Journal!$W$5:$W$1504,0),"") -> 10 | C11: =IF($B11="","",INDEX(Journal!$A$5:$A$1504,$B11)) -> 46058 | D11: =IF($B11="","",INDEX(Journal!$B$5:$B$1504,$B11)) -> B-003 | E11: =IF($B11="","",INDEX(Journal!$C$5:$C$1504,$B11)) -> BEISPIEL Zahlungseingang R-001 | F11: =IF($B11="","",IF(INDEX(Journal!$D$5:$D$1504,$B11)=$C$4,INDEX(Journal!$E$5:$E$1504,$B11),INDEX(Journal!$D$5:$D$1504,$B11))) -> 1100 | G11: =IF($B11="","",IF(INDEX(Journal!$D$5:$D$1504,$B11)=$C$4,INDEX(Journal!$M$5:$M$1504,$B11),0)) -> 2486.3 | H11: =IF($B11="","",IF(INDEX(Journal!$E$5:$E$1504,$B11)=$C$4,INDEX(Journal!$N$5:$N$1504,$B11),0)) -> 0 | I11: =IF($B11="","",IF(OR($G$4="Aktiv",$G$4="Aufwand"),I10+G11-H11,I10+H11-G11)) -> 38849.7
A12: 5 | B12: =IFERROR(MATCH(A12,Journal!$W$5:$W$1504,0),"") -> 11 | C12: =IF($B12="","",INDEX(Journal!$A$5:$A$1504,$B12)) -> 46063 | D12: =IF($B12="","",INDEX(Journal!$B$5:$B$1504,$B12)) -> F-001 | E12: =IF($B12="","",INDEX(Journal!$C$5:$C$1504,$B12)) -> BEISPIEL Ankauf Occasion VW Golf von Privat | F12: =IF($B12="","",IF(INDEX(Journal!$D$5:$D$1504,$B12)=$C$4,INDEX(Journal!$E$5:$E$1504,$B12),INDEX(Journal!$D$5:$D$1504,$B12))) -> 4200 | G12: =IF($B12="","",IF(INDEX(Journal!$D$5:$D$1504,$B12)=$C$4,INDEX(Journal!$M$5:$M$1504,$B12),0)) -> 0 | H12: =IF($B12="","",IF(INDEX(Journal!$E$5:$E$1504,$B12)=$C$4,INDEX(Journal!$N$5:$N$1504,$B12),0)) -> 12000 | I12: =IF($B12="","",IF(OR($G$4="Aktiv",$G$4="Aufwand"),I11+G12-H12,I11+H12-G12)) -> 26849.7
A13: 6 | B13: =IFERROR(MATCH(A13,Journal!$W$5:$W$1504,0),"") -> 12 | C13: =IF($B13="","",INDEX(Journal!$A$5:$A$1504,$B13)) -> 46073 | D13: =IF($B13="","",INDEX(Journal!$B$5:$B$1504,$B13)) -> B-004 | E13: =IF($B13="","",INDEX(Journal!$C$5:$C$1504,$B13)) -> BEISPIEL Betriebshaftpflicht 2026 | F13: =IF($B13="","",IF(INDEX(Journal!$D$5:$D$1504,$B13)=$C$4,INDEX(Journal!$E$5:$E$1504,$B13),INDEX(Journal!$D$5:$D$1504,$B13))) -> 6300 | G13: =IF($B13="","",IF(INDEX(Journal!$D$5:$D$1504,$B13)=$C$4,INDEX(Journal!$M$5:$M$1504,$B13),0)) -> 0 | H13: =IF($B13="","",IF(INDEX(Journal!$E$5:$E$1504,$B13)=$C$4,INDEX(Journal!$N$5:$N$1504,$B13),0)) -> 2400 | I13: =IF($B13="","",IF(OR($G$4="Aktiv",$G$4="Aufwand"),I12+G13-H13,I12+H13-G13)) -> 24449.7
A14: 7 | B14: =IFERROR(MATCH(A14,Journal!$W$5:$W$1504,0),"") -> 13 | C14: =IF($B14="","",INDEX(Journal!$A$5:$A$1504,$B14)) -> 46099 | D14: =IF($B14="","",INDEX(Journal!$B$5:$B$1504,$B14)) -> F-002 | E14: =IF($B14="","",INDEX(Journal!$C$5:$C$1504,$B14)) -> BEISPIEL Verkauf Occasion VW Golf | F14: =IF($B14="","",IF(INDEX(Journal!$D$5:$D$1504,$B14)=$C$4,INDEX(Journal!$E$5:$E$1504,$B14),INDEX(Journal!$D$5:$D$1504,$B14))) -> 3400 | G14: =IF($B14="","",IF(INDEX(Journal!$D$5:$D$1504,$B14)=$C$4,INDEX(Journal!$M$5:$M$1504,$B14),0)) -> 15900 | H14: =IF($B14="","",IF(INDEX(Journal!$E$5:$E$1504,$B14)=$C$4,INDEX(Journal!$N$5:$N$1504,$B14),0)) -> 0 | I14: =IF($B14="","",IF(OR($G$4="Aktiv",$G$4="Aufwand"),I13+G14-H14,I13+H14-G14)) -> 40349.7
A15: 8 | B15: =IFERROR(MATCH(A15,Journal!$W$5:$W$1504,0),"") -> 14 | C15: =IF($B15="","",INDEX(Journal!$A$5:$A$1504,$B15)) -> 46101 | D15: =IF($B15="","",INDEX(Journal!$B$5:$B$1504,$B15)) -> B-005 | E15: =IF($B15="","",INDEX(Journal!$C$5:$C$1504,$B15)) -> BEISPIEL Inserate AutoScout | F15: =IF($B15="","",IF(INDEX(Journal!$D$5:$D$1504,$B15)=$C$4,INDEX(Journal!$E$5:$E$1504,$B15),INDEX(Journal!$D$5:$D$1504,$B15))) -> 6600 | G15: =IF($B15="","",IF(INDEX(Journal!$D$5:$D$1504,$B15)=$C$4,INDEX(Journal!$M$5:$M$1504,$B15),0)) -> 0 | H15: =IF($B15="","",IF(INDEX(Journal!$E$5:$E$1504,$B15)=$C$4,INDEX(Journal!$N$5:$N$1504,$B15),0)) -> 540 | I15: =IF($B15="","",IF(OR($G$4="Aktiv",$G$4="Aufwand"),I14+G15-H15,I14+H15-G15)) -> 39809.7
A16: 9 | B16: =IFERROR(MATCH(A16,Journal!$W$5:$W$1504,0),"") -> 15 | C16: =IF($B16="","",INDEX(Journal!$A$5:$A$1504,$B16)) -> 46112 | D16: =IF($B16="","",INDEX(Journal!$B$5:$B$1504,$B16)) -> P-001 | E16: =IF($B16="","",INDEX(Journal!$C$5:$C$1504,$B16)) -> BEISPIEL Privatbezug Inhaber | F16: =IF($B16="","",IF(INDEX(Journal!$D$5:$D$1504,$B16)=$C$4,INDEX(Journal!$E$5:$E$1504,$B16),INDEX(Journal!$D$5:$D$1504,$B16))) -> 2850 | G16: =IF($B16="","",IF(INDEX(Journal!$D$5:$D$1504,$B16)=$C$4,INDEX(Journal!$M$5:$M$1504,$B16),0)) -> 0 | H16: =IF($B16="","",IF(INDEX(Journal!$E$5:$E$1504,$B16)=$C$4,INDEX(Journal!$N$5:$N$1504,$B16),0)) -> 4000 | I16: =IF($B16="","",IF(OR($G$4="Aktiv",$G$4="Aufwand"),I15+G16-H16,I15+H16-G16)) -> 35809.7
A17: 10 | B17: =IFERROR(MATCH(A17,Journal!$W$5:$W$1504,0),"") -> 16 | C17: =IF($B17="","",INDEX(Journal!$A$5:$A$1504,$B17)) -> 46112 | D17: =IF($B17="","",INDEX(Journal!$B$5:$B$1504,$B17)) -> B-006 | E17: =IF($B17="","",INDEX(Journal!$C$5:$C$1504,$B17)) -> BEISPIEL Bankspesen/Zins Q1 | F17: =IF($B17="","",IF(INDEX(Journal!$D$5:$D$1504,$B17)=$C$4,INDEX(Journal!$E$5:$E$1504,$B17),INDEX(Journal!$D$5:$D$1504,$B17))) -> 6900 | G17: =IF($B17="","",IF(INDEX(Journal!$D$5:$D$1504,$B17)=$C$4,INDEX(Journal!$M$5:$M$1504,$B17),0)) -> 0 | H17: =IF($B17="","",IF(INDEX(Journal!$E$5:$E$1504,$B17)=$C$4,INDEX(Journal!$N$5:$N$1504,$B17),0)) -> 85 | I17: =IF($B17="","",IF(OR($G$4="Aktiv",$G$4="Aufwand"),I16+G17-H17,I16+H17-G17)) -> 35724.7
A18: 11 | B18: =IFERROR(MATCH(A18,Journal!$W$5:$W$1504,0),"") | C18: =IF($B18="","",INDEX(Journal!$A$5:$A$1504,$B18)) | D18: =IF($B18="","",INDEX(Journal!$B$5:$B$1504,$B18)) | E18: =IF($B18="","",INDEX(Journal!$C$5:$C$1504,$B18)) | F18: =IF($B18="","",IF(INDEX(Journal!$D$5:$D$1504,$B18)=$C$4,INDEX(Journal!$E$5:$E$1504,$B18),INDEX(Journal!$D$5:$D$1504,$B18))) | G18: =IF($B18="","",IF(INDEX(Journal!$D$5:$D$1504,$B18)=$C$4,INDEX(Journal!$M$5:$M$1504,$B18),0)) | H18: =IF($B18="","",IF(INDEX(Journal!$E$5:$E$1504,$B18)=$C$4,INDEX(Journal!$N$5:$N$1504,$B18),0)) | I18: =IF($B18="","",IF(OR($G$4="Aktiv",$G$4="Aufwand"),I17+G18-H18,I17+H18-G18))
A19: 12 | B19: =IFERROR(MATCH(A19,Journal!$W$5:$W$1504,0),"") | C19: =IF($B19="","",INDEX(Journal!$A$5:$A$1504,$B19)) | D19: =IF($B19="","",INDEX(Journal!$B$5:$B$1504,$B19)) | E19: =IF($B19="","",INDEX(Journal!$C$5:$C$1504,$B19)) | F19: =IF($B19="","",IF(INDEX(Journal!$D$5:$D$1504,$B19)=$C$4,INDEX(Journal!$E$5:$E$1504,$B19),INDEX(Journal!$D$5:$D$1504,$B19))) | G19: =IF($B19="","",IF(INDEX(Journal!$D$5:$D$1504,$B19)=$C$4,INDEX(Journal!$M$5:$M$1504,$B19),0)) | H19: =IF($B19="","",IF(INDEX(Journal!$E$5:$E$1504,$B19)=$C$4,INDEX(Journal!$N$5:$N$1504,$B19),0)) | I19: =IF($B19="","",IF(OR($G$4="Aktiv",$G$4="Aufwand"),I18+G19-H19,I18+H19-G19))
... A507: 500 | B507: =IFERROR(MATCH(A507,Journal!$W$5:$W$1504,0),"") | C507: =IF($B507="","",INDEX(Journal!$A$5:$A$1504,$B507)) | D507: =IF($B507="","",INDEX(Journal!$B$5:$B$1504,$B507)) | E507: =IF($B507="","",INDEX(Journal!$C$5:$C$1504,$B507)) | F507: =IF($B507="","",IF(INDEX(Journal!$D$5:$D$1504,$B507)=$C$4,INDEX(Journal!$E$5:$E$1504,$B507),INDEX(Journal!$D$5:$D$1504,$B507))) | G507: =IF($B507="","",IF(INDEX(Journal!$D$5:$D$1504,$B507)=$C$4,INDEX(Journal!$M$5:$M$1504,$B507),0)) | H507: =IF($B507="","",IF(INDEX(Journal!$E$5:$E$1504,$B507)=$C$4,INDEX(Journal!$N$5:$N$1504,$B507),0)) | I507: =IF($B507="","",IF(OR($G$4="Aktiv",$G$4="Aufwand"),I506+G507-H507,I506+H507-G507))

Sheet Fristen
A1: Termine & Pflichten Einzelfirma
A2: Daten werden aus dem Geschäftsjahr berechnet. Erledigt-Spalte abhaken.
A4: Fällig | B4: Was | C4: Hinweis | D4: Erledigt (x)
A5: =DATE(Einstellungen!$B$7,6,30)+60 -> 46263 | B5: MWST-Abrechnung 1. Semester (Saldomethode) | C5: Online im ESTV-Portal; Zahlung gleichzeitig fällig | E5: =IF(OR(A5="",D5<>""),"",IF(A5<TODAY(),"überfällig!",IF(A5-TODAY()<=30,"in "&(A5-TODAY())&" Tagen",""))) -> überfällig!
A6: =DATE(Einstellungen!$B$7,12,31)+60 -> 46447 | B6: MWST-Abrechnung 2. Semester (Saldomethode) | C6: Frist kann online verlängert werden | E6: =IF(OR(A6="",D6<>""),"",IF(A6<TODAY(),"überfällig!",IF(A6-TODAY()<=30,"in "&(A6-TODAY())&" Tagen","")))
A7: =DATE(Einstellungen!$B$7,3,31)+60 -> 46172 | B7: MWST Q1 (nur effektive Methode) | E7: =IF(OR(A7="",D7<>""),"",IF(A7<TODAY(),"überfällig!",IF(A7-TODAY()<=30,"in "&(A7-TODAY())&" Tagen",""))) -> überfällig!
A8: =DATE(Einstellungen!$B$7,6,30)+60 -> 46263 | B8: MWST Q2 (nur effektive Methode) | E8: =IF(OR(A8="",D8<>""),"",IF(A8<TODAY(),"überfällig!",IF(A8-TODAY()<=30,"in "&(A8-TODAY())&" Tagen",""))) -> überfällig!
A9: =DATE(Einstellungen!$B$7,9,30)+60 -> 46355 | B9: MWST Q3 (nur effektive Methode) | E9: =IF(OR(A9="",D9<>""),"",IF(A9<TODAY(),"überfällig!",IF(A9-TODAY()<=30,"in "&(A9-TODAY())&" Tagen","")))
A10: =DATE(Einstellungen!$B$7,12,31)+60 -> 46447 | B10: MWST Q4 (nur effektive Methode) | E10: =IF(OR(A10="",D10<>""),"",IF(A10<TODAY(),"überfällig!",IF(A10-TODAY()<=30,"in "&(A10-TODAY())&" Tagen","")))
A11: =DATE(Einstellungen!$B$7,3,31) -> 46112 | B11: AHV-Akontobeiträge Selbständige (Quartal) | C11: Gemäss Akontoverfügung der Ausgleichskasse SO (meist quartalsweise) | E11: =IF(OR(A11="",D11<>""),"",IF(A11<TODAY(),"überfällig!",IF(A11-TODAY()<=30,"in "&(A11-TODAY())&" Tagen",""))) -> überfällig!
A12: =DATE(Einstellungen!$B$7,6,30) -> 46203 | B12: AHV-Akontobeiträge (Quartal) | E12: =IF(OR(A12="",D12<>""),"",IF(A12<TODAY(),"überfällig!",IF(A12-TODAY()<=30,"in "&(A12-TODAY())&" Tagen",""))) -> überfällig!
A13: =DATE(Einstellungen!$B$7,9,30) -> 46295 | B13: AHV-Akontobeiträge (Quartal) | E13: =IF(OR(A13="",D13<>""),"",IF(A13<TODAY(),"überfällig!",IF(A13-TODAY()<=30,"in "&(A13-TODAY())&" Tagen",""))) -> überfällig!
A14: =DATE(Einstellungen!$B$7,12,31) -> 46387 | B14: AHV-Akontobeiträge (Quartal) | C14: Bei stark höherem Gewinn: AK informieren (sonst Verzugszins) | E14: =IF(OR(A14="",D14<>""),"",IF(A14<TODAY(),"überfällig!",IF(A14-TODAY()<=30,"in "&(A14-TODAY())&" Tagen","")))
A15: =DATE(Einstellungen!$B$7,12,31) -> 46387 | B15: Säule 3a einzahlen | C15: Muss bis 31.12. auf dem 3a-Konto sein | E15: =IF(OR(A15="",D15<>""),"",IF(A15<TODAY(),"überfällig!",IF(A15-TODAY()<=30,"in "&(A15-TODAY())&" Tagen","")))
A16: =DATE(Einstellungen!$B$7,12,31) -> 46387 | B16: Inventur Lager & Fahrzeuge | C16: Blatt Lager / Fahrzeuge; Bestandesänderung buchen | E16: =IF(OR(A16="",D16<>""),"",IF(A16<TODAY(),"überfällig!",IF(A16-TODAY()<=30,"in "&(A16-TODAY())&" Tagen","")))
A17: =DATE(Einstellungen!$B$7,12,31) -> 46387 | B17: Debitoren & Kreditoren abstimmen, Abgrenzungen buchen | C17: Offene Rechnungen per 31.12. vollständig? | E17: =IF(OR(A17="",D17<>""),"",IF(A17<TODAY(),"überfällig!",IF(A17-TODAY()<=30,"in "&(A17-TODAY())&" Tagen","")))
A18: =DATE(Einstellungen!$B$7+1,1,30) -> 46417 | B18: AHV-Lohnbescheinigung Mitarbeitende | C18: An die Ausgleichskasse | E18: =IF(OR(A18="",D18<>""),"",IF(A18<TODAY(),"überfällig!",IF(A18-TODAY()<=30,"in "&(A18-TODAY())&" Tagen","")))
A19: =DATE(Einstellungen!$B$7+1,1,31) -> 46418 | B19: Lohnausweise an Mitarbeitende | E19: =IF(OR(A19="",D19<>""),"",IF(A19<TODAY(),"überfällig!",IF(A19-TODAY()<=30,"in "&(A19-TODAY())&" Tagen","")))
A20: =DATE(Einstellungen!$B$7+1,3,31) -> 46477 | B20: Jahresabschluss (Bilanz, ER) fertigstellen | C20: Für Steuererklärung; Frist gemäss Steuerformular SO | E20: =IF(OR(A20="",D20<>""),"",IF(A20<TODAY(),"überfällig!",IF(A20-TODAY()<=30,"in "&(A20-TODAY())&" Tagen","")))
B21: Steuererklärung Kanton SO | C21: Frist steht auf dem Formular; Verlängerung online möglich | E21: =IF(OR(A21="",D21<>""),"",IF(A21<TODAY(),"überfällig!",IF(A21-TODAY()<=30,"in "&(A21-TODAY())&" Tagen","")))
B22: Belege aufbewahren | C22: 10 Jahre (Art. 958f OR) – auch digital zulässig | E22: =IF(OR(A22="",D22<>""),"",IF(A22<TODAY(),"überfällig!",IF(A22-TODAY()<=30,"in "&(A22-TODAY())&" Tagen","")))
